Workbook
Name DATEBISS: [1]!ALL_DATA[DATA_OSS]
Name NAN: [1]PARAMETRI!$A$36
Name SERIEBISS: [1]!ALL_DATA[#Headers]

Sheet 1AT
B2: Template corresponding to Part 1 of the project Fiscal Drag in Europe
B3: Yellow cells have to be filled by you (remember to rename the sheets as well)
B4: Remaing cells are automatically calculated using information from yellow cells (grey cells remain empty)
B8: Country | C8: AT | D8: Austria | E8: Updated: 21/01/2025
C10: Personal Income Tax Revenue | P10: Tac Base (il_fiscaldrag_all) | W10: TTB | AD10: TTB by income source | AH10: Decomposition of TTB in pp | AQ10: Decomposition of fiscal drag in percentage | AZ10: OECD estimates | CC10: Ratio8020 all income | CK10: Gini tax base (from Table 3.1) | CS10: Ratio8020 tax base | DA10: Kakwani (from Table 3.2) | DD10: Share taxpayers | EA10: 2023 Personal Income Tax Revenue | EN10: 2023 Tax Base (il_fiscaldrag_all) | EV10: 2023 TTB | EZ10: 2023 Share taxpayers | FB10: 2023 TTB by income source
B11: Decile | C11: Original | D11: Incomes grow 1% | E11: Incomes & all parameters grow 1% | F11: Incomes & (only) tax brackets grow 1% | G11: Incomes & (only) tax brackets and tax benefit #1 grow 1% | H11: Incomes & tax brackets and tax benefit #1 & 2 grow 1% | I11: Incomes & tax brackets and tax benefit #1 & 2 & 3 grow 1% | K11: Labor income grows 1% | L11: Benefits and pensions grow 1% | M11: Self-employment income grows 1% | N11: Capital income grows 1% | O11: Share of total tax liability | P11: Original | Q11: Incomes grow 1% | R11: Relative change (should be 1%) | S11: Labor income grows 1% | T11: Benefits and pensions grow 1% | U11: Self-employment income grows 1% | V11: Capital income grows 1% | W11: Incomes grow 1% | X11: Incomes & all parameters grow 1% | Y11: Incomes & tax brackets grow 1% | Z11: Incomes & tax brackets and tax benefit #1 grow 1% | AA11: Incomes & tax brackets and tax benefit #1 & 2 grow 1% | AB11: Incomes & tax brackets and tax benefit #1 & 2 & 3 grow 1% | AC11: Incomes & tax brackets and tax benefit #1 & 2 & 3 & 4 grow 1% | AD11: Labor income grows 1% | AE11: Benefits and pensions grow 1% | AF11: Self-employment income grows 1% | AG11: Capital income grows 1% | AH11: Proportional effect | AI11: Residual | AJ11: By bracket progressivity | AK11: By tax benefit 1 | AL11: By tax benefit 2 | AM11: By tax benefit 3 | AN11: By tax benefit 4 | AO11: By other tax benefits | AP11: By other tax benefits and residual | AQ11: Proportional effect | AR11: Residual | AS11: By bracket progressivity | AT11: By tax benefit 1 | AU11: By tax benefit 2 | AV11: By tax benefit 3 | AX11: By other tax benefits | AY11: By other tax benefits and residual | AZ11: TTB all incomes | BA11: TTB earnings | BB11: TTB self-empl. | BC11: TTB capital | BD11: Diff. all incomes (pp) | BE11: Diff. earnings (pp) | BF11: Diff. self-empl. (pp) | BG11: Diff. capital (pp) | BH11: Labour income | BI11: Pension and benefits | BJ11: Self-employment income | BK11: Capital income | BL11: Share of labour income | BM11: Share of pension and benefits | BN11: Share of self-employment income | BO11: Share of capital income | BP11: TTB without pensions | BQ11: Diff TTB TTB_nopens | BR11: Diff TTB_nopens TTB_OECD | BS11: Share of total tax base | CC11: Ratio8020 all income preincrease pretax | CD11: Ratio8020 all income preincrease posttax | CE11: Ratio8020 all income postincrease pretax | CF11: Ratio8020 all income postincrease posttax | CG11: Ratio8020 allinc increase preincrease | CH11: Ratio8020 allinc increase postincrease | CI11: Diff Ratio8020 change allinc (pp) | CJ11: Diff Ratio8020 allinc postax (pp) | CK11: Gini tax base preincrease pretax | CL11: Gini tax base preincrease posttax | CM11: Gini tax base postincrease pretax | CN11: Gini tax base postincrease posttax | CO11: Gini taxinc reduction preincrease | CP11: Gini taxinc reduction postincrease | CQ11: Diff Gini reduction taxinc (pp) | CR11: Diff Gini tax base posttax | CS11: Ratio8020 tax base preincrease pretax | CT11: Ratio8020 tax base preincrease posttax | CU11: Ratio8020 tax base postincrease pretax | CV11: Ratio8020 tax base postincrease posttax | CW11: Ratio8020 taxinc decrease preincrease | CX11: Ratio8020 taxinc decrease postincrease | CY11: Diff Ratio8020 change taxinc (pp) | CZ11: Diff Ratio8020 taxinc postax (pp) | DA11: kawani taxinc preincrease | DB11: kawani taxinc postincrease | DC11: Diff kakwani taxinc | DD11: Share with zero tax liability (right axis) | DE11: Share with non-zero tax liability | EA11: 2023 Original | EB11: 2023 Incomes grow 1% | EC11: 2023 Incomes & all parameters grow 1% | ED11: 2023 Incomes & (only) tax brackets grow 1% | EE11: 2023 Incomes & (only) tax brackets and tax benefit #1 grow 1% | EF11: 2023 Incomes & tax brackets and tax benefit #1 & 2 grow 1% | EG11: 2023 Incomes & tax brackets and tax benefit #1 & 2 & 3 grow 1% | EI11: 2023 Labor income grows 1% | EJ11: 2023 Benefits and pensions grow 1% | EK11: 2023 Self-employment income grows 1% | EL11: 2023 Capital income grows 1% | EM11: Share of total tax liability | EN11: 2023 Original | EO11: 2023 Incomes grow 1% | EP11: 2023 Relative change (should be 1%) | EQ11: 2023 Labor income grows 1% | ER11: 2023 Benefits and pensions grow 1% | ES11: 2023 Self-employment income grows 1% | ET11: 2023 Capital income grows 1% | EU11: 2023 Share of total tax base | EV11: 2023 TTB Incomes grow 1% | EW11: 2023 Incomes & all parameters grow 1% | EX11: 2023 Diff residual (pp) | EY11: 2023 TTB change | EZ11: 2023 Share with zero tax liability (right axis) | FA11: 2023 Share with non-zero tax liability | FB11: 2023 TTB Labor income grows 1% | FC11: 2023 TTB Benefits and pensions grow 1% | FD11: 2023 TTB Self-employment income grows 1% | FE11: 2023 TTB Capital income grows 1% | FF11: 2023 TTB change Labor | FG11: 2023 TTB change Benefits and pensions | FH11: 2023 TTB change Self-employment income | FI11: 2023 TTB change Capital
B12: 1 | C12: {='[2]2. Distributional by deciles o'!$B$82:$G$92} -> -1.5702069e+08 | D12: -1.5615024e+08 | E12: -1.5859483e+08 | F12: -1.5688058e+08 | G12: -1.5718223e+08 | H12: -1.5725564e+08 | K12: - | L12: - | M12: - | N12: - | O12: =C12/C$22*100 -> -0.44734438 | P12: {='[2]2. Distributional by deciles o'!$B$100:$C$110} -> 3.2257884e+09 | Q12: 3.2580468e+09 | R12: =(Q12/P12-1)*100 -> 1.0000148 | S12: - | T12: - | U12: - | V12: - | W12: =IF(D12<>0,((D12-$C12)/ABS($C12)) / ($Q12/$P12-1),0) -> 0.55434579 | X12: =IF(E12<>0,((E12-$C12)/ABS($C12)) / ($Q12/$P12-1),0) -> -1.0024891 | Y12: =IF(F12<>0,MAX(((F12-$C12)/ABS($C12)) / ($Q12/$P12-1),0),0) -> 0.089229866 | Z12: =IF(G12<>0,MAX(((G12-$C12)/ABS($C12)) / ($Q12/$P12-1),0),0) -> 0 | AA12: =IF(H12<>0,MAX(((H12-$C12)/ABS($C12)) / ($Q12/$P12-1),0),0) -> 0 | AB12: =IF(I12<>0,MAX(((I12-$C12)/ABS($C12)) / ($Q12/$P12-1),0),AA12) -> 0 | AC12: =IF(J12<>0,MAX(((J12-$C12)/ABS($C12)) / ($Q12/$P12-1),0),AB12) -> 0 | AD12: - | AE12: - | AF12: - | AG12: - | AH12: =MIN(W12,1) -> 0.55434579 | AI12: =IF(W12>1,MAX(W12-SUM(AH12,AJ12:AO12),0),0) -> 0 | AJ12: =IF(W12>1,MIN($W12-Y12,W12-AH12),0) -> 0 | AK12: =IF(W12>1,MAX(MIN(Y12-Z12,W12-AH12-AJ12),0),0) -> 0 | AL12: =IF(W12>1,MAX(MIN(Z12-AA12,W12-AH12-AJ12-AK12),0),0) -> 0 | AM12: =IF(I12<>0,IF(W12>1,MAX(MIN(AA12-AB12,W12-AH12-AJ12-AK12-AL12),0),0),0) -> 0 | AN12: =IF(J12<>0,IF(W12>1,MAX(MIN(AB12-AC12,W12-AH12-AJ12-AK12-AL12-AM12),0),0),0) -> 0 | AO12: =IF(W12>1,MAX(0,MIN(W12-AH12-AJ12-AK12-AL12-AM12,W12-AH12-AJ12-AK12-AL12-AM12-X12+1)),0) -> 0 | AP12: =AI12+AO12 -> 0 | AQ12: - | AR12: =AI12/($W12-1)*100 -> 0 | AS12: =AJ12/($W12-1)*100 -> 0 | AT12: =AK12/($W12-1)*100 -> 0 | AU12: =AL12/($W12-1)*100 -> 0 | AV12: =AM12/($W12-1)*100 -> 0 | AW12: =AN12/($W12-1)*100 -> 0 | AX12: =AO12/($W12-1)*100 -> 0 | AY12: =AP12/($W12-1)*100 -> 0 | AZ12: - | BA12: - | BB12: - | BC12: - | BD12: - | BE12: - | BF12: - | BG12: - | BH12: {='[2]2. Distributional by deciles o'!$B$118:$B$128} -> 1.870474e+09 | BI12: {='[2]2. Distributional by deciles o'!$B$136:$B$146} -> 9.4220443e+08 | BJ12: {='[2]2. Distributional by deciles o'!$B$154:$B$164} -> 2.7071392e+08 | BK12: {='[2]2. Distributional by deciles o'!$B$172:$B$182} -> 1.4239577e+08 | BL12: =BH12/SUM($BH12:$BK12) -> 0.57985023 | BM12: =BI12/SUM($BH12:$BK12) -> 0.29208504 | BN12: =BJ12/SUM($BH12:$BK12) -> 0.083921793 | BO12: =BK12/SUM($BH12:$BK12) -> 0.044142939 | BP12: - | BQ12: - | BR12: - | BS12: =P12/P$22*100 -> 1.2309505 | CC12: - | CD12: - | CE12: - | CF12: - | CG12: - | CH12: - | CI12: - | CK12: - | CL12: - | CM12: - | CN12: - | CO12: - | CP12: - | CQ12: - | CS12: - | CT12: - | CU12: - | CV12: - | CW12: - | CX12: - | CY12: - | DA12: - | DB12: - | DC12: - | DD12: =(1-DE12)*100 -> 17.164668 | DE12: {='[2]2. Distributional by deciles o'!$M$10:$M$20} -> 0.82835332 | EA12: {='[3]2. Distributional by deciles o'!$B$82:$H$92} -> -2.9403817e+08 | EB12: -2.9336951e+08 | EC12: -2.969286e+08 | ED12: -2.9435276e+08 | EE12: -2.9546264e+08 | EF12: -2.9553617e+08 | EG12: -2.9350792e+08 | EI12: - | EJ12: - | EK12: - | EL12: - | EM12: =EA12/EA$22*100 -> -0.74784531 | EN12: {='[3]2. Distributional by deciles o'!$B$100:$C$110} -> 3.7517771e+09 | EO12: 3.7892945e+09 | EP12: =(EO12/EN12-1)*100 -> 0.99999005 | EQ12: - | ER12: - | ES12: - | ET12: - | EU12: =EN12/EN$22*100 -> 1.2228736 | EV12: =((EB12-$EA12)/ABS($EA12)) / ($EO12/$EN12-1) -> 0.22740673 | EW12: =IF(EC12<>0,((EC12-$EA12)/ABS($EA12)) / ($EO12/$EN12-1),0) -> -0.9830214 | EY12: =EV12-W12 -> -0.32693906 | EZ12: =(1-FA12)*100 -> 15.580745 | FA12: {='[3]2. Distributional by deciles o'!$L$10:$L$20} -> 0.84419255 | FB12: - | FC12: - | FD12: - | FE12: - | FF12: - | FG12: - | FH12: - | FI12: -
B13: 2 | C13: 26423258 | D13: 36796737 | E13: 26681814 | F13: 29820420 | G13: 28947728 | H13: 28621805 | K13: - | L13: - | M13: - | N13: - | O13: =C13/C$22*100 -> 0.075278591 | P13: 1.037195e+10 | Q13: 1.047567e+10 | R13: =(Q13/P13-1)*100 -> 0.99999922 | S13: - | T13: - | U13: - | V13: - | W13: =IF(D13<>0,((D13-$C13)/ABS($C13)) / ($Q13/$P13-1),0) -> 39.258922 | X13: =IF(E13<>0,((E13-$C13)/ABS($C13)) / ($Q13/$P13-1),0) -> 0.97851517 | Y13: =IF(F13<>0,MAX(((F13-$C13)/ABS($C13)) / ($Q13/$P13-1),0),0) -> 12.856719 | Z13: =IF(G13<>0,MAX(((G13-$C13)/ABS($C13)) / ($Q13/$P13-1),0),0) -> 9.5539736 | AA13: =IF(H13<>0,MAX(((H13-$C13)/ABS($C13)) / ($Q13/$P13-1),0),0) -> 8.3205042 | AB13: =IF(I13<>0,MAX(((I13-$C13)/ABS($C13)) / ($Q13/$P13-1),0),AA13) -> 8.3205042 | AC13: =IF(J13<>0,MAX(((J13-$C13)/ABS($C13)) / ($Q13/$P13-1),0),AB13) -> 8.3205042 | AD13: - | AE13: - | AF13: - | AG13: - | AH13: =MIN(W13,1) -> 1 | AI13: =IF(W13>1,MAX(W13-SUM(AH13,AJ13:AO13),0),0) -> 0 | AJ13: =IF(W13>1,MIN($W13-Y13,W13-AH13),0) -> 26.402203 | AK13: =IF(W13>1,MAX(MIN(Y13-Z13,W13-AH13-AJ13),0),0) -> 3.3027456 | AL13: =IF(W13>1,MAX(MIN(Z13-AA13,W13-AH13-AJ13-AK13),0),0) -> 1.2334693 | AM13: =IF(I13<>0,IF(W13>1,MAX(MIN(AA13-AB13,W13-AH13-AJ13-AK13-AL13),0),0),0) -> 0 | AN13: =IF(J13<>0,IF(W13>1,MAX(MIN(AB13-AC13,W13-AH13-AJ13-AK13-AL13-AM13),0),0),0) -> 0 | AO13: =IF(W13>1,MAX(0,MIN(W13-AH13-AJ13-AK13-AL13-AM13,W13-AH13-AJ13-AK13-AL13-AM13-X13+1)),0) -> 7.3205042 | AP13: =AI13+AO13 -> 7.3205042 | AQ13: - | AR13: =AI13/($W13-1)*100 -> 0 | AS13: =AJ13/($W13-1)*100 -> 69.00927 | AT13: =AK13/($W13-1)*100 -> 8.6326153 | AU13: =AL13/($W13-1)*100 -> 3.2240044 | AV13: =AM13/($W13-1)*100 -> 0 | AW13: =AN13/($W13-1)*100 -> 0 | AX13: =AO13/($W13-1)*100 -> 19.13411 | AY13: =AP13/($W13-1)*100 -> 19.13411 | AZ13: - | BA13: - | BB13: - | BC13: - | BD13: - | BE13: - | BF13: - | BG13: - | BH13: 4.2957874e+09 | BI13: 5.1463495e+09 | BJ13: 7.4251444e+08 | BK13: 1.8730013e+08 | BL13: =BH13/SUM($BH13:$BK13) -> 0.41417349 | BM13: =BI13/SUM($BH13:$BK13) -> 0.49617948 | BN13: =BJ13/SUM($BH13:$BK13) -> 0.071588692 | BO13: =BK13/SUM($BH13:$BK13) -> 0.018058331 | BP13: - | BQ13: - | BR13: - | BS13: =P13/P$22*100 -> 3.9579029 | CC13: - | CD13: - | CE13: - | CF13: - | CG13: - | CH13: - | CI13: - | CK13: - | CL13: - | CM13: - | CN13: - | CO13: - | CP13: - | CQ13: - | CS13: - | CT13: - | CU13: - | CV13: - | CW13: - | CX13: - | CY13: - | DA13: - | DB13: - | DC13: - | DD13: =(1-DE13)*100 -> 14.776201 | DE13: 0.85223799 | EA13: -1.701921e+08 | EB13: -1.5746408e+08 | EC13: -1.7187851e+08 | ED13: -1.6574578e+08 | EE13: -1.6658925e+08 | EF13: -1.7613939e+08 | EG13: -1.654674e+08 | EI13: - | EJ13: - | EK13: - | EL13: - | EM13: =EA13/EA$22*100 -> -0.43286001 | EN13: 1.2216853e+10 | EO13: 1.2339022e+10 | EP13: =(EO13/EN13-1)*100 -> 1.0000017 | EQ13: - | ER13: - | ES13: - | ET13: - | EU13: =EN13/EN$22*100 -> 3.9820242 | EV13: =((EB13-$EA13)/ABS($EA13)) / ($EO13/$EN13-1) -> 7.4786083 | EW13: =IF(EC13<>0,((EC13-$EA13)/ABS($EA13)) / ($EO13/$EN13-1),0) -> -0.9908824 | EY13: =EV13-W13 -> -31.780314 | EZ13: =(1-FA13)*100 -> 0.47940527 | FA13: 0.99520595 | FB13: - | FC13: - | FD13: - | FE13: - | FF13: - | FG13: - | FH13: - | FI13: -
B14: 3 | C14: 5.3322438e+08 | D14: 5.5899296e+08 | E14: 5.3855277e+08 | F14: 5.4434209e+08 | G14: 5.4169153e+08 | H14: 5.4083676e+08 | K14: - | L14: - | M14: - | N14: - | O14: =C14/C$22*100 -> 1.5191306 | P14: 1.4137687e+10 | Q14: 1.4279066e+10 | R14: =(Q14/P14-1)*100 -> 1.0000148 | S14: - | T14: - | U14: - | V14: - | W14: =IF(D14<>0,((D14-$C14)/ABS($C14)) / ($Q14/$P14-1),0) -> 4.8325244 | X14: =IF(E14<>0,((E14-$C14)/ABS($C14)) / ($Q14/$P14-1),0) -> 0.99926321 | Y14: =IF(F14<>0,MAX(((F14-$C14)/ABS($C14)) / ($Q14/$P14-1),0),0) -> 2.0849665 | Z14: =IF(G14<>0,MAX(((G14-$C14)/ABS($C14)) / ($Q14/$P14-1),0),0) -> 1.5878912 | AA14: =IF(H14<>0,MAX(((H14-$C14)/ABS($C14)) / ($Q14/$P14-1),0),0) -> 1.4275914 | AB14: =IF(I14<>0,MAX(((I14-$C14)/ABS($C14)) / ($Q14/$P14-1),0),AA14) -> 1.4275914 | AC14: =IF(J14<>0,MAX(((J14-$C14)/ABS($C14)) / ($Q14/$P14-1),0),AB14) -> 1.4275914 | AD14: - | AE14: - | AF14: - | AG14: - | AH14: =MIN(W14,1) -> 1 | AI14: =IF(W14>1,MAX(W14-SUM(AH14,AJ14:AO14),0),0) -> 8.8817842e-16 | AJ14: =IF(W14>1,MIN($W14-Y14,W14-AH14),0) -> 2.7475579 | AK14: =IF(W14>1,MAX(MIN(Y14-Z14,W14-AH14-AJ14),0),0) -> 0.49707531 | AL14: =IF(W14>1,MAX(MIN(Z14-AA14,W14-AH14-AJ14-AK14),0),0) -> 0.16029971 | AM14: =IF(I14<>0,IF(W14>1,MAX(MIN(AA14-AB14,W14-AH14-AJ14-AK14-AL14),0),0),0) -> 0 | AN14: =IF(J14<>0,IF(W14>1,MAX(MIN(AB14-AC14,W14-AH14-AJ14-AK14-AL14-AM14),0),0),0) -> 0 | AO14: =IF(W14>1,MAX(0,MIN(W14-AH14-AJ14-AK14-AL14-AM14,W14-AH14-AJ14-AK14-AL14-AM14-X14+1)),0) -> 0.42759144 | AP14: =AI14+AO14 -> 0.42759144 | AQ14: - | AR14: =AI14/($W14-1)*100 -> 2.3174762e-14 | AS14: =AJ14/($W14-1)*100 -> 71.690553 | AT14: =AK14/($W14-1)*100 -> 12.969919 | AU14: =AL14/($W14-1)*100 -> 4.1826143 | AV14: =AM14/($W14-1)*100 -> 0 | AW14: =AN14/($W14-1)*100 -> 0 | AX14: =AO14/($W14-1)*100 -> 11.156914 | AY14: =AP14/($W14-1)*100 -> 11.156914 | AZ14: - | BA14: - | BB14: - | BC14: - | BD14: - | BE14: - | BF14: - | BG14: - | BH14: 8.0552016e+09 | BI14: 5.1172231e+09 | BJ14: 7.0143093e+08 | BK14: 2.6383252e+08 | BL14: =BH14/SUM($BH14:$BK14) -> 0.56976795 | BM14: =BI14/SUM($BH14:$BK14) -> 0.36195615 | BN14: =BJ14/SUM($BH14:$BK14) -> 0.049614259 | BO14: =BK14/SUM($BH14:$BK14) -> 0.018661645 | BP14: - | BQ14: - | BR14: - | BS14: =P14/P$22*100 -> 5.3948959 | CC14: - | CD14: - | CE14: - | CF14: - | CG14: - | CH14: - | CI14: - | CK14: - | CL14: - | CM14: - | CN14: - | CO14: - | CP14: - | CQ14: - | CS14: - | CT14: - | CU14: - | CV14: - | CW14: - | CX14: - | CY14: - | DA14: - | DB14: - | DC14: - | DD14: =(1-DE14)*100 -> 0 | DE14: 1 | EA14: 4.1304447e+08 | EB14: 4.4320389e+08 | EC14: 4.1713549e+08 | ED14: 4.2758131e+08 | EE14: 4.2450556e+08 | EF14: 4.2217075e+08 | EG14: 4.2837965e+08 | EI14: - | EJ14: - | EK14: - | EL14: - | EM14: =EA14/EA$22*100 -> 1.0505213 | EN14: 1.6653157e+10 | EO14: 1.681969e+10 | EP14: =(EO14/EN14-1)*100 -> 1.0000042 | EQ14: - | ER14: - | ES14: - | ET14: - | EU14: =EN14/EN$22*100 -> 5.4280161 | EV14: =((EB14-$EA14)/ABS($EA14)) / ($EO14/$EN14-1) -> 7.3017073 | EW14: =IF(EC14<>0,((EC14-$EA14)/ABS($EA14)) / ($EO14/$EN14-1),0) -> 0.9904509 | EY14: =EV14-W14 -> 2.469183 | EZ14: =(1-FA14)*100 -> 0 | FA14: 1 | FB14: - | FC14: - | FD14: - | FE14: - | FF14: - | FG14: - | FH14: - | FI14: -
B15: 4 | C15: 1.0527935e+09 | D15: 1.0894493e+09 | E15: 1.0633183e+09 | F15: 1.0694568e+09 | G15: 1.0667283e+09 | H15: 1.0656674e+09 | K15: - | L15: - | M15: - | N15: - | O15: =C15/C$22*100 -> 2.999358 | P15: 1.7268543e+10 | Q15: 1.7441226e+10 | R15: =(Q15/P15-1)*100 -> 0.9999898 | S15: - | T15: - | U15: - | V15: - | W15: =IF(D15<>0,((D15-$C15)/ABS($C15)) / ($Q15/$P15-1),0) -> 3.4818014 | X15: =IF(E15<>0,((E15-$C15)/ABS($C15)) / ($Q15/$P15-1),0) -> 0.9997108 | Y15: =IF(F15<>0,MAX(((F15-$C15)/ABS($C15)) / ($Q15/$P15-1),0),0) -> 1.5827847 | Z15: =IF(G15<>0,MAX(((G15-$C15)/ABS($C15)) / ($Q15/$P15-1),0),0) -> 1.323612 | AA15: =IF(H15<>0,MAX(((H15-$C15)/ABS($C15)) / ($Q15/$P15-1),0),0) -> 1.222841 | AB15: =IF(I15<>0,MAX(((I15-$C15)/ABS($C15)) / ($Q15/$P15-1),0),AA15) -> 1.222841 | AC15: =IF(J15<>0,MAX(((J15-$C15)/ABS($C15)) / ($Q15/$P15-1),0),AB15) -> 1.222841 | AD15: - | AE15: - | AF15: - | AG15: - | AH15: =MIN(W15,1) -> 1 | AI15: =IF(W15>1,MAX(W15-SUM(AH15,AJ15:AO15),0),0) -> 0 | AJ15: =IF(W15>1,MIN($W15-Y15,W15-AH15),0) -> 1.8990167 | AK15: =IF(W15>1,MAX(MIN(Y15-Z15,W15-AH15-AJ15),0),0) -> 0.25917271 | AL15: =IF(W15>1,MAX(MIN(Z15-AA15,W15-AH15-AJ15-AK15),0),0) -> 0.10077101 | AM15: =IF(I15<>0,IF(W15>1,MAX(MIN(AA15-AB15,W15-AH15-AJ15-AK15-AL15),0),0),0) -> 0 | AN15: =IF(J15<>0,IF(W15>1,MAX(MIN(AB15-AC15,W15-AH15-AJ15-AK15-AL15-AM15),0),0),0) -> 0 | AO15: =IF(W15>1,MAX(0,MIN(W15-AH15-AJ15-AK15-AL15-AM15,W15-AH15-AJ15-AK15-AL15-AM15-X15+1)),0) -> 0.22284095 | AP15: =AI15+AO15 -> 0.22284095 | AQ15: - | AR15: =AI15/($W15-1)*100 -> 0 | AS15: =AJ15/($W15-1)*100 -> 76.517675 | AT15: =AK15/($W15-1)*100 -> 10.442927 | AU15: =AL15/($W15-1)*100 -> 4.0603978 | AV15: =AM15/($W15-1)*100 -> 0 | AW15: =AN15/($W15-1)*100 -> 0 | AX15: =AO15/($W15-1)*100 -> 8.9790004 | AY15: =AP15/($W15-1)*100 -> 8.9790004 | AZ15: - | BA15: - | BB15: - | BC15: - | BD15: - | BE15: - | BF15: - | BG15: - | BH15: 9.624971e+09 | BI15: 6.2099844e+09 | BJ15: 1.1355477e+09 | BK15: 2.9803988e+08 | BL15: =BH15/SUM($BH15:$BK15) -> 0.55737019 | BM15: =BI15/SUM($BH15:$BK15) -> 0.35961253 | BN15: =BJ15/SUM($BH15:$BK15) -> 0.065758162 | BO15: =BK15/SUM($BH15:$BK15) -> 0.017259122 | BP15: - | BQ15: - | BR15: - | BS15: =P15/P$22*100 -> 6.5896205 | CC15: - | CD15: - | CE15: - | CF15: - | CG15: - | CH15: - | CI15: - | CK15: - | CL15: - | CM15: - | CN15: - | CO15: - | CP15: - | CQ15: - | CS15: - | CT15: - | CU15: - | CV15: - | CW15: - | CX15: - | CY15: - | DA15: - | DB15: - | DC15: - | DD15: =(1-DE15)*100 -> 0 | DE15: 1 | EA15: 1.0158175e+09 | EB15: 1.0591615e+09 | EC15: 1.0259197e+09 | ED15: 1.0372811e+09 | EE15: 1.0336835e+09 | EF15: 1.0319477e+09 | EG15: 1.0389004e+09 | EI15: - | EJ15: - | EK15: - | EL15: - | EM15: =EA15/EA$22*100 -> 2.5835909 | EN15: 2.0117273e+10 | EO15: 2.0318446e+10 | EP15: =(EO15/EN15-1)*100 -> 0.99999901 | EQ15: - | ER15: - | ES15: - | ET15: - | EU15: =EN15/EN$22*100 -> 6.5571279 | EV15: =((EB15-$EA15)/ABS($EA15)) / ($EO15/$EN15-1) -> 4.2669179 | EW15: =IF(EC15<>0,((EC15-$EA15)/ABS($EA15)) / ($EO15/$EN15-1),0) -> 0.99449848 | EY15: =EV15-W15 -> 0.78511653 | EZ15: =(1-FA15)*100 -> 0.44253136 | FA15: 0.99557469 | FB15: - | FC15: - | FD15: - | FE15: - | FF15: - | FG15: - | FH15: - | FI15: -
B16: 5 | C16: 1.6073541e+09 | D16: 1.6523379e+09 | E16: 1.6234242e+09 | F16: 1.6293881e+09 | G16: 1.6268633e+09 | H16: 1.6256115e+09 | K16: - | L16: - | M16: - | N16: - | O16: =C16/C$22*100 -> 4.5792745 | P16: 2.0486801e+10 | Q16: 2.0691668e+10 | R16: =(Q16/P16-1)*100 -> 0.99999151 | S16: - | T16: - | U16: - | V16: - | W16: =IF(D16<>0,((D16-$C16)/ABS($C16)) / ($Q16/$P16-1),0) -> 2.7986468 | X16: =IF(E16<>0,((E16-$C16)/ABS($C16)) / ($Q16/$P16-1),0) -> 0.9997939 | Y16: =IF(F16<>0,MAX(((F16-$C16)/ABS($C16)) / ($Q16/$P16-1),0),0) -> 1.3708365 | Z16: =IF(G16<>0,MAX(((G16-$C16)/ABS($C16)) / ($Q16/$P16-1),0),0) -> 1.2137538 | AA16: =IF(H16<>0,MAX(((H16-$C16)/ABS($C16)) / ($Q16/$P16-1),0),0) -> 1.1358749 | AB16: =IF(I16<>0,MAX(((I16-$C16)/ABS($C16)) / ($Q16/$P16-1),0),AA16) -> 1.1358749 | AC16: =IF(J16<>0,MAX(((J16-$C16)/ABS($C16)) / ($Q16/$P16-1),0),AB16) -> 1.1358749 | AD16: - | AE16: - | AF16: - | AG16: - | AH16: =MIN(W16,1) -> 1 | AI16: =IF(W16>1,MAX(W16-SUM(AH16,AJ16:AO16),0),0) -> 0 | AJ16: =IF(W16>1,MIN($W16-Y16,W16-AH16),0) -> 1.4278102 | AK16: =IF(W16>1,MAX(MIN(Y16-Z16,W16-AH16-AJ16),0),0) -> 0.15708273 | AL16: =IF(W16>1,MAX(MIN(Z16-AA16,W16-AH16-AJ16-AK16),0),0) -> 0.077878924 | AM16: =IF(I16<>0,IF(W16>1,MAX(MIN(AA16-AB16,W16-AH16-AJ16-AK16-AL16),0),0),0) -> 0 | AN16: =IF(J16<>0,IF(W16>1,MAX(MIN(AB16-AC16,W16-AH16-AJ16-AK16-AL16-AM16),0),0),0) -> 0 | AO16: =IF(W16>1,MAX(0,MIN(W16-AH16-AJ16-AK16-AL16-AM16,W16-AH16-AJ16-AK16-AL16-AM16-X16+1)),0) -> 0.1358749 | AP16: =AI16+AO16 -> 0.1358749 | AQ16: - | AR16: =AI16/($W16-1)*100 -> 0 | AS16: =AJ16/($W16-1)*100 -> 79.382469 | AT16: =AK16/($W16-1)*100 -> 8.733384 | AU16: =AL16/($W16-1)*100 -> 4.329862 | AV16: =AM16/($W16-1)*100 -> 0 | AW16: =AN16/($W16-1)*100 -> 0 | AX16: =AO16/($W16-1)*100 -> 7.5542845 | AY16: =AP16/($W16-1)*100 -> 7.5542845 | AZ16: - | BA16: - | BB16: - | BC16: - | BD16: - | BE16: - | BF16: - | BG16: - | BH16: 1.2203248e+10 | BI16: 6.5263722e+09 | BJ16: 1.4978513e+09 | BK16: 2.59329e+08 | BL16: =BH16/SUM($BH16:$BK16) -> 0.59566392 | BM16: =BI16/SUM($BH16:$BK16) -> 0.31856474 | BN16: =BJ16/SUM($BH16:$BK16) -> 0.073112996 | BO16: =BK16/SUM($BH16:$BK16) -> 0.012658346 | BP16: - | BQ16: - | BR16: - | BS16: =P16/P$22*100 -> 7.8176977 | CC16: - | CD16: - | CE16: - | CF16: - | CG16: - | CH16: - | CI16: - | CK16: - | CL16: - | CM16: - | CN16: - | CO16: - | CP16: - | CQ16: - | CS16: - | CT16: - | CU16: - | CV16: - | CW16: - | CX16: - | CY16: - | DA16: - | DB16: - | DC16: - | DD16: =(1-DE16)*100 -> 0 | DE16: 1 | EA16: 1.6605394e+09 | EB16: 1.7130265e+09 | EC16: 1.6771342e+09 | ED16: 1.6876355e+09 | EE16: 1.6841252e+09 | EF16: 1.6827738e+09 | EG16: 1.6905705e+09 | EI16: - | EJ16: - | EK16: - | EL16: - | EM16: =EA16/EA$22*100 -> 4.2233517 | EN16: 2.3902111e+10 | EO16: 2.414113e+10 | EP16: =(EO16/EN16-1)*100 -> 0.99999055 | EQ16: - | ER16: - | ES16: - | ET16: - | EU16: =EN16/EN$22*100 -> 7.7907775 | EV16: =((EB16-$EA16)/ABS($EA16)) / ($EO16/$EN16-1) -> 3.1608782 | EW16: =IF(EC16<>0,((EC16-$EA16)/ABS($EA16)) / ($EO16/$EN16-1),0) -> 0.99937028 | EY16: =EV16-W16 -> 0.36223142 | EZ16: =(1-FA16)*100 -> 0 | FA16: 1 | FB16: - | FC16: - | FD16: - | FE16: - | FF16: - | FG16: - | FH16: - | FI16: -
B17: 6 | C17: 2.2988003e+09 | D17: 2.3539824e+09 | E17: 2.3217857e+09 | F17: 2.3271094e+09 | G17: 2.3247358e+09 | H17: 2.323221e+09 | K17: - | L17: - | M17: - | N17: - | O17: =C17/C$22*100 -> 6.5491714 | P17: 2.3783687e+10 | Q17: 2.4021525e+10 | R17: =(Q17/P17-1)*100 -> 1.000003 | S17: - | T17: - | U17: - | V17: - | W17: =IF(D17<>0,((D17-$C17)/ABS($C17)) / ($Q17/$P17-1),0) -> 2.4004676 | X17: =IF(E17<>0,((E17-$C17)/ABS($C17)) / ($Q17/$P17-1),0) -> 0.99988319 | Y17: =IF(F17<>0,MAX(((F17-$C17)/ABS($C17)) / ($Q17/$P17-1),0),0) -> 1.2314699 | Z17: =IF(G17<>0,MAX(((G17-$C17)/ABS($C17)) / ($Q17/$P17-1),0),0) -> 1.1282165 | AA17: =IF(H17<>0,MAX(((H17-$C17)/ABS($C17)) / ($Q17/$P17-1),0),0) -> 1.0623216 | AB17: =IF(I17<>0,MAX(((I17-$C17)/ABS($C17)) / ($Q17/$P17-1),0),AA17) -> 1.0623216 | AC17: =IF(J17<>0,MAX(((J17-$C17)/ABS($C17)) / ($Q17/$P17-1),0),AB17) -> 1.0623216 | AD17: - | AE17: - | AF17: - | AG17: - | AH17: =MIN(W17,1) -> 1 | AI17: =IF(W17>1,MAX(W17-SUM(AH17,AJ17:AO17),0),0) -> 0 | AJ17: =IF(W17>1,MIN($W17-Y17,W17-AH17),0) -> 1.1689978 | AK17: =IF(W17>1,MAX(MIN(Y17-Z17,W17-AH17-AJ17),0),0) -> 0.1032534 | AL17: =IF(W17>1,MAX(MIN(Z17-AA17,W17-AH17-AJ17-AK17),0),0) -> 0.065894872 | AM17: =IF(I17<>0,IF(W17>1,MAX(MIN(AA17-AB17,W17-AH17-AJ17-AK17-AL17),0),0),0) -> 0 | AN17: =IF(J17<>0,IF(W17>1,MAX(MIN(AB17-AC17,W17-AH17-AJ17-AK17-AL17-AM17),0),0),0) -> 0 | AO17: =IF(W17>1,MAX(0,MIN(W17-AH17-AJ17-AK17-AL17-AM17,W17-AH17-AJ17-AK17-AL17-AM17-X17+1)),0) -> 0.062321591 | AP17: =AI17+AO17 -> 0.062321591 | AQ17: - | AR17: =AI17/($W17-1)*100 -> 0 | AS17: =AJ17/($W17-1)*100 -> 83.471959 | AT17: =AK17/($W17-1)*100 -> 7.3727799 | AU17: =AL17/($W17-1)*100 -> 4.7052049 | AV17: =AM17/($W17-1)*100 -> 0 | AW17: =AN17/($W17-1)*100 -> 0 | AX17: =AO17/($W17-1)*100 -> 4.4500558 | AY17: =AP17/($W17-1)*100 -> 4.4500558 | AZ17: - | BA17: - | BB17: - | BC17: - | BD17: - | BE17: - | BF17: - | BG17: - | BH17: 1.5285858e+10 | BI17: 7.1799095e+09 | BJ17: 1.0490029e+09 | BK17: 2.6891777e+08 | BL17: =BH17/SUM($BH17:$BK17) -> 0.64270343 | BM17: =BI17/SUM($BH17:$BK17) -> 0.30188377 | BN17: =BJ17/SUM($BH17:$BK17) -> 0.044105982 | BO17: =BK17/SUM($BH17:$BK17) -> 0.011306815 | BP17: - | BQ17: - | BR17: - | BS17: =P17/P$22*100 -> 9.0757787 | CC17: - | CD17: - | CE17: - | CF17: - | CG17: - | CH17: - | CI17: - | CK17: - | CL17: - | CM17: - | CN17: - | CO17: - | CP17: - | CQ17: - | CS17: - | CT17: - | CU17: - | CV17: - | CW17: - | CX17: - | CY17: - | DA17: - | DB17: - | DC17: - | DD17: =(1-DE17)*100 -> 0 | DE17: 1 | EA17: 2.4529152e+09 | EB17: 2.516948e+09 | EC17: 2.477414e+09 | ED17: 2.4862696e+09 | EE17: 2.4831993e+09 | EF17: 2.4815872e+09 | EG17: 2.4916474e+09 | EI17: - | EJ17: - | EK17: - | EL17: - | EM17: =EA17/EA$22*100 -> 6.2386496 | EN17: 2.7869725e+10 | EO17: 2.8148421e+10 | EP17: =(EO17/EN17-1)*100 -> 0.99999756 | EQ17: - | ER17: - | ES17: - | ET17: - | EU17: =EN17/EN$22*100 -> 9.084002 | EV17: =((EB17-$EA17)/ABS($EA17)) / ($EO17/$EN17-1) -> 2.6104847 | EW17: =IF(EC17<>0,((EC17-$EA17)/ABS($EA17)) / ($EO17/$EN17-1),0) -> 0.99876708 | EY17: =EV17-W17 -> 0.21001711 | EZ17: =(1-FA17)*100 -> 0 | FA17: 1 | FB17: - | FC17: - | FD17: - | FE17: - | FF17: - | FG17: - | FH17: - | FI17: -
B18: 7 | C18: 3.100813e+09 | D18: 3.1677522e+09 | E18: 3.1318189e+09 | F18: 3.1368552e+09 | G18: 3.1349101e+09 | H18: 3.1332674e+09 | K18: - | L18: - | M18: - | N18: - | O18: =C18/C$22*100 -> 8.8340671 | P18: 2.8139029e+10 | Q18: 2.842042e+10 | R18: =(Q18/P18-1)*100 -> 1.0000026 | S18: - | T18: - | U18: - | V18: - | W18: =IF(D18<>0,((D18-$C18)/ABS($C18)) / ($Q18/$P18-1),0) -> 2.1587569 | X18: =IF(E18<>0,((E18-$C18)/ABS($C18)) / ($Q18/$P18-1),0) -> 0.99992322 | Y18: =IF(F18<>0,MAX(((F18-$C18)/ABS($C18)) / ($Q18/$P18-1),0),0) -> 1.1623434 | Z18: =IF(G18<>0,MAX(((G18-$C18)/ABS($C18)) / ($Q18/$P18-1),0),0) -> 1.0996146 | AA18: =IF(H18<>0,MAX(((H18-$C18)/ABS($C18)) / ($Q18/$P18-1),0),0) -> 1.0466367 | AB18: =IF(I18<>0,MAX(((I18-$C18)/ABS($C18)) / ($Q18/$P18-1),0),AA18) -> 1.0466367 | AC18: =IF(J18<>0,MAX(((J18-$C18)/ABS($C18)) / ($Q18/$P18-1),0),AB18) -> 1.0466367 | AD18: - | AE18: - | AF18: - | AG18: - | AH18: =MIN(W18,1) -> 1 | AI18: =IF(W18>1,MAX(W18-SUM(AH18,AJ18:AO18),0),0) -> 4.4408921e-16 | AJ18: =IF(W18>1,MIN($W18-Y18,W18-AH18),0) -> 0.99641346 | AK18: =IF(W18>1,MAX(MIN(Y18-Z18,W18-AH18-AJ18),0),0) -> 0.062728784 | AL18: =IF(W18>1,MAX(MIN(Z18-AA18,W18-AH18-AJ18-AK18),0),0) -> 0.052977961 | AM18: =IF(I18<>0,IF(W18>1,MAX(MIN(AA18-AB18,W18-AH18-AJ18-AK18-AL18),0),0),0) -> 0 | AN18: =IF(J18<>0,IF(W18>1,MAX(MIN(AB18-AC18,W18-AH18-AJ18-AK18-AL18-AM18),0),0),0) -> 0 | AO18: =IF(W18>1,MAX(0,MIN(W18-AH18-AJ18-AK18-AL18-AM18,W18-AH18-AJ18-AK18-AL18-AM18-X18+1)),0) -> 0.046636679 | AP18: =AI18+AO18 -> 0.046636679 | AQ18: - | AR18: =AI18/($W18-1)*100 -> 3.8324623e-14 | AS18: =AJ18/($W18-1)*100 -> 85.989863 | AT18: =AK18/($W18-1)*100 -> 5.4134551 | AU18: =AL18/($W18-1)*100 -> 4.5719652 | AV18: =AM18/($W18-1)*100 -> 0 | AW18: =AN18/($W18-1)*100 -> 0 | AX18: =AO18/($W18-1)*100 -> 4.0247165 | AY18: =AP18/($W18-1)*100 -> 4.0247165 | AZ18: - | BA18: - | BB18: - | BC18: - | BD18: - | BE18: - | BF18: - | BG18: - | BH18: 1.8210682e+10 | BI18: 7.8274543e+09 | BJ18: 1.722736e+09 | BK18: 3.7816061e+08 | BL18: =BH18/SUM($BH18:$BK18) -> 0.64716801 | BM18: =BI18/SUM($BH18:$BK18) -> 0.2781707 | BN18: =BJ18/SUM($BH18:$BK18) -> 0.06122229 | BO18: =BK18/SUM($BH18:$BK18) -> 0.013439005 | BP18: - | BQ18: - | BR18: - | BS18: =P18/P$22*100 -> 10.737763 | CC18: - | CD18: - | CE18: - | CF18: - | CG18: - | CH18: - | CI18: - | CK18: - | CL18: - | CM18: - | CN18: - | CO18: - | CP18: - | CQ18: - | CS18: - | CT18: - | CU18: - | CV18: - | CW18: - | CX18: - | CY18: - | DA18: - | DB18: - | DC18: - | DD18: =(1-DE18)*100 -> 0 | DE18: 1 | EA18: 3.3451474e+09 | EB18: 3.4238435e+09 | EC18: 3.3785449e+09 | ED18: 3.387263e+09 | EE18: 3.3845582e+09 | EF18: 3.3827066e+09 | EG18: 3.3970863e+09 | EI18: - | EJ18: - | EK18: - | EL18: - | EM18: =EA18/EA$22*100 -> 8.5079187 | EN18: 3.2873385e+10 | EO18: 3.3202118e+10 | EP18: =(EO18/EN18-1)*100 -> 0.99999799 | EQ18: - | ER18: - | ES18: - | ET18: - | EU18: =EN18/EN$22*100 -> 10.714921 | EV18: =((EB18-$EA18)/ABS($EA18)) / ($EO18/$EN18-1) -> 2.3525494 | EW18: =IF(EC18<>0,((EC18-$EA18)/ABS($EA18)) / ($EO18/$EN18-1),0) -> 0.99838596 | EY18: =EV18-W18 -> 0.1937925 | EZ18: =(1-FA18)*100 -> 0 | FA18: 1 | FB18: - | FC18: - | FD18: - | FE18: - | FF18: - | FG18: - | FH18: - | FI18: -
B19: 8 | C19: 4.1011487e+09 | D19: 4.1833436e+09 | E19: 4.1421573e+09 | F19: 4.1473937e+09 | G19: 4.1454889e+09 | H19: 4.1434211e+09 | K19: - | L19: - | M19: - | N19: - | O19: =C19/C$22*100 -> 11.683975 | P19: 3.3005546e+10 | Q19: 3.3335601e+10 | R19: =(Q19/P19-1)*100 -> 0.9999993 | S19: - | T19: - | U19: - | V19: - | W19: =IF(D19<>0,((D19-$C19)/ABS($C19)) / ($Q19/$P19-1),0) -> 2.0041936 | X19: =IF(E19<>0,((E19-$C19)/ABS($C19)) / ($Q19/$P19-1),0) -> 0.9999289 | Y19: =IF(F19<>0,MAX(((F19-$C19)/ABS($C19)) / ($Q19/$P19-1),0),0) -> 1.1276118 | Z19: =IF(G19<>0,MAX(((G19-$C19)/ABS($C19)) / ($Q19/$P19-1),0),0) -> 1.0811655 | AA19: =IF(H19<>0,MAX(((H19-$C19)/ABS($C19)) / ($Q19/$P19-1),0),0) -> 1.0307446 | AB19: =IF(I19<>0,MAX(((I19-$C19)/ABS($C19)) / ($Q19/$P19-1),0),AA19) -> 1.0307446 | AC19: =IF(J19<>0,MAX(((J19-$C19)/ABS($C19)) / ($Q19/$P19-1),0),AB19) -> 1.0307446 | AD19: - | AE19: - | AF19: - | AG19: - | AH19: =MIN(W19,1) -> 1 | AI19: =IF(W19>1,MAX(W19-SUM(AH19,AJ19:AO19),0),0) -> 0 | AJ19: =IF(W19>1,MIN($W19-Y19,W19-AH19),0) -> 0.87658178 | AK19: =IF(W19>1,MAX(MIN(Y19-Z19,W19-AH19-AJ19),0),0) -> 0.04644632 | AL19: =IF(W19>1,MAX(MIN(Z19-AA19,W19-AH19-AJ19-AK19),0),0) -> 0.050420902 | AM19: =IF(I19<>0,IF(W19>1,MAX(MIN(AA19-AB19,W19-AH19-AJ19-AK19-AL19),0),0),0) -> 0 | AN19: =IF(J19<>0,IF(W19>1,MAX(MIN(AB19-AC19,W19-AH19-AJ19-AK19-AL19-AM19),0),0),0) -> 0 | AO19: =IF(W19>1,MAX(0,MIN(W19-AH19-AJ19-AK19-AL19-AM19,W19-AH19-AJ19-AK19-AL19-AM19-X19+1)),0) -> 0.030744593 | AP19: =AI19+AO19 -> 0.030744593 | AQ19: - | AR19: =AI19/($W19-1)*100 -> 0 | AS19: =AJ19/($W19-1)*100 -> 87.29211 | AT19: =AK19/($W19-1)*100 -> 4.6252357 | AU19: =AL19/($W19-1)*100 -> 5.0210341 | AV19: =AM19/($W19-1)*100 -> 0 | AW19: =AN19/($W19-1)*100 -> 0 | AX19: =AO19/($W19-1)*100 -> 3.0616201 | AY19: =AP19/($W19-1)*100 -> 3.0616201 | AZ19: - | BA19: - | BB19: - | BC19: - | BD19: - | BE19: - | BF19: - | BG19: - | BH19: 2.460014e+10 | BI19: 6.4777857e+09 | BJ19: 1.5379073e+09 | BK19: 3.8971272e+08 | BL19: =BH19/SUM($BH19:$BK19) -> 0.74533353 | BM19: =BI19/SUM($BH19:$BK19) -> 0.19626355 | BN19: =BJ19/SUM($BH19:$BK19) -> 0.046595423 | BO19: =BK19/SUM($BH19:$BK19) -> 0.011807492 | BP19: - | BQ19: - | BR19: - | BS19: =P19/P$22*100 -> 12.59481 | CC19: - | CD19: - | CE19: - | CF19: - | CG19: - | CH19: - | CI19: - | CK19: - | CL19: - | CM19: - | CN19: - | CO19: - | CP19: - | CQ19: - | CS19: - | CT19: - | CU19: - | CV19: - | CW19: - | CX19: - | CY19: - | DA19: - | DB19: - | DC19: - | DD19: =(1-DE19)*100 -> 0 | DE19: 1 | EA19: 4.5523314e+09 | EB19: 4.6495836e+09 | EC19: 4.5978356e+09 | ED19: 4.6064502e+09 | EE19: 4.6039233e+09 | EF19: 4.6016928e+09 | EG19: 4.624055e+09 | EI19: - | EJ19: - | EK19: - | EL19: - | EM19: =EA19/EA$22*100 -> 11.578224 | EN19: 3.8599376e+10 | EO19: 3.898537e+10 | EP19: =(EO19/EN19-1)*100 -> 1.0000005 | EQ19: - | ER19: - | ES19: - | ET19: - | EU19: =EN19/EN$22*100 -> 12.58128 | EV19: =((EB19-$EA19)/ABS($EA19)) / ($EO19/$EN19-1) -> 2.1363142 | EW19: =IF(EC19<>0,((EC19-$EA19)/ABS($EA19)) / ($EO19/$EN19-1),0) -> 0.99957932 | EY19: =EV19-W19 -> 0.13212061 | EZ19: =(1-FA19)*100 -> 0 | FA19: 1 | FB19: - | FC19: - | FD19: - | FE19: - | FF19: - | FG19: - | FH19: - | FI19: -
B20: 9 | C20: 6.4523723e+09 | D20: 6.5656336e+09 | E20: 6.5168966e+09 | F20: 6.5218994e+09 | G20: 6.5204054e+09 | H20: 6.5182733e+09 | K20: - | L20: - | M20: - | N20: - | O20: =C20/C$22*100 -> 18.382498 | P20: 4.1649731e+10 | Q20: 4.2066227e+10 | R20: =(Q20/P20-1)*100 -> 0.99999696 | S20: - | T20: - | U20: - | V20: - | W20: =IF(D20<>0,((D20-$C20)/ABS($C20)) / ($Q20/$P20-1),0) -> 1.7553482 | X20: =IF(E20<>0,((E20-$C20)/ABS($C20)) / ($Q20/$P20-1),0) -> 1.0000126 | Y20: =IF(F20<>0,MAX(((F20-$C20)/ABS($C20)) / ($Q20/$P20-1),0),0) -> 1.0775471 | Z20: =IF(G20<>0,MAX(((G20-$C20)/ABS($C20)) / ($Q20/$P20-1),0),0) -> 1.0543929 | AA20: =IF(H20<>0,MAX(((H20-$C20)/ABS($C20)) / ($Q20/$P20-1),0),0) -> 1.0213488 | AB20: =IF(I20<>0,MAX(((I20-$C20)/ABS($C20)) / ($Q20/$P20-1),0),AA20) -> 1.0213488 | AC20: =IF(J20<>0,MAX(((J20-$C20)/ABS($C20)) / ($Q20/$P20-1),0),AB20) -> 1.0213488 | AD20: - | AE20: - | AF20: - | AG20: - | AH20: =MIN(W20,1) -> 1 | AI20: =IF(W20>1,MAX(W20-SUM(AH20,AJ20:AO20),0),0) -> 1.2626763e-05 | AJ20: =IF(W20>1,MIN($W20-Y20,W20-AH20),0) -> 0.67780111 | AK20: =IF(W20>1,MAX(MIN(Y20-Z20,W20-AH20-AJ20),0),0) -> 0.023154205 | AL20: =IF(W20>1,MAX(MIN(Z20-AA20,W20-AH20-AJ20-AK20),0),0) -> 0.033044062 | AM20: =IF(I20<>0,IF(W20>1,MAX(MIN(AA20-AB20,W20-AH20-AJ20-AK20-AL20),0),0),0) -> 0 | AN20: =IF(J20<>0,IF(W20>1,MAX(MIN(AB20-AC20,W20-AH20-AJ20-AK20-AL20-AM20),0),0),0) -> 0 | AO20: =IF(W20>1,MAX(0,MIN(W20-AH20-AJ20-AK20-AL20-AM20,W20-AH20-AJ20-AK20-AL20-AM20-X20+1)),0) -> 0.021336167 | AP20: =AI20+AO20 -> 0.021348794 | AQ20: - | AR20: =AI20/($W20-1)*100 -> 0.001671648 | AS20: =AJ20/($W20-1)*100 -> 89.7336 | AT20: =AK20/($W20-1)*100 -> 3.0653685 | AU20: =AL20/($W20-1)*100 -> 4.3746796 | AV20: =AM20/($W20-1)*100 -> 0 | AW20: =AN20/($W20-1)*100 -> 0 | AX20: =AO20/($W20-1)*100 -> 2.8246798 | AY20: =AP20/($W20-1)*100 -> 2.8263515 | AZ20: - | BA20: - | BB20: - | BC20: - | BD20: - | BE20: - | BF20: - | BG20: - | BH20: 2.8983696e+10 | BI20: 8.3325448e+09 | BJ20: 3.0093877e+09 | BK20: 1.3241043e+09 | BL20: =BH20/SUM($BH20:$BK20) -> 0.69589152 | BM20: =BI20/SUM($BH20:$BK20) -> 0.20006239 | BN20: =BJ20/SUM($BH20:$BK20) -> 0.072254672 | BO20: =BK20/SUM($BH20:$BK20) -> 0.031791423 | BP20: - | BQ20: - | BR20: - | BS20: =P20/P$22*100 -> 15.893404 | CC20: - | CD20: - | CE20: - | CF20: - | CG20: - | CH20: - | CI20: - | CK20: - | CL20: - | CM20: - | CN20: - | CO20: - | CP20: - | CQ20: - | CS20: - | CT20: - | CU20: - | CV20: - | CW20: - | CX20: - | CY20: - | DA20: - | DB20: - | DC20: - | DD20: =(1-DE20)*100 -> 0 | DE20: 1 | EA20: 7.3342782e+09 | EB20: 7.4667905e+09 | EC20: 7.407532e+09 | ED20: 7.4150022e+09 | EE20: 7.4128918e+09 | EF20: 7.4106277e+09 | EG20: 7.4240684e+09 | EI20: - | EJ20: - | EK20: - | EL20: - | EM20: =EA20/EA$22*100 -> 18.65372 | EN20: 4.8567602e+10 | EO20: 4.9053279e+10 | EP20: =(EO20/EN20-1)*100 -> 1.0000018 | EQ20: - | ER20: - | ES20: - | ET20: - | EU20: =EN20/EN$22*100 -> 15.830375 | EV20: =((EB20-$EA20)/ABS($EA20)) / ($EO20/$EN20-1) -> 1.8067495 | EW20: =IF(EC20<>0,((EC20-$EA20)/ABS($EA20)) / ($EO20/$EN20-1),0) -> 0.99878541 | EY20: =EV20-W20 -> 0.051401334 | EZ20: =(1-FA20)*100 -> 0 | FA20: 1 | FB20: - | FC20: - | FD20: - | FE20: - | FF20: - | FG20: - | FH20: - | FI20: -
B21: 10 | C21: 1.6084719e+10 | D21: 1.6310707e+10 | E21: 1.6245567e+10 | F21: 1.625108e+10 | G21: 1.624988e+10 | H21: 1.6247567e+10 | K21: - | L21: - | M21: - | N21: - | O21: =C21/C$22*100 -> 45.824591 | P21: 6.9987948e+10 | Q21: 7.0687826e+10 | R21: =(Q21/P21-1)*100 -> 0.99999713 | S21: - | T21: - | U21: - | V21: - | W21: =IF(D21<>0,((D21-$C21)/ABS($C21)) / ($Q21/$P21-1),0) -> 1.4049842 | X21: =IF(E21<>0,((E21-$C21)/ABS($C21)) / ($Q21/$P21-1),0) -> 1.0000029 | Y21: =IF(F21<>0,MAX(((F21-$C21)/ABS($C21)) / ($Q21/$P21-1),0),0) -> 1.0342826 | Z21: =IF(G21<>0,MAX(((G21-$C21)/ABS($C21)) / ($Q21/$P21-1),0),0) -> 1.026818 | AA21: =IF(H21<>0,MAX(((H21-$C21)/ABS($C21)) / ($Q21/$P21-1),0),0) -> 1.012439 | AB21: =IF(I21<>0,MAX(((I21-$C21)/ABS($C21)) / ($Q21/$P21-1),0),AA21) -> 1.012439 | AC21: =IF(J21<>0,MAX(((J21-$C21)/ABS($C21)) / ($Q21/$P21-1),0),AB21) -> 1.012439 | AD21: - | AE21: - | AF21: - | AG21: - | AH21: =MIN(W21,1) -> 1 | AI21: =IF(W21>1,MAX(W21-SUM(AH21,AJ21:AO21),0),0) -> 2.9127634e-06 | AJ21: =IF(W21>1,MIN($W21-Y21,W21-AH21),0) -> 0.37070161 | AK21: =IF(W21>1,MAX(MIN(Y21-Z21,W21-AH21-AJ21),0),0) -> 0.0074645984 | AL21: =IF(W21>1,MAX(MIN(Z21-AA21,W21-AH21-AJ21-AK21),0),0) -> 0.014378954 | AM21: =IF(I21<>0,IF(W21>1,MAX(MIN(AA21-AB21,W21-AH21-AJ21-AK21-AL21),0),0),0) -> 0 | AN21: =IF(J21<>0,IF(W21>1,MAX(MIN(AB21-AC21,W21-AH21-AJ21-AK21-AL21-AM21),0),0),0) -> 0 | AO21: =IF(W21>1,MAX(0,MIN(W21-AH21-AJ21-AK21-AL21-AM21,W21-AH21-AJ21-AK21-AL21-AM21-X21+1)),0) -> 0.012436105 | AP21: =AI21+AO21 -> 0.012439018 | AQ21: - | AR21: =AI21/($W21-1)*100 -> 0.00071922894 | AS21: =AJ21/($W21-1)*100 -> 91.534837 | AT21: =AK21/($W21-1)*100 -> 1.8431827 | AU21: =AL21/($W21-1)*100 -> 3.5504976 | AV21: =AM21/($W21-1)*100 -> 0 | AW21: =AN21/($W21-1)*100 -> 0 | AX21: =AO21/($W21-1)*100 -> 3.0707631 | AY21: =AP21/($W21-1)*100 -> 3.0714823 | AZ21: - | BA21: - | BB21: - | BC21: - | BD21: - | BE21: - | BF21: - | BG21: - | BH21: 4.7316502e+10 | BI21: 9.5777991e+09 | BJ21: 9.5558316e+09 | BK21: 3.5378168e+09 | BL21: =BH21/SUM($BH21:$BK21) -> 0.67606641 | BM21: =BI21/SUM($BH21:$BK21) -> 0.13684926 | BN21: =BJ21/SUM($BH21:$BK21) -> 0.13653539 | BO21: =BK21/SUM($BH21:$BK21) -> 0.050548942 | BP21: - | BQ21: - | BR21: - | BS21: =P21/P$22*100 -> 26.707177 | CC21: - | CD21: - | CE21: - | CF21: - | CG21: - | CH21: - | CI21: - | CK21: - | CL21: - | CM21: - | CN21: - | CO21: - | CP21: - | CQ21: - | CS21: - | CT21: - | CU21: - | CV21: - | CW21: - | CX21: - | CY21: - | DA21: - | DB21: - | DC21: - | DD21: =(1-DE21)*100 -> 0 | DE21: 1 | EA21: 1.9008203e+10 | EB21: 1.9278713e+10 | EC21: 1.9198265e+10 | ED21: 1.9205481e+10 | EE21: 1.9203853e+10 | EF21: 1.9201379e+10 | EG21: 1.9183808e+10 | EI21: - | EJ21: - | EK21: - | EL21: - | EM21: =EA21/EA$22*100 -> 48.344729 | EN21: 8.2248813e+10 | EO21: 8.3071304e+10 | EP21: =(EO21/EN21-1)*100 -> 1.0000026 | EQ21: - | ER21: - | ES21: - | ET21: - | EU21: =EN21/EN$22*100 -> 26.808603 | EV21: =((EB21-$EA21)/ABS($EA21)) / ($EO21/$EN21-1) -> 1.4231201 | EW21: =IF(EC21<>0,((EC21-$EA21)/ABS($EA21)) / ($EO21/$EN21-1),0) -> 0.99989073 | EY21: =EV21-W21 -> 0.018135883 | EZ21: =(1-FA21)*100 -> 0 | FA21: 1 | FB21: - | FC21: - | FD21: - | FE21: - | FF21: - | FG21: - | FH21: - | FI21: -
B22: Total | C22: 3.5100628e+10 | D22: 3.5762845e+10 | E22: 3.5451607e+10 | F22: 3.5500465e+10 | G22: 3.5482469e+10 | H22: 3.5469232e+10 | K22: {='[2]2. Distributional by deciles o'!$H$92:$K$92} -> 3.5516722e+10 | L22: 3.5259487e+10 | M22: 3.5169067e+10 | N22: 3.5120056e+10 | O22: - | P22: 2.6205671e+11 | Q22: 2.6467727e+11 | R22: =(Q22/P22-1)*100 -> 0.99999883 | S22: {='[2]2. Distributional by deciles o'!$H$110:$K$110} -> 2.6376118e+11 | T22: 2.6269008e+11 | U22: 2.6226894e+11 | V22: 2.621272e+11 | W22: =IF(D22<>0,((D22-$C22)/ABS($C22)) / ($Q22/$P22-1),0) -> 1.8866256 | X22: =IF(E22<>0,((E22-$C22)/ABS($C22)) / ($Q22/$P22-1),0) -> 0.99992341 | Y22: =IF(F22<>0,MAX(((F22-$C22)/ABS($C22)) / ($Q22/$P22-1),0),0) -> 1.1391169 | Z22: =IF(G22<>0,MAX(((G22-$C22)/ABS($C22)) / ($Q22/$P22-1),0),0) -> 1.0878457 | AA22: =IF(H22<>0,MAX(((H22-$C22)/ABS($C22)) / ($Q22/$P22-1),0),0) -> 1.0501338 | AB22: =IF(I22<>0,MAX(((I22-$C22)/ABS($C22)) / ($Q22/$P22-1),0),AA22) -> 1.0501338 | AC22: =IF(J22<>0,MAX(((J22-$C22)/ABS($C22)) / ($Q22/$P22-1),0),AB22) -> 1.0501338 | AD22: =(K22/$C22-1) / (S22/$P22-1) -> 1.8225672 | AE22: =(L22/$C22-1) / (T22/$P22-1) -> 1.8725384 | AF22: =(M22/$C22-1) / (U22/$P22-1) -> 2.4075526 | AG22: =(N22/$C22-1) / (V22/$P22-1) -> 2.057656 | AH22: =MIN(W22,1) -> 1 | AI22: =IF(W22>1,MAX(W22-SUM(AH22,AJ22:AO22),0),0) -> 0 | AJ22: =IF(W22>1,MIN($W22-Y22,W22-AH22),0) -> 0.74750879 | AK22: =IF(W22>1,MAX(MIN(Y22-Z22,W22-AH22-AJ22),0),0) -> 0.051271133 | AL22: =IF(W22>1,MAX(MIN(Z22-AA22,W22-AH22-AJ22-AK22),0),0) -> 0.037711883 | AM22: =IF(I22<>0,IF(W22>1,MAX(MIN(AA22-AB22,W22-AH22-AJ22-AK22-AL22),0),0),0) -> 0 | AN22: =IF(J22<>0,IF(W22>1,MAX(MIN(AB22-AC22,W22-AH22-AJ22-AK22-AL22-AM22),0),0),0) -> 0 | AO22: =IF(W22>1,MAX(0,MIN(W22-AH22-AJ22-AK22-AL22-AM22,W22-AH22-AJ22-AK22-AL22-AM22-X22+1)),0) -> 0.050133834 | AP22: =AI22+AO22 -> 0.050133834 | AQ22: - | AR22: =AI22/($W22-1)*100 -> 0 | AS22: =AJ22/($W22-1)*100 -> 84.309404 | AT22: =AK22/($W22-1)*100 -> 5.7827262 | AU22: =AL22/($W22-1)*100 -> 4.2534167 | AV22: =AM22/($W22-1)*100 -> 0 | AW22: =AN22/($W22-1)*100 -> 0 | AX22: =AO22/($W22-1)*100 -> 5.6544534 | AY22: =AP22/($W22-1)*100 -> 5.6544534 | AZ22: 1.97 | BA22: 2 | BB22: 1.85 | BC22: 1.7 | BD22: =W22-AZ22 -> -0.083374358 | BE22: =AD22-BA22 -> -0.17743284 | BF22: =AF22-BB22 -> 0.55755258 | BG22: =AG22-BC22 -> 0.35765597 | BH22: 1.7044656e+11 | BI22: 6.3337627e+10 | BJ22: 2.1222924e+10 | BK22: 7.0496094e+09 | BL22: =BH22/SUM($BH22:$BK22) -> 0.65041858 | BM22: =BI22/SUM($BH22:$BK22) -> 0.24169435 | BN22: =BJ22/SUM($BH22:$BK22) -> 0.080985994 | BO22: =BK22/SUM($BH22:$BK22) -> 0.026901082 | BP22: =(AD22*BL22+AF22*BN22+AG22*BO22)/(BL22+BN22+BO22) -> 1.8933826 | BQ22: =W22-BP22 -> -0.0067569829 | BR22: =BP22-AZ22 -> -0.076617375 | BS22: - | CK22: ='[2]3. Inequality and Poverty'!$B$7 -> 0.35867389 | CL22: ='[2]3. Inequality and Poverty'!$B$8 -> 0.31858803 | CM22: ='[2]3. Inequality and Poverty'!$C$7 -> 0.35867389 | CN22: ='[2]3. Inequality and Poverty'!$C$8 -> 0.3186097 | CO22: =(CK22-CL22)/CK22 -> 0.11176132 | CP22: =(CM22-CN22)/CM22 -> 0.11170087 | CQ22: =(CP22-CO22)*100 -> -0.0060455769 | CR22: =CN22-CL22 -> 2.1676367e-05 | CS22: =(SUM(P20:P21))/(SUM(P12:P13)) -> 8.210018 | CT22: =(SUM(P20:P21)-SUM(C20:C21))/(SUM(P12:P13)-SUM(C12:C13)) -> 6.4902685 | CU22: =(SUM(Q20:Q21))/(SUM(Q12:Q13)) -> 8.2100175 | CV22: =(SUM(Q20:Q21)-SUM(D20:D21))/(SUM(Q12:Q13)-SUM(D12:D13)) -> 6.4879274 | CW22: =(CS22-CT22)/CS22 -> 0.20946964 | CX22: =(CU22-CV22)/CU22 -> 0.20975474 | CY22: =(CX22-CW22)*100 -> 0.028510268 | CZ22: =CV22-CT22 -> -0.0023410741 | DA22: {='[2]3. Inequality and Poverty'!$B$34:$C$34} -> 0.2704958 | DB22: 0.26756475 | DC22: =DB22-DA22 -> -0.0029310443 | DD22: =(1-DE22)*100 -> 3.3936931 | DE22: 0.96606307 | EA22: 3.9318046e+10 | EB22: 4.0100437e+10 | EC22: 3.9710974e+10 | ED22: 3.9792865e+10 | EE22: 3.9768688e+10 | EF22: 3.974321e+10 | EG22: 3.981954e+10 | EI22: {='[3]2. Distributional by deciles o'!$H$92:$K$92} -> 3.981954e+10 | EJ22: 3.9495375e+10 | EK22: 3.9399905e+10 | EL22: 3.9340776e+10 | EM22: - | EN22: 3.0680007e+11 | EO22: 3.0986808e+11 | EP22: =(EO22/EN22-1)*100 -> 0.99999999 | EQ22: {='[3]2. Distributional by deciles o'!$H$110:$K$110} -> 3.0882076e+11 | ER22: 3.0751423e+11 | ES22: 3.0705442e+11 | ET22: 3.0687889e+11 | EU22: - | EV22: =((EB22-$EA22)/ABS($EA22)) / ($EO22/$EN22-1) -> 1.9899028 | EW22: =IF(EC22<>0,((EC22-$EA22)/ABS($EA22)) / ($EO22/$EN22-1),0) -> 0.9993561 | EX22: =EW22-X22 -> -0.00056730899 | EY22: =EV22-W22 -> 0.10327713 | EZ22: =(1-FA22)*100 -> 1.6546433 | FA22: 0.98345357 | FB22: =(EI22/$EA22-1) / (EQ22/$EN22-1) -> 1.9365548 | FC22: =(EJ22/$EA22-1) / (ER22/$EN22-1) -> 1.9375453 | FD22: =(EK22/$EA22-1) / (ES22/$EN22-1) -> 2.5113079 | FE22: =(EL22/$EA22-1) / (ET22/$EN22-1) -> 2.2504535 | FF22: =FB22-AD22 -> 0.11398765 | FG22: =FC22-AE22 -> 0.065006953 | FH22: =FD22-AF22 -> 0.10375537 | FI22: =FE22-AG22 -> 0.19279756

Sheet 2AT
B2: Template corresponding to Part 2 of the project Fiscal Drag in Europe.
B3: Yellow cells have to be filled by you
B4: Remaing cells are automatically calculated using information from yellow cells (grey cells remain empty)
B5: Red cells are 2026 results that can be filled with fake/provisional results. When we fill them with final results (the plan is to use Dec BMPE data) turn them yellow.
B8: Country | C8: AT | D8: Austria | E8: Updated: dd/mm/2025
C10: Personal Income Tax Revenue | P10: Tax Base (il_fiscaldrag_all) | AM10: Sensitivity test
B11: Decile | C11: 2019_baseline | D11: 2020_baseline | E11: 2021_baseline | F11: 2022_baseline | G11: 2023_baseline | H11: 2023 if 2019legis unchanged (upper bound) | I11: 2023 if 2019legis indexed with tax base growth (lower bound a) | J11: 2023 if 2019legis indexed with lagged HCPI (lower bound b) | K11: 2023 if 2019legis indexed with concurrent HCPI (lower bound c) | P11: 2019_baseline | Q11: 2020_baseline | R11: 2021_baseline | S11: 2022_baseline | T11: 2023_baseline | U11: Growth rate 2023/2019 | AK11: 2023_baseline without indexation measures | AM11: TBB elasticity | AN11: 2023_newbaseline | AO11: 2023_homogeneous | AP11: 2023_heterogeneous | AQ11: initial growth | AR11: adjusted growth | AS11: weight
B12: 1 | C12: {='[4]2. Distributional by deciles o'!$B$82:$F$92} -> -1.5702069e+08 | D12: -2.0794697e+08 | E12: -2.3632036e+08 | F12: -3.3914978e+08 | G12: -2.9724656e+08 | H12: {='[4]2. Distributional by deciles o'!$H$82:$K$92} -> -1.3626453e+08 | I12: -1.7717673e+08 | J12: -1.7568175e+08 | K12: -1.9361364e+08 | P12: {='[4]2. Distributional by deciles o'!$B$100:$F$110} -> 3.2257884e+09 | Q12: 3.2881219e+09 | R12: 3.3803686e+09 | S12: 3.5231959e+09 | T12: 3.768538e+09 | U12: =T12/P12-1 -> 0.16825332 | AK12: {='[4]2. Distributional by deciles o'!$L$82:$L$92} -> -2.6743198e+08 | AM12: {=INDIRECT("'1"&$C$8&"'!W12")} -> 0.55434579 | AN12: =C12+C12*U12*AM12 -> -1.7166609e+08 | AO12: =C12+C12*U$22*AM12 -> -1.7188247e+08 | AP12: =C12+C12*AR12*AM12 -> -1.7166609e+08 | AQ12: =U12 -> 0.16825332 | AR12: =AQ12 -> 0.16825332 | AS12: =P12/P$22 -> 0.012309505
B13: 2 | C13: 26423258 | D13: -1.1352545e+08 | E13: -1.7300794e+08 | F13: -2.6472351e+08 | G13: -1.76391e+08 | H13: 2.4328725e+08 | I13: 39735715 | J13: 45953963 | K13: -18906640 | P13: 1.037195e+10 | Q13: 1.0610427e+10 | R13: 1.0911393e+10 | S13: 1.1325073e+10 | T13: 1.2110872e+10 | U13: =T13/P13-1 -> 0.16765619 | AK13: 4137109.8 | AM13: {=INDIRECT("'1"&$C$8&"'!W13")} -> 39.258922 | AN13: =C13+C13*U13*AM13 -> 2.0034118e+08 | AO13: =C13+C13*U$22*AM13 -> 2.0353938e+08 | AP13: =C13+C13*AR13*AM13 -> 2.0034118e+08 | AQ13: =U13 -> 0.16765619 | AR13: =AQ13 -> 0.16765619 | AS13: =P13/P$22 -> 0.039579029
B14: 3 | C14: 5.3322438e+08 | D14: 3.8025507e+08 | E14: 3.8231386e+08 | F14: 2.7634964e+08 | G14: 3.8361334e+08 | H14: 9.8775242e+08 | I14: 6.4008163e+08 | J14: 6.5249807e+08 | K14: 5.1250314e+08 | P14: 1.4137687e+10 | Q14: 1.4432777e+10 | R14: 1.4803798e+10 | S14: 1.5376819e+10 | T14: 1.6467652e+10 | U14: =T14/P14-1 -> 0.16480527 | AK14: 5.6554547e+08 | AM14: {=INDIRECT("'1"&$C$8&"'!W14")} -> 4.8325244 | AN14: =C14+C14*U14*AM14 -> 9.5789785e+08 | AO14: =C14+C14*U$22*AM14 -> 9.7318864e+08 | AP14: =C14+C14*AR14*AM14 -> 9.5789785e+08 | AQ14: =U14 -> 0.16480527 | AR14: =AQ14 -> 0.16480527 | AS14: =P14/P$22 -> 0.053948959
B15: 4 | C15: 1.0527935e+09 | D15: 9.0090455e+08 | E15: 9.5119044e+08 | F15: 8.6863887e+08 | G15: 9.8829801e+08 | H15: 1.6778239e+09 | I15: 1.24448e+09 | J15: 1.2605063e+09 | K15: 1.0810566e+09 | P15: 1.7268543e+10 | Q15: 1.76215e+10 | R15: 1.8086398e+10 | S15: 1.8797211e+10 | T15: 2.0112856e+10 | U15: =T15/P15-1 -> 0.1647107 | AK15: 1.1906189e+09 | AM15: {=INDIRECT("'1"&$C$8&"'!W15")} -> 3.4818014 | AN15: =C15+C15*U15*AM15 -> 1.65656e+09 | AO15: =C15+C15*U$22*AM15 -> 1.6786584e+09 | AP15: =C15+C15*AR15*AM15 -> 1.65656e+09 | AQ15: =U15 -> 0.1647107 | AR15: =AQ15 -> 0.1647107 | AS15: =P15/P$22 -> 0.065896205
B16: 5 | C16: 1.6073541e+09 | D16: 1.4711325e+09 | E16: 1.5660649e+09 | F16: 1.5104053e+09 | G16: 1.6428539e+09 | H16: 2.3800382e+09 | I16: 1.9036162e+09 | J16: 1.92139e+09 | K16: 1.7199437e+09 | P16: 2.0486801e+10 | Q16: 2.0893159e+10 | R16: 2.1460044e+10 | S16: 2.2332654e+10 | T16: 2.3911846e+10 | U16: =T16/P16-1 -> 0.16718297 | AK16: 1.8374689e+09 | AM16: {=INDIRECT("'1"&$C$8&"'!W16")} -> 2.7986468 | AN16: =C16+C16*U16*AM16 -> 2.3594127e+09 | AO16: =C16+C16*U$22*AM16 -> 2.3754103e+09 | AP16: =C16+C16*AR16*AM16 -> 2.3594127e+09 | AQ16: =U16 -> 0.16718297 | AR16: =AQ16 -> 0.16718297 | AS16: =P16/P$22 -> 0.078176977
B17: 6 | C17: 2.2988003e+09 | D17: 2.1687198e+09 | E17: 2.2885061e+09 | F17: 2.2600717e+09 | G17: 2.4292412e+09 | H17: 3.243044e+09 | I17: 2.7200063e+09 | J17: 2.7396981e+09 | K17: 2.5155369e+09 | P17: 2.3783687e+10 | Q17: 2.426369e+10 | R17: 2.4894753e+10 | S17: 2.5887072e+10 | T17: 2.7768145e+10 | U17: =T17/P17-1 -> 0.16752904 | AK17: 2.6375182e+09 | AM17: {=INDIRECT("'1"&$C$8&"'!W17")} -> 2.4004676 | AN17: =C17+C17*U17*AM17 -> 3.2232584e+09 | AO17: =C17+C17*U$22*AM17 -> 3.2409729e+09 | AP17: =C17+C17*AR17*AM17 -> 3.2232584e+09 | AQ17: =U17 -> 0.16752904 | AR17: =AQ17 -> 0.16752904 | AS17: =P17/P$22 -> 0.090757787
B18: 7 | C18: 3.100813e+09 | D18: 2.9777761e+09 | E18: 3.137534e+09 | F18: 3.1636513e+09 | G18: 3.3665093e+09 | H18: 4.2668275e+09 | I18: 3.6720612e+09 | J18: 3.6940184e+09 | K18: 3.4462696e+09 | P18: 2.8139029e+10 | Q18: 2.8688938e+10 | R18: 2.9461291e+10 | S18: 3.0668583e+10 | T18: 3.2880887e+10 | U18: =T18/P18-1 -> 0.16851533 | AK18: 3.6049385e+09 | AM18: {=INDIRECT("'1"&$C$8&"'!W18")} -> 2.1587569 | AN18: =C18+C18*U18*AM18 -> 4.2288381e+09 | AO18: =C18+C18*U$22*AM18 -> 4.2437247e+09 | AP18: =C18+C18*AR18*AM18 -> 4.2288381e+09 | AQ18: =U18 -> 0.16851533 | AR18: =AQ18 -> 0.16851533 | AS18: =P18/P$22 -> 0.10737763
B19: 8 | C19: 4.1011487e+09 | D19: 3.9916437e+09 | E19: 4.2075365e+09 | F19: 4.2969825e+09 | G19: 4.5875862e+09 | H19: 5.5702552e+09 | I19: 4.8925107e+09 | J19: 4.9179668e+09 | K19: 4.6305432e+09 | P19: 3.3005546e+10 | Q19: 3.3634378e+10 | R19: 3.4547014e+10 | S19: 3.6017444e+10 | T19: 3.8726234e+10 | U19: =T19/P19-1 -> 0.17332506 | AK19: 4.8342037e+09 | AM19: {=INDIRECT("'1"&$C$8&"'!W19")} -> 2.0041936 | AN19: =C19+C19*U19*AM19 -> 5.5257934e+09 | AO19: =C19+C19*U$22*AM19 -> 5.5045392e+09 | AP19: =C19+C19*AR19*AM19 -> 5.1405121e+09 | AQ19: =U19 -> 0.17332506 | AR19: =U19-AP31*AS21/SUM(AS19:AS20) -> 0.12645098 | AS19: =P19/P$22 -> 0.1259481
B20: 9 | C20: 6.4523723e+09 | D20: 6.3961503e+09 | E20: 6.7169703e+09 | F20: 6.9749345e+09 | G20: 7.3769942e+09 | H20: 8.4600046e+09 | I20: 7.6749179e+09 | J20: 7.7048948e+09 | K20: 7.364033e+09 | P20: 4.1649731e+10 | Q20: 4.2428207e+10 | R20: 4.3599841e+10 | S20: 4.5491435e+10 | T20: 4.8821129e+10 | U20: =T20/P20-1 -> 0.17218355 | AK20: 7.6565078e+09 | AM20: {=INDIRECT("'1"&$C$8&"'!W20")} -> 1.7553482 | AN20: =C20+C20*U20*AM20 -> 8.4025507e+09 | AO20: =C20+C20*U$22*AM20 -> 8.3861923e+09 | AP20: =C20+C20*AR20*AM20 -> 7.8716474e+09 | AQ20: =U20 -> 0.17218355 | AR20: =U20-AP31*AS21/SUM(AS19:AS20) -> 0.12530947 | AS20: =P20/P$22 -> 0.15893404
B21: 10 | C21: 1.6084719e+10 | D21: 1.6177745e+10 | E21: 1.6934383e+10 | F21: 1.7905816e+10 | G21: 1.9016588e+10 | H21: 2.0246351e+10 | I21: 1.9190259e+10 | J21: 1.9230433e+10 | K21: 1.8774946e+10 | P21: 6.9987948e+10 | Q21: 7.1163642e+10 | R21: 7.3332058e+10 | S21: 7.6804596e+10 | T21: 8.2231915e+10 | U21: =T21/P21-1 -> 0.17494393 | AK21: 1.9359536e+10 | AM21: {=INDIRECT("'1"&$C$8&"'!W21")} -> 1.4049842 | AN21: =C21+C21*U21*AM21 -> 2.0038238e+10 | AO21: =C21+C21*U$22*AM21 -> 1.9943217e+10 | AP21: =C21+C21*AR21*AM21 -> 2.1168177e+10 | AQ21: =U21 -> 0.17494393 | AR21: =U21+AP31 -> 0.22494393 | AS21: =P21/P$22 -> 0.26707177
B22: Total | C22: 3.5100628e+10 | D22: 3.4142855e+10 | E22: 3.5775171e+10 | F22: 3.6652976e+10 | G22: 3.9318046e+10 | H22: 4.693912e+10 | I22: 4.1800492e+10 | J22: 4.1991678e+10 | K22: 3.9832312e+10 | P22: 2.6205671e+11 | Q22: 2.6702484e+11 | R22: 2.7447696e+11 | S22: 2.8622408e+11 | T22: 3.0680007e+11 | U22: =T22/P22-1 -> 0.17073924 | AK22: 4.1423042e+10 | AM22: {=INDIRECT("'1"&$C$8&"'!W22")} -> 1.8866256 | AN22: =SUM(AN12:AN21) -> 4.6421224e+10 | AO22: =SUM(AO12:AO21) -> 4.6377561e+10 | AP22: =SUM(AP12:AP21) -> 4.6634979e+10 | AQ22: =SUMPRODUCT(AQ12:AQ21,AS12:AS21) -> 0.17073924 | AR22: =SUMPRODUCT(AR12:AR21,AS12:AS21) -> 0.17073924
AR23: =U22 -> 0.17073924
G24: inc.growth | H24: =U22 -> 0.17073924 | K24: inc.growth | AN24: =AN22/G22-1 -> 0.18065949 | AR24: =IF(AR23-AR22<0.0000000001,"ok","wrong") -> ok
G25: laggedHCPI | H25: 0.1486 | K25: laggedHCPI | AR25: =IF(AQ22-AR22<0.0000000001,"ok","wrong") -> ok
G26: concurr.HCPI | H26: 0.2189 | K26: concurr.HCPI | AM26: relative to new baseline 2023 | AO26: =AO22/$AN22-1 -> -0.00094059748 | AP26: =AP22/$AN22-1 -> 0.0046046647
AM28: relative to potential fiscal drag | AO28: =(AO22-$AN22)/($W$37*1000000) -> -0.0074007692 | AP28: =(AP22-$AN22)/($W$37*1000000) -> 0.036230228
B29: Outcome: total tax revenue
B30: Query: | C30: UPDATE FOR BMPE: Growth rate from old projections on top of NA | D30: lv; var=B1GQ:=SC_devgr101.DATA!ISIS&4575.ESVG2010&38,CAT(B1GQ; YED_AT_J*YER_AT_J;'cp'),(D51A_C01+D51A_C08)*100/B1GQ,(D51A_C01+D51A_C08)*1000000; date=8J to 2026; offset=2,-1; error=; txt=off; txt2=off; txt3=off; info=0; dateformat=off; daterangeformat=1 | AC30: Table for results (share GDP)
B31: Table for calculations | E31: For reescaling | F31: For reescaling | H31: All these are reescaled | N31: Table for results (million euros) | P31: Actual Fiscal Drag | T31: Potential Fiscal Drag | X31: Effective offsetting of Fiscal Drag | AC31: Actual Fiscal Drag | AF31: Potential Fiscal Drag | AO31: shock | AP31: 0.05
C32: Baseline (before reescaling) | D32: GDP (million euros) | E32: National Account PIT Revenue observed | F32: National Account PIT Revenue observed (euros) | G32: Reescaling factor | H32: Baseline | I32: Legislation unchanged since 2019/2023 | J32: Index with tax base growth | K32: Index with lagged HCPI | L32: Index with concurrent HCPI | M32: Baseline w/o "indexation measures" | O32: Size of reescaling | P32: Actual Fiscal Drag (wrt tax.inc.growth) | Q32: Actual Fiscal Drag (wrt lagged HCPI) | R32: Actual Fiscal Drag (wrt concurrent HCPI) | S32: Actual Fiscal Drag (wrt average index) | T32: Potential Fiscal Drag (wrt tax.inc.growth) | U32: Potential Fiscal Drag (wrt lagged HCPI) | V32: Potential Fiscal Drag (wrt concurrent HCPI) | W32: Potential Fiscal Drag (wrt average index) | X32: % Offsetting (wrt tax.inc.growth) | Y32: % Offsetting (wrt lagged HCPI) | Z32: % Offsetting (wrt concurrent HCPI) | AA32: % Offsetting (wrt average index) | AC32: Actual Fiscal Drag (wrt tax.inc.growth) | AD32: Actual Fiscal Drag (wrt lagged HCPI) | AE32: Actual Fiscal Drag (wrt concurrent HCPI) | AF32: Potential Fiscal Drag (wrt tax.inc.growth) | AG32: Potential Fiscal Drag (wrt lagged HCPI) | AH32: Potential Fiscal Drag (wrt concurrent HCPI)
B33: 2019 | C33: =C22 -> 3.5100628e+10 | D33: 395706.77 | E33: 8.9520508 | F33: 3.5423871e+10 | G33: =F33/C33 -> 1.009209 | H33: =C33*G33 -> 3.5423871e+10 | I33: - | J33: - | K33: - | L33: - | N33: 2019 | O33: =G33 -> 1.009209
B34: 2020 | C34: =D22 -> 3.4142855e+10 | D34: 380317.88 | E34: 8.6871036 | F34: 3.3038608e+10 | G34: =F34/C34 -> 0.96765806 | H34: =C34*G34 -> 3.3038608e+10 | N34: 2020
B35: 2021 | C35: =E22 -> 3.5775171e+10 | D35: 406232.06 | E35: 8.8437542 | F35: 3.5926165e+10 | G35: =F35/C35 -> 1.0042206 | H35: =C35*G35 -> 3.5926165e+10 | N35: 2021
B36: 2022 | C36: =F22 -> 3.6652976e+10 | D36: 448007.45 | E36: 8.786152 | F36: 3.9362615e+10 | G36: =F36/C36 -> 1.0739268 | H36: =C36*G36 -> 3.9362615e+10 | N36: 2022
B37: 2023 | C37: =G22 -> 3.9318046e+10 | D37: 473226.72 | E37: 8.5534027 | F37: 4.0476987e+10 | G37: =F37/C37 -> 1.029476 | H37: =C37*G37 -> 4.0476987e+10 | I37: =H22*$G37 -> 4.8322699e+10 | J37: =I22*$G37 -> 4.3032605e+10 | K37: =J22*$G37 -> 4.3229426e+10 | L37: =K22*$G37 -> 4.1006411e+10 | M37: =AK22*$G37 -> 4.264403e+10 | N37: 2023 | O37: =G37 -> 1.029476 | P37: =($H37-J37)/1000000 -> -2555.6182 | Q37: =($H37-K37)/1000000 -> -2752.4392 | R37: =($H37-L37)/1000000 -> -529.42439 | S37: =AVERAGE(P37:R37) -> -1945.8273 | T37: =($I37-J37)/1000000 -> 5290.094 | U37: =($I37-K37)/1000000 -> 5093.273 | V37: =($I37-L37)/1000000 -> 7316.2878 | W37: =AVERAGE(T37:V37) -> 5899.8849 | X37: =(T37-P37)/T37 -> 1.483095 | Y37: =(U37-Q37)/U37 -> 1.5404068 | Z37: =(V37-R37)/V37 -> 1.0723624 | AA37: =AVERAGE(X37:Z37) -> 1.3652881 | AC37: =P37/$D37 -> -0.0054004098 | AD37: =Q37/$D37 -> -0.0058163225 | AE37: =R37/$D37 -> -0.0011187542 | AF37: =T37/$D37 -> 0.011178773 | AG37: =U37/$D37 -> 0.01076286 | AH37: =V37/$D37 -> 0.015460428
B38: 2024 | D38: 493091.52 | N38: 2024
B39: 2025 | D39: 516212.47 | N39: 2025
B40: 2026 | D40: 537993.83 | N40: 2026
X41: Of which, through "indexation measures":
W42: 2023 | X42: =(($M37-$H37)/1000000)/T37 -> 0.40964165 | Y42: =(($M37-$H37)/1000000)/U37 -> 0.42547157 | Z42: =(($M37-$H37)/1000000)/V37 -> 0.29619431 | AA42: =AVERAGE(X42:Z42) -> 0.37710251
B44: Table for Figure (million euros) | D44: For reescaling | F44: All these are reescaled | U44: Table for Figure (share GDP) | W44: For reescaling | Y44: All these are reescaled
C45: Baseline simulation (before reescaling) | D45: Observed (National Accounts) | E45: Reescaling factor | F45: Baseline simulation (after reescaling) | G45: Unchanged legislation since 2019/2023 | H45: Indexing with tax base growth | I45: Indexing with lagged HCPI | J45: Indexing with concurrent HCPI | K45: Baseline w/o "indexation measures" | V45: Baseline simulation (before reescaling) | W45: Observed (National Accounts) | X45: Reescaling factor | Y45: Baseline simulation (after reescaling) | Z45: Unchanged legislation since 2019/2023 | AA45: Indexing with tax base growth | AB45: Indexing with lagged HCPI | AC45: Indexing with concurrent HCPI
B46: 2019 | C46: =C33/1000000 -> 35100.628 | D46: =F33/1000000 -> 35423.871 | F46: =H33/1000000 -> 35423.871 | U46: 2019 | V46: =C33/1000000/D33 -> 0.088703634 | W46: =F33/(D33*1000000) -> 0.089520508 | Y46: =H33/($D33*1000000) -> 0.089520508
B47: 2020 | C47: =C34/1000000 -> 34142.855 | D47: =F34/1000000 -> 33038.608 | U47: 2020 | V47: =C34/1000000/D34 -> 0.089774519 | W47: =F34/(D34*1000000) -> 0.086871036
B48: 2021 | C48: =C35/1000000 -> 35775.171 | D48: =F35/1000000 -> 35926.165 | U48: 2021 | V48: =C35/1000000/D35 -> 0.088065848 | W48: =F35/(D35*1000000) -> 0.088437542
B49: 2022 | C49: =C36/1000000 -> 36652.976 | D49: =F36/1000000 -> 39362.615 | U49: 2022 | V49: =C36/1000000/D36 -> 0.08181332 | W49: =F36/(D36*1000000) -> 0.08786152
B50: 2023 | C50: =C37/1000000 -> 39318.046 | D50: =F37/1000000 -> 40476.987 | F50: =H37/1000000 -> 40476.987 | G50: =I37/1000000 -> 48322.699 | H50: =J37/1000000 -> 43032.605 | I50: =K37/1000000 -> 43229.426 | J50: =L37/1000000 -> 41006.411 | K50: =M37/1000000 -> 42644.03 | U50: 2023 | V50: =C37/1000000/D37 -> 0.08308501 | W50: =F37/(D37*1000000) -> 0.085534027 | Y50: =H37/($D37*1000000) -> 0.085534027 | Z50: =I37/($D37*1000000) -> 0.10211321 | AA50: =J37/($D37*1000000) -> 0.090934436 | AB50: =K37/($D37*1000000) -> 0.091350349 | AC50: =L37/($D37*1000000) -> 0.086652781
B51: 2024 | U51: 2024
B52: 2025 | U52: 2025
B53: 2026 | U53: 2026
B61: Outcome: average effective tax rate
B64: Table for Figure (%) | C64: Baseline simulation | D64: Legislation unchanged since 2019/2023 | E64: Index with tax base growth | F64: Index with lagged HCPI | G64: Index with concurrent HCPI
B65: 2019 | C65: =C22/P22*100 -> 13.394287
B66: 2020 | C66: =D22/Q22*100 -> 12.786396
B67: 2021 | C67: =E22/R22*100 -> 13.033943
B68: 2022 | C68: =F22/S22*100 -> 12.805693
B69: 2023 | C69: =G22/$T22*100 -> 12.815527 | D69: =H22/$T22*100 -> 15.299579 | E69: =I22/$T22*100 -> 13.624668 | F69: =J22/$T22*100 -> 13.686984 | G69: =K22/$T22*100 -> 12.983149
B70: 2024
B71: 2025
B72: 2026
B77: Table for results % | C77: Baseline simulation | D77: Legislation unchanged since 2019/2023 | E77: Index with tax base growth | F77: Index with lagged HCPI | G77: Index with concurrent HCPI
B78: 2019 | C78: =C65 -> 13.394287
B79: 2020 | C79: =C66 -> 12.786396
B80: 2021 | C80: =C67 -> 13.033943
B81: 2022 | C81: =C68 -> 12.805693
B82: 2023 | C82: =C69 -> 12.815527 | D82: =D69 -> 15.299579 | E82: =E69 -> 13.624668 | F82: =F69 -> 13.686984 | G82: =G69 -> 12.983149
B83: 2024
B84: 2025
B85: 2026

Sheet 1BE
B2: Template corresponding to Part 1 of the project Fiscal Drag in Europe
B3: Yellow cells have to be filled by you (remember to rename the sheets as well)
B4: Remaing cells are automatically calculated using information from yellow cells (grey cells remain empty)
B8: Country | C8: BE | D8: Belgium | E8: Updated:10/02/2025 (indepth) [ 24/09/2024 (data) (fileversion 22/10/2024)]
C10: Personal Income Tax Revenue | P10: Tac Base (il_fiscaldrag_all) | W10: TTB | AD10: TTB by income source | AH10: Decomposition of TTB in pp | AQ10: Decomposition of fiscal drag in percentage | AZ10: OECD estimates | CC10: Ratio8020 all income | CK10: Gini tax base (from Table 3.1) | CS10: Ratio8020 tax base | DA10: Kakwani (from Table 3.2) | DD10: Share taxpayers | EA10: 2023 Personal Income Tax Revenue | EN10: 2023 Tax Base (il_fiscaldrag_all) | EV10: 2023 TTB | EZ10: 2023 Share taxpayers | FB10: 2023 TTB by income source
B11: Decile | C11: Original | D11: Incomes grow 1% | E11: Incomes & all parameters grow 1% | F11: Incomes & (only) tax brackets grow 1% | G11: Incomes & tax brackets and tax benefit #1 grow 1% | H11: Incomes & tax brackets and tax benefit #1 & 2 grow 1% | I11: Incomes & tax brackets and tax benefit #1 & 2 & 3 grow 1% | K11: Labor income grows 1% | L11: Benefits and pensions grow 1% | M11: Self-employment income grows 1% | N11: Capital income grows 1% | O11: Share of total tax liability | P11: Original | Q11: Incomes grow 1% | R11: Relative change (should be 1%) | S11: Labor income grows 1% | T11: Benefits and pensions grow 1% | U11: Self-employment income grows 1% | V11: Capital income grows 1% | W11: Incomes grow 1% | X11: Incomes & all parameters grow 1% | Y11: Incomes & tax brackets grow 1% | Z11: Incomes & tax brackets and tax benefit #1 grow 1% | AA11: Incomes & tax brackets and tax benefit #1 & 2 grow 1% | AB11: Incomes & tax brackets and tax benefit #1 & 2 & 3 grow 1% | AC11: Incomes & tax brackets and tax benefit #1 & 2 & 3 & 4 grow 1% | AD11: Labor income grows 1% | AE11: Benefits and pensions grow 1% | AF11: Self-employment income grows 1% | AG11: Capital income grows 1% | AH11: Proportional effect | AI11: Residual | AJ11: By bracket progressivity | AK11: By tax benefit 1 | AL11: By tax benefit 2 | AM11: By tax benefit 3 | AN11: By tax benefit 4 | AO11: By other tax benefits | AP11: By other tax benefits and residual | AQ11: Proportional effect | AR11: Residual | AS11: By bracket progressivity | AT11: By tax benefit 1 | AU11: By tax benefit 2 | AV11: By tax benefit 3 | AX11: By other tax benefits | AY11: By other tax benefits and residual | AZ11: TTB all incomes | BA11: TTB earnings | BB11: TTB self-empl. | BC11: TTB capital | BD11: Diff. all incomes (pp) | BE11: Diff. earnings (pp) | BF11: Diff. self-empl. (pp) | BG11: Diff. capital (pp) | BH11: Labour income | BI11: Pension and benefits | BJ11: Self-employment income | BK11: Capital income | BL11: Share of labour income | BM11: Share of pension and benefits | BN11: Share of self-employment income | BO11: Share of capital income | BP11: TTB without pensions | BQ11: Diff TTB TTB_nopens | BR11: Diff TTB_nopens TTB_OECD | BS11: Share of total tax base | CC11: Ratio8020 all income preincrease pretax | CD11: Ratio8020 all income preincrease posttax | CE11: Ratio8020 all income postincrease pretax | CF11: Ratio8020 all income postincrease posttax | CG11: Ratio8020 allinc increase preincrease | CH11: Ratio8020 allinc increase postincrease | CI11: Diff Ratio8020 change allinc (pp) | CJ11: Diff Ratio8020 allinc postax (pp) | CK11: Gini tax base preincrease pretax | CL11: Gini tax base preincrease posttax | CM11: Gini tax base postincrease pretax | CN11: Gini tax base postincrease posttax | CO11: Gini taxinc reduction preincrease | CP11: Gini taxinc reduction postincrease | CQ11: Diff Gini reduction taxinc (pp) | CR11: Diff Gini tax base posttax | CS11: Ratio8020 tax base preincrease pretax | CT11: Ratio8020 tax base preincrease posttax | CU11: Ratio8020 tax base postincrease pretax | CV11: Ratio8020 tax base postincrease posttax | CW11: Ratio8020 taxinc decrease preincrease | CX11: Ratio8020 taxinc decrease postincrease | CY11: Diff Ratio8020 change taxinc (pp) | CZ11: Diff Ratio8020 taxinc postax (pp) | DA11: kawani taxinc preincrease | DB11: kawani taxinc postincrease | DC11: Diff kakwani taxinc | DD11: Share with zero tax liability (right axis) | DE11: Share with non-zero tax liability | EA11: 2023 Original | EB11: 2023 Incomes grow 1% | EC11: 2023 Incomes & all parameters grow 1% | ED11: 2023 Incomes & (only) tax brackets grow 1% | EE11: 2023 Incomes & (only) tax brackets and tax benefit #1 grow 1% | EF11: 2023 Incomes & tax brackets and tax benefit #1 & 2 grow 1% | EG11: 2023 Incomes & tax brackets and tax benefit #1 & 2 & 3 grow 1% | EI11: 2023 Labor income grows 1% | EJ11: 2023 Benefits and pensions grow 1% | EK11: 2023 Self-employment income grows 1% | EL11: 2023 Capital income grows 1% | EM11: Share of total tax liability | EN11: 2023 Original | EO11: 2023 Incomes grow 1% | EP11: 2023 Relative change (should be 1%) | EQ11: 2023 Labor income grows 1% | ER11: 2023 Benefits and pensions grow 1% | ES11: 2023 Self-employment income grows 1% | ET11: 2023 Capital income grows 1% | EU11: 2023 Share of total tax base | EV11: 2023 TTB Incomes grow 1% | EW11: 2023 Incomes & all parameters grow 1% | EX11: 2023 Diff residual (pp) | EY11: 2023 TTB change | EZ11: 2023 Share with zero tax liability (right axis) | FA11: 2023 Share with non-zero tax liability | FB11: 2023 TTB Labor income grows 1% | FC11: 2023 TTB Benefits and pensions grow 1% | FD11: 2023 TTB Self-employment income grows 1% | FE11: 2023 TTB Capital income grows 1% | FF11: 2023 TTB change Labor | FG11: 2023 TTB change Benefits and pensions | FH11: 2023 TTB change Self-employment income | FI11: 2023 TTB change Capital
B12: 1 | C12: ='[5]2. Distributional by deciles o'!B100 -> -1.9320262e+08 | D12: ='[5]2. Distributional by deciles o'!C100 -> -1.9001159e+08 | E12: ='[5]2. Distributional by deciles o'!D100 -> -1.9454132e+08 | F12: ='[5]2. Distributional by deciles o'!E100 -> -1.9019953e+08 | G12: ='[5]2. Distributional by deciles o'!F100 -> -1.9438087e+08 | H12: ='[5]2. Distributional by deciles o'!G100 -> -1.9454132e+08 | I12: ='[5]2. Distributional by deciles o'!H100 -> -1.9454132e+08 | K12: - | L12: - | M12: - | N12: - | O12: =C12/C$22*100 -> -0.34150139 | P12: ='[5]2. Distributional by deciles o'!B118 -> 5.9810798e+09 | Q12: ='[5]2. Distributional by deciles o'!C118 -> 6.04089e+09 | R12: =(Q12/P12-1)*100 -> 0.99999124 | S12: - | T12: - | U12: - | V12: - | W12: =IF(D12<>0,((D12-$C12)/ABS($C12)) / ($Q12/$P12-1),0) -> 1.6516613 | X12: =IF(E12<>0,((E12-$C12)/ABS($C12)) / ($Q12/$P12-1),0) -> -0.69290835 | Y12: =IF(F12<>0,MAX(((F12-$C12)/ABS($C12)) / ($Q12/$P12-1),0),0) -> 1.5543835 | Z12: =IF(G12<>0,MAX(((G12-$C12)/ABS($C12)) / ($Q12/$P12-1),0),0) -> 0 | AA12: =IF(H12<>0,MAX(((H12-$C12)/ABS($C12)) / ($Q12/$P12-1),0),0) -> 0 | AB12: =IF(I12<>0,MAX(((I12-$C12)/ABS($C12)) / ($Q12/$P12-1),0),AA12) -> 0 | AC12: =IF(J12<>0,MAX(((J12-$C12)/ABS($C12)) / ($Q12/$P12-1),0),AB12) -> 0 | AD12: - | AE12: - | AF12: - | AG12: - | AH12: =MIN(W12,1) -> 1 | AI12: =IF(W12>1,MAX(W12-SUM(AH12,AJ12:AO12),0),0) -> 0 | AJ12: =IF(W12>1,MIN($W12-Y12,W12-AH12),0) -> 0.097277749 | AK12: =IF(W12>1,MAX(MIN(Y12-Z12,W12-AH12-AJ12),0),0) -> 0.55438351 | AL12: =IF(W12>1,MAX(MIN(Z12-AA12,W12-AH12-AJ12-AK12),0),0) -> 0 | AM12: =IF(I12<>0,IF(W12>1,MAX(MIN(AA12-AB12,W12-AH12-AJ12-AK12-AL12),0),0),0) -> 0 | AN12: =IF(J12<>0,IF(W12>1,MAX(MIN(AB12-AC12,W12-AH12-AJ12-AK12-AL12-AM12),0),0),0) -> 0 | AO12: =IF(W12>1,MAX(0,MIN(W12-AH12-AJ12-AK12-AL12-AM12,W12-AH12-AJ12-AK12-AL12-AM12-X12+1)),0) -> 0 | AP12: =AI12+AO12 -> 0 | AQ12: - | AR12: =AI12/($W12-1)*100 -> 0 | AS12: =AJ12/($W12-1)*100 -> 14.927656 | AT12: =AK12/($W12-1)*100 -> 85.072344 | AU12: =AL12/($W12-1)*100 -> 0 | AV12: =AM12/($W12-1)*100 -> 0 | AW12: =AN12/($W12-1)*100 -> 0 | AX12: =AO12/($W12-1)*100 -> 0 | AY12: =AP12/($W12-1)*100 -> 0 | AZ12: - | BA12: - | BB12: - | BC12: - | BD12: - | BE12: - | BF12: - | BG12: - | BH12: ='[5]2. Distributional by deciles o'!B136 -> 1.7615382e+09 | BI12: ='[5]2. Distributional by deciles o'!B154 -> 3.8665876e+09 | BJ12: ='[5]2. Distributional by deciles o'!B172 -> 3.1223967e+08 | BK12: ='[5]2. Distributional by deciles o'!B190 -> 40712715 | BL12: =BH12/SUM($BH12:$BK12) -> 0.2945185 | BM12: =BI12/SUM($BH12:$BK12) -> 0.64647 | BN12: =BJ12/SUM($BH12:$BK12) -> 0.052204579 | BO12: =BK12/SUM($BH12:$BK12) -> 0.006806919 | BP12: - | BQ12: - | BR12: - | BS12: =P12/P$22*100 -> 2.1403718 | CC12: - | CD12: - | CE12: - | CF12: - | CG12: - | CH12: - | CI12: - | CK12: - | CL12: - | CM12: - | CN12: - | CO12: - | CP12: - | CQ12: - | CS12: - | CT12: - | CU12: - | CV12: - | CW12: - | CX12: - | CY12: - | DA12: - | DB12: - | DC12: - | DD12: =(1-DE12)*100 -> 38.935881 | DE12: ='[5]2. Distributional by deciles o'!J28 -> 0.61064119 | EA12: ='[6]2. Distributional by deciles o'!B100 -> -2.0725065e+08 | EB12: ='[6]2. Distributional by deciles o'!C100 -> -2.0207674e+08 | EC12: ='[6]2. Distributional by deciles o'!D100 -> -2.084856e+08 | ED12: ='[6]2. Distributional by deciles o'!E100 -> -2.0261711e+08 | EE12: ='[6]2. Distributional by deciles o'!F100 -> -2.0824184e+08 | EF12: ='[6]2. Distributional by deciles o'!G100 -> -2.084856e+08 | EI12: - | EJ12: - | EK12: - | EL12: - | EM12: =EA12/EA$22*100 -> -0.28280637 | EN12: ='[6]2. Distributional by deciles o'!B118 -> 7.4324841e+09 | EO12: ='[6]2. Distributional by deciles o'!C118 -> 7.5065405e+09 | EP12: =(EO12/EN12-1)*100 -> 0.99638884 | EQ12: - | ER12: - | ES12: - | ET12: - | EU12: =EN12/EN$22*100 -> 2.1874929 | EV12: =((EB12-$EA12)/ABS($EA12)) / ($EO12/$EN12-1) -> 2.5055 | EW12: =IF(EC12<>0,((EC12-$EA12)/ABS($EA12)) / ($EO12/$EN12-1),0) -> -0.59803213 | EY12: =EV12-W12 -> 0.85383876 | EZ12: =(1-FA12)*100 -> 39.582018 | FA12: ='[6]2. Distributional by deciles o'!I28 -> 0.60417982 | FB12: - | FC12: - | FD12: - | FE12: - | FF12: - | FG12: - | FH12: - | FI12: -
B13: 2 | C13: ='[5]2. Distributional by deciles o'!B101 -> 55151602 | D13: ='[5]2. Distributional by deciles o'!C101 -> 74307301 | E13: ='[5]2. Distributional by deciles o'!D101 -> 56101665 | F13: ='[5]2. Distributional by deciles o'!E101 -> 70011928 | G13: ='[5]2. Distributional by deciles o'!F101 -> 56915038 | H13: ='[5]2. Distributional by deciles o'!G101 -> 56162395 | I13: ='[5]2. Distributional by deciles o'!H101 -> 56162395 | K13: - | L13: - | M13: - | N13: - | O13: =C13/C$22*100 -> 0.097484957 | P13: ='[5]2. Distributional by deciles o'!B119 -> 1.3228337e+10 | Q13: ='[5]2. Distributional by deciles o'!C119 -> 1.3360616e+10 | R13: =(Q13/P13-1)*100 -> 0.99996926 | S13: - | T13: - | U13: - | V13: - | W13: =IF(D13<>0,((D13-$C13)/ABS($C13)) / ($Q13/$P13-1),0) -> 34.733873 | X13: =IF(E13<>0,((E13-$C13)/ABS($C13)) / ($Q13/$P13-1),0) -> 1.7226924 | Y13: =IF(F13<>0,MAX(((F13-$C13)/ABS($C13)) / ($Q13/$P13-1),0),0) -> 26.945333 | Z13: =IF(G13<>0,MAX(((G13-$C13)/ABS($C13)) / ($Q13/$P13-1),0),0) -> 3.1975313 | AA13: =IF(H13<>0,MAX(((H13-$C13)/ABS($C13)) / ($Q13/$P13-1),0),0) -> 1.8328088 | AB13: =IF(I13<>0,MAX(((I13-$C13)/ABS($C13)) / ($Q13/$P13-1),0),AA13) -> 1.8328088 | AC13: =IF(J13<>0,MAX(((J13-$C13)/ABS($C13)) / ($Q13/$P13-1),0),AB13) -> 1.8328088 | AD13: - | AE13: - | AF13: - | AG13: - | AH13: =MIN(W13,1) -> 1 | AI13: =IF(W13>1,MAX(W13-SUM(AH13,AJ13:AO13),0),0) -> 0.72269243 | AJ13: =IF(W13>1,MIN($W13-Y13,W13-AH13),0) -> 7.7885406 | AK13: =IF(W13>1,MAX(MIN(Y13-Z13,W13-AH13-AJ13),0),0) -> 23.747801 | AL13: =IF(W13>1,MAX(MIN(Z13-AA13,W13-AH13-AJ13-AK13),0),0) -> 1.3647225 | AM13: =IF(I13<>0,IF(W13>1,MAX(MIN(AA13-AB13,W13-AH13-AJ13-AK13-AL13),0),0),0) -> 0 | AN13: =IF(J13<>0,IF(W13>1,MAX(MIN(AB13-AC13,W13-AH13-AJ13-AK13-AL13-AM13),0),0),0) -> 0 | AO13: =IF(W13>1,MAX(0,MIN(W13-AH13-AJ13-AK13-AL13-AM13,W13-AH13-AJ13-AK13-AL13-AM13-X13+1)),0) -> 0.11011635 | AP13: =AI13+AO13 -> 0.83280878 | AQ13: - | AR13: =AI13/($W13-1)*100 -> 2.1423346 | AS13: =AJ13/($W13-1)*100 -> 23.08819 | AT13: =AK13/($W13-1)*100 -> 70.397494 | AU13: =AL13/($W13-1)*100 -> 4.0455554 | AV13: =AM13/($W13-1)*100 -> 0 | AW13: =AN13/($W13-1)*100 -> 0 | AX13: =AO13/($W13-1)*100 -> 0.32642664 | AY13: =AP13/($W13-1)*100 -> 2.4687612 | AZ13: - | BA13: - | BB13: - | BC13: - | BD13: - | BE13: - | BF13: - | BG13: - | BH13: ='[5]2. Distributional by deciles o'!B137 -> 2.6569338e+09 | BI13: ='[5]2. Distributional by deciles o'!B155 -> 1.0069663e+10 | BJ13: ='[5]2. Distributional by deciles o'!B173 -> 3.7868998e+08 | BK13: ='[5]2. Distributional by deciles o'!B191 -> 1.230506e+08 | BL13: =BH13/SUM($BH13:$BK13) -> 0.20085168 | BM13: =BI13/SUM($BH13:$BK13) -> 0.76121909 | BN13: =BJ13/SUM($BH13:$BK13) -> 0.028627179 | BO13: =BK13/SUM($BH13:$BK13) -> 0.0093020459 | BP13: - | BQ13: - | BR13: - | BS13: =P13/P$22*100 -> 4.733854 | CC13: - | CD13: - | CE13: - | CF13: - | CG13: - | CH13: - | CI13: - | CK13: - | CL13: - | CM13: - | CN13: - | CO13: - | CP13: - | CQ13: - | CS13: - | CT13: - | CU13: - | CV13: - | CW13: - | CX13: - | CY13: - | DA13: - | DB13: - | DC13: - | DD13: =(1-DE13)*100 -> 34.835839 | DE13: ='[5]2. Distributional by deciles o'!J29 -> 0.65164161 | EA13: ='[6]2. Distributional by deciles o'!B101 -> 2.8476125e+08 | EB13: ='[6]2. Distributional by deciles o'!C101 -> 3.2660618e+08 | EC13: ='[6]2. Distributional by deciles o'!D101 -> 2.8811482e+08 | ED13: ='[6]2. Distributional by deciles o'!E101 -> 3.1720223e+08 | EE13: ='[6]2. Distributional by deciles o'!F101 -> 2.8936356e+08 | EF13: ='[6]2. Distributional by deciles o'!G101 -> 2.8813243e+08 | EI13: - | EJ13: - | EK13: - | EL13: - | EM13: =EA13/EA$22*100 -> 0.38857439 | EN13: ='[6]2. Distributional by deciles o'!B119 -> 1.6447736e+10 | EO13: ='[6]2. Distributional by deciles o'!C119 -> 1.6612032e+10 | EP13: =(EO13/EN13-1)*100 -> 0.99889819 | EQ13: - | ER13: - | ES13: - | ET13: - | EU13: =EN13/EN$22*100 -> 4.8408184 | EV13: =((EB13-$EA13)/ABS($EA13)) / ($EO13/$EN13-1) -> 14.710952 | EW13: =IF(EC13<>0,((EC13-$EA13)/ABS($EA13)) / ($EO13/$EN13-1),0) -> 1.1789789 | EY13: =EV13-W13 -> -20.022921 | EZ13: =(1-FA13)*100 -> 19.399749 | FA13: ='[6]2. Distributional by deciles o'!I29 -> 0.80600251 | FB13: - | FC13: - | FD13: - | FE13: - | FF13: - | FG13: - | FH13: - | FI13: -
B14: 3 | C14: ='[5]2. Distributional by deciles o'!B102 -> 8.6033542e+08 | D14: ='[5]2. Distributional by deciles o'!C102 -> 9.1674432e+08 | E14: ='[5]2. Distributional by deciles o'!D102 -> 8.7052409e+08 | F14: ='[5]2. Distributional by deciles o'!E102 -> 9.0492278e+08 | G14: ='[5]2. Distributional by deciles o'!F102 -> 8.7345519e+08 | H14: ='[5]2. Distributional by deciles o'!G102 -> 8.7063261e+08 | I14: ='[5]2. Distributional by deciles o'!H102 -> 8.7063261e+08 | K14: - | L14: - | M14: - | N14: - | O14: =C14/C$22*100 -> 1.5207131 | P14: ='[5]2. Distributional by deciles o'!B120 -> 1.6300935e+10 | Q14: ='[5]2. Distributional by deciles o'!C120 -> 1.6463943e+10 | R14: =(Q14/P14-1)*100 -> 0.99999107 | S14: - | T14: - | U14: - | V14: - | W14: =IF(D14<>0,((D14-$C14)/ABS($C14)) / ($Q14/$P14-1),0) -> 6.5566763 | X14: =IF(E14<>0,((E14-$C14)/ABS($C14)) / ($Q14/$P14-1),0) -> 1.1842773 | Y14: =IF(F14<>0,MAX(((F14-$C14)/ABS($C14)) / ($Q14/$P14-1),0),0) -> 5.1826015 | Z14: =IF(G14<>0,MAX(((G14-$C14)/ABS($C14)) / ($Q14/$P14-1),0),0) -> 1.5249736 | AA14: =IF(H14<>0,MAX(((H14-$C14)/ABS($C14)) / ($Q14/$P14-1),0),0) -> 1.1968917 | AB14: =IF(I14<>0,MAX(((I14-$C14)/ABS($C14)) / ($Q14/$P14-1),0),AA14) -> 1.1968917 | AC14: =IF(J14<>0,MAX(((J14-$C14)/ABS($C14)) / ($Q14/$P14-1),0),AB14) -> 1.1968917 | AD14: - | AE14: - | AF14: - | AG14: - | AH14: =MIN(W14,1) -> 1 | AI14: =IF(W14>1,MAX(W14-SUM(AH14,AJ14:AO14),0),0) -> 0.1842773 | AJ14: =IF(W14>1,MIN($W14-Y14,W14-AH14),0) -> 1.3740748 | AK14: =IF(W14>1,MAX(MIN(Y14-Z14,W14-AH14-AJ14),0),0) -> 3.6576279 | AL14: =IF(W14>1,MAX(MIN(Z14-AA14,W14-AH14-AJ14-AK14),0),0) -> 0.32808194 | AM14: =IF(I14<>0,IF(W14>1,MAX(MIN(AA14-AB14,W14-AH14-AJ14-AK14-AL14),0),0),0) -> 0 | AN14: =IF(J14<>0,IF(W14>1,MAX(MIN(AB14-AC14,W14-AH14-AJ14-AK14-AL14-AM14),0),0),0) -> 0 | AO14: =IF(W14>1,MAX(0,MIN(W14-AH14-AJ14-AK14-AL14-AM14,W14-AH14-AJ14-AK14-AL14-AM14-X14+1)),0) -> 0.012614368 | AP14: =AI14+AO14 -> 0.19689167 | AQ14: - | AR14: =AI14/($W14-1)*100 -> 3.3163224 | AS14: =AJ14/($W14-1)*100 -> 24.728358 | AT14: =AK14/($W14-1)*100 -> 65.824023 | AU14: =AL14/($W14-1)*100 -> 5.9042839 | AV14: =AM14/($W14-1)*100 -> 0 | AW14: =AN14/($W14-1)*100 -> 0 | AX14: =AO14/($W14-1)*100 -> 0.22701282 | AY14: =AP14/($W14-1)*100 -> 3.5433352 | AZ14: - | BA14: - | BB14: - | BC14: - | BD14: - | BE14: - | BF14: - | BG14: - | BH14: ='[5]2. Distributional by deciles o'!B138 -> 5.1695228e+09 | BI14: ='[5]2. Distributional by deciles o'!B156 -> 1.0114224e+10 | BJ14: ='[5]2. Distributional by deciles o'!B174 -> 8.3475235e+08 | BK14: ='[5]2. Distributional by deciles o'!B192 -> 1.8243772e+08 | BL14: =BH14/SUM($BH14:$BK14) -> 0.31713042 | BM14: =BI14/SUM($BH14:$BK14) -> 0.62046887 | BN14: =BJ14/SUM($BH14:$BK14) -> 0.051208858 | BO14: =BK14/SUM($BH14:$BK14) -> 0.011191855 | BP14: - | BQ14: - | BR14: - | BS14: =P14/P$22*100 -> 5.8334049 | CC14: - | CD14: - | CE14: - | CF14: - | CG14: - | CH14: - | CI14: - | CK14: - | CL14: - | CM14: - | CN14: - | CO14: - | CP14: - | CQ14: - | CS14: - | CT14: - | CU14: - | CV14: - | CW14: - | CX14: - | CY14: - | DA14: - | DB14: - | DC14: - | DD14: =(1-DE14)*100 -> 3.5931418 | DE14: ='[5]2. Distributional by deciles o'!J30 -> 0.96406858 | EA14: ='[6]2. Distributional by deciles o'!B102 -> 1.4291451e+09 | EB14: ='[6]2. Distributional by deciles o'!C102 -> 1.4936509e+09 | EC14: ='[6]2. Distributional by deciles o'!D102 -> 1.4371975e+09 | ED14: ='[6]2. Distributional by deciles o'!E102 -> 1.4786772e+09 | EE14: ='[6]2. Distributional by deciles o'!F102 -> 1.4407372e+09 | EF14: ='[6]2. Distributional by deciles o'!G102 -> 1.4372552e+09 | EI14: - | EJ14: - | EK14: - | EL14: - | EM14: =EA14/EA$22*100 -> 1.9501572 | EN14: ='[6]2. Distributional by deciles o'!B120 -> 1.9546734e+10 | EO14: ='[6]2. Distributional by deciles o'!C120 -> 1.9741867e+10 | EP14: =(EO14/EN14-1)*100 -> 0.99829396 | EQ14: - | ER14: - | ES14: - | ET14: - | EU14: =EN14/EN$22*100 -> 5.7529005 | EV14: =((EB14-$EA14)/ABS($EA14)) / ($EO14/$EN14-1) -> 4.521304 | EW14: =IF(EC14<>0,((EC14-$EA14)/ABS($EA14)) / ($EO14/$EN14-1),0) -> 0.56440699 | EY14: =EV14-W14 -> -2.0353722 | EZ14: =(1-FA14)*100 -> 0.89335211 | FA14: ='[6]2. Distributional by deciles o'!I30 -> 0.99106648 | FB14: - | FC14: - | FD14: - | FE14: - | FF14: - | FG14: - | FH14: - | FI14: -
B15: 4 | C15: ='[5]2. Distributional by deciles o'!B103 -> 1.8956208e+09 | D15: ='[5]2. Distributional by deciles o'!C103 -> 1.9678829e+09 | E15: ='[5]2. Distributional by deciles o'!D103 -> 1.9152076e+09 | F15: ='[5]2. Distributional by deciles o'!E103 -> 1.9518089e+09 | G15: ='[5]2. Distributional by deciles o'!F103 -> 1.9197154e+09 | H15: ='[5]2. Distributional by deciles o'!G103 -> 1.9154323e+09 | I15: ='[5]2. Distributional by deciles o'!H103 -> 1.9154323e+09 | K15: - | L15: - | M15: - | N15: - | O15: =C15/C$22*100 -> 3.3506645 | P15: ='[5]2. Distributional by deciles o'!B121 -> 1.9440481e+10 | Q15: ='[5]2. Distributional by deciles o'!C121 -> 1.9634884e+10 | R15: =(Q15/P15-1)*100 -> 0.99998619 | S15: - | T15: - | U15: - | V15: - | W15: =IF(D15<>0,((D15-$C15)/ABS($C15)) / ($Q15/$P15-1),0) -> 3.8121034 | X15: =IF(E15<>0,((E15-$C15)/ABS($C15)) / ($Q15/$P15-1),0) -> 1.0332776 | Y15: =IF(F15<>0,MAX(((F15-$C15)/ABS($C15)) / ($Q15/$P15-1),0),0) -> 2.9641375 | Z15: =IF(G15<>0,MAX(((G15-$C15)/ABS($C15)) / ($Q15/$P15-1),0),0) -> 1.2710823 | AA15: =IF(H15<>0,MAX(((H15-$C15)/ABS($C15)) / ($Q15/$P15-1),0),0) -> 1.0451315 | AB15: =IF(I15<>0,MAX(((I15-$C15)/ABS($C15)) / ($Q15/$P15-1),0),AA15) -> 1.0451315 | AC15: =IF(J15<>0,MAX(((J15-$C15)/ABS($C15)) / ($Q15/$P15-1),0),AB15) -> 1.0451315 | AD15: - | AE15: - | AF15: - | AG15: - | AH15: =MIN(W15,1) -> 1 | AI15: =IF(W15>1,MAX(W15-SUM(AH15,AJ15:AO15),0),0) -> 0.03327764 | AJ15: =IF(W15>1,MIN($W15-Y15,W15-AH15),0) -> 0.84796589 | AK15: =IF(W15>1,MAX(MIN(Y15-Z15,W15-AH15-AJ15),0),0) -> 1.6930552 | AL15: =IF(W15>1,MAX(MIN(Z15-AA15,W15-AH15-AJ15-AK15),0),0) -> 0.22595071 | AM15: =IF(I15<>0,IF(W15>1,MAX(MIN(AA15-AB15,W15-AH15-AJ15-AK15-AL15),0),0),0) -> 0 | AN15: =IF(J15<>0,IF(W15>1,MAX(MIN(AB15-AC15,W15-AH15-AJ15-AK15-AL15-AM15),0),0),0) -> 0 | AO15: =IF(W15>1,MAX(0,MIN(W15-AH15-AJ15-AK15-AL15-AM15,W15-AH15-AJ15-AK15-AL15-AM15-X15+1)),0) -> 0.011853908 | AP15: =AI15+AO15 -> 0.045131548 | AQ15: - | AR15: =AI15/($W15-1)*100 -> 1.1833719 | AS15: =AJ15/($W15-1)*100 -> 30.154151 | AT15: =AK15/($W15-1)*100 -> 60.20601 | AU15: =AL15/($W15-1)*100 -> 8.034936 | AV15: =AM15/($W15-1)*100 -> 0 | AW15: =AN15/($W15-1)*100 -> 0 | AX15: =AO15/($W15-1)*100 -> 0.42153174 | AY15: =AP15/($W15-1)*100 -> 1.6049036 | AZ15: - | BA15: - | BB15: - | BC15: - | BD15: - | BE15: - | BF15: - | BG15: - | BH15: ='[5]2. Distributional by deciles o'!B139 -> 7.390403e+09 | BI15: ='[5]2. Distributional by deciles o'!B157 -> 1.0202753e+10 | BJ15: ='[5]2. Distributional by deciles o'!B175 -> 1.4142019e+09 | BK15: ='[5]2. Distributional by deciles o'!B193 -> 4.3312104e+08 | BL15: =BH15/SUM($BH15:$BK15) -> 0.3801554 | BM15: =BI15/SUM($BH15:$BK15) -> 0.52482005 | BN15: =BJ15/SUM($BH15:$BK15) -> 0.072745217 | BO15: =BK15/SUM($BH15:$BK15) -> 0.02227934 | BP15: - | BQ15: - | BR15: - | BS15: =P15/P$22*100 -> 6.956914 | CC15: - | CD15: - | CE15: - | CF15: - | CG15: - | CH15: - | CI15: - | CK15: - | CL15: - | CM15: - | CN15: - | CO15: - | CP15: - | CQ15: - | CS15: - | CT15: - | CU15: - | CV15: - | CW15: - | CX15: - | CY15: - | DA15: - | DB15: - | DC15: - | DD15: =(1-DE15)*100 -> 0.32938727 | DE15: ='[5]2. Distributional by deciles o'!J31 -> 0.99670613 | EA15: ='[6]2. Distributional by deciles o'!B103 -> 2.8060592e+09 | EB15: ='[6]2. Distributional by deciles o'!C103 -> 2.8985042e+09 | EC15: ='[6]2. Distributional by deciles o'!D103 -> 2.8332802e+09 | ED15: ='[6]2. Distributional by deciles o'!E103 -> 2.8776497e+09 | EE15: ='[6]2. Distributional by deciles o'!F103 -> 2.8385136e+09 | EF15: ='[6]2. Distributional by deciles o'!G103 -> 2.8333347e+09 | EI15: - | EJ15: - | EK15: - | EL15: - | EM15: =EA15/EA$22*100 -> 3.8290419 | EN15: ='[6]2. Distributional by deciles o'!B121 -> 2.4022772e+10 | EO15: ='[6]2. Distributional by deciles o'!C121 -> 2.426254e+10 | EP15: =(EO15/EN15-1)*100 -> 0.99808787 | EQ15: - | ER15: - | ES15: - | ET15: - | EU15: =EN15/EN$22*100 -> 7.0702665 | EV15: =((EB15-$EA15)/ABS($EA15)) / ($EO15/$EN15-1) -> 3.3007907 | EW15: =IF(EC15<>0,((EC15-$EA15)/ABS($EA15)) / ($EO15/$EN15-1),0) -> 0.97193755 | EY15: =EV15-W15 -> -0.51131262 | EZ15: =(1-FA15)*100 -> 0.5172064 | FA15: ='[6]2. Distributional by deciles o'!I31 -> 0.99482794 | FB15: - | FC15: - | FD15: - | FE15: - | FF15: - | FG15: - | FH15: - | FI15: -
B16: 5 | C16: ='[5]2. Distributional by deciles o'!B104 -> 2.8673942e+09 | D16: ='[5]2. Distributional by deciles o'!C104 -> 2.9505149e+09 | E16: ='[5]2. Distributional by deciles o'!D104 -> 2.896824e+09 | F16: ='[5]2. Distributional by deciles o'!E104 -> 2.9327737e+09 | G16: ='[5]2. Distributional by deciles o'!F104 -> 2.9046057e+09 | H16: ='[5]2. Distributional by deciles o'!G104 -> 2.8973806e+09 | I16: ='[5]2. Distributional by deciles o'!H104 -> 2.8973806e+09 | K16: - | L16: - | M16: - | N16: - | O16: =C16/C$22*100 -> 5.0683532 | P16: ='[5]2. Distributional by deciles o'!B122 -> 2.1748542e+10 | Q16: ='[5]2. Distributional by deciles o'!C122 -> 2.1966026e+10 | R16: =(Q16/P16-1)*100 -> 0.99998924 | S16: - | T16: - | U16: - | V16: - | W16: =IF(D16<>0,((D16-$C16)/ABS($C16)) / ($Q16/$P16-1),0) -> 2.8988533 | X16: =IF(E16<>0,((E16-$C16)/ABS($C16)) / ($Q16/$P16-1),0) -> 1.0263705 | Y16: =IF(F16<>0,MAX(((F16-$C16)/ABS($C16)) / ($Q16/$P16-1),0),0) -> 2.2801252 | Z16: =IF(G16<>0,MAX(((G16-$C16)/ABS($C16)) / ($Q16/$P16-1),0),0) -> 1.2977609 | AA16: =IF(H16<>0,MAX(((H16-$C16)/ABS($C16)) / ($Q16/$P16-1),0),0) -> 1.0457814 | AB16: =IF(I16<>0,MAX(((I16-$C16)/ABS($C16)) / ($Q16/$P16-1),0),AA16) -> 1.0457814 | AC16: =IF(J16<>0,MAX(((J16-$C16)/ABS($C16)) / ($Q16/$P16-1),0),AB16) -> 1.0457814 | AD16: - | AE16: - | AF16: - | AG16: - | AH16: =MIN(W16,1) -> 1 | AI16: =IF(W16>1,MAX(W16-SUM(AH16,AJ16:AO16),0),0) -> 0.026370498 | AJ16: =IF(W16>1,MIN($W16-Y16,W16-AH16),0) -> 0.61872808 | AK16: =IF(W16>1,MAX(MIN(Y16-Z16,W16-AH16-AJ16),0),0) -> 0.98236432 | AL16: =IF(W16>1,MAX(MIN(Z16-AA16,W16-AH16-AJ16-AK16),0),0) -> 0.25197946 | AM16: =IF(I16<>0,IF(W16>1,MAX(MIN(AA16-AB16,W16-AH16-AJ16-AK16-AL16),0),0),0) -> 0 | AN16: =IF(J16<>0,IF(W16>1,MAX(MIN(AB16-AC16,W16-AH16-AJ16-AK16-AL16-AM16),0),0),0) -> 0 | AO16: =IF(W16>1,MAX(0,MIN(W16-AH16-AJ16-AK16-AL16-AM16,W16-AH16-AJ16-AK16-AL16-AM16-X16+1)),0) -> 0.019410932 | AP16: =AI16+AO16 -> 0.04578143 | AQ16: - | AR16: =AI16/($W16-1)*100 -> 1.3887591 | AS16: =AJ16/($W16-1)*100 -> 32.584301 | AT16: =AK16/($W16-1)*100 -> 51.734609 | AU16: =AL16/($W16-1)*100 -> 13.270086 | AV16: =AM16/($W16-1)*100 -> 0 | AW16: =AN16/($W16-1)*100 -> 0 | AX16: =AO16/($W16-1)*100 -> 1.0222449 | AY16: =AP16/($W16-1)*100 -> 2.411004 | AZ16: - | BA16: - | BB16: - | BC16: - | BD16: - | BE16: - | BF16: - | BG16: - | BH16: ='[5]2. Distributional by deciles o'!B140 -> 1.2241261e+10 | BI16: ='[5]2. Distributional by deciles o'!B158 -> 7.3282879e+09 | BJ16: ='[5]2. Distributional by deciles o'!B176 -> 1.6919071e+09 | BK16: ='[5]2. Distributional by deciles o'!B194 -> 4.8708783e+08 | BL16: =BH16/SUM($BH16:$BK16) -> 0.56285428 | BM16: =BI16/SUM($BH16:$BK16) -> 0.33695533 | BN16: =BJ16/SUM($BH16:$BK16) -> 0.077794041 | BO16: =BK16/SUM($BH16:$BK16) -> 0.022396342 | BP16: - | BQ16: - | BR16: - | BS16: =P16/P$22*100 -> 7.78287 | CC16: - | CD16: - | CE16: - | CF16: - | CG16: - | CH16: - | CI16: - | CK16: - | CL16: - | CM16: - | CN16: - | CO16: - | CP16: - | CQ16: - | CS16: - | CT16: - | CU16: - | CV16: - | CW16: - | CX16: - | CY16: - | DA16: - | DB16: - | DC16: - | DD16: =(1-DE16)*100 -> 0 | DE16: ='[5]2. Distributional by deciles o'!J32 -> 1 | EA16: ='[6]2. Distributional by deciles o'!B104 -> 3.9091152e+09 | EB16: ='[6]2. Distributional by deciles o'!C104 -> 4.0125263e+09 | EC16: ='[6]2. Distributional by deciles o'!D104 -> 3.9473331e+09 | ED16: ='[6]2. Distributional by deciles o'!E104 -> 3.9902964e+09 | EE16: ='[6]2. Distributional by deciles o'!F104 -> 3.9563153e+09 | EF16: ='[6]2. Distributional by deciles o'!G104 -> 3.9474059e+09 | EI16: - | EJ16: - | EK16: - | EL16: - | EM16: =EA16/EA$22*100 -> 5.3342302 | EN16: ='[6]2. Distributional by deciles o'!B122 -> 2.6525502e+10 | EO16: ='[6]2. Distributional by deciles o'!C122 -> 2.6790238e+10 | EP16: =(EO16/EN16-1)*100 -> 0.99804348 | EQ16: - | ER16: - | ES16: - | ET16: - | EU16: =EN16/EN$22*100 -> 7.806858 | EV16: =((EB16-$EA16)/ABS($EA16)) / ($EO16/$EN16-1) -> 2.6505696 | EW16: =IF(EC16<>0,((EC16-$EA16)/ABS($EA16)) / ($EO16/$EN16-1),0) -> 0.97957855 | EY16: =EV16-W16 -> -0.24828368 | EZ16: =(1-FA16)*100 -> 0 | FA16: ='[6]2. Distributional by deciles o'!I32 -> 1 | FB16: - | FC16: - | FD16: - | FE16: - | FF16: - | FG16: - | FH16: - | FI16: -
B17: 6 | C17: ='[5]2. Distributional by deciles o'!B105 -> 4.2526059e+09 | D17: ='[5]2. Distributional by deciles o'!C105 -> 4.3555873e+09 | E17: ='[5]2. Distributional by deciles o'!D105 -> 4.2963249e+09 | F17: ='[5]2. Distributional by deciles o'!E105 -> 4.3339934e+09 | G17: ='[5]2. Distributional by deciles o'!F105 -> 4.3066167e+09 | H17: ='[5]2. Distributional by deciles o'!G105 -> 4.296841e+09 | I17: ='[5]2. Distributional by deciles o'!H105 -> 4.296841e+09 | K17: - | L17: - | M17: - | N17: - | O17: =C17/C$22*100 -> 7.5168278 | P17: ='[5]2. Distributional by deciles o'!B123 -> 2.5952554e+10 | Q17: ='[5]2. Distributional by deciles o'!C123 -> 2.6212076e+10 | R17: =(Q17/P17-1)*100 -> 0.99998782 | S17: - | T17: - | U17: - | V17: - | W17: =IF(D17<>0,((D17-$C17)/ABS($C17)) / ($Q17/$P17-1),0) -> 2.4216368 | X17: =IF(E17<>0,((E17-$C17)/ABS($C17)) / ($Q17/$P17-1),0) -> 1.028066 | Y17: =IF(F17<>0,MAX(((F17-$C17)/ABS($C17)) / ($Q17/$P17-1),0),0) -> 1.9138516 | Z17: =IF(G17<>0,MAX(((G17-$C17)/ABS($C17)) / ($Q17/$P17-1),0),0) -> 1.2700805 | AA17: =IF(H17<>0,MAX(((H17-$C17)/ABS($C17)) / ($Q17/$P17-1),0),0) -> 1.0402021 | AB17: =IF(I17<>0,MAX(((I17-$C17)/ABS($C17)) / ($Q17/$P17-1),0),AA17) -> 1.0402021 | AC17: =IF(J17<>0,MAX(((J17-$C17)/ABS($C17)) / ($Q17/$P17-1),0),AB17) -> 1.0402021 | AD17: - | AE17: - | AF17: - | AG17: - | AH17: =MIN(W17,1) -> 1 | AI17: =IF(W17>1,MAX(W17-SUM(AH17,AJ17:AO17),0),0) -> 0.028066 | AJ17: =IF(W17>1,MIN($W17-Y17,W17-AH17),0) -> 0.50778516 | AK17: =IF(W17>1,MAX(MIN(Y17-Z17,W17-AH17-AJ17),0),0) -> 0.64377114 | AL17: =IF(W17>1,MAX(MIN(Z17-AA17,W17-AH17-AJ17-AK17),0),0) -> 0.2298784 | AM17: =IF(I17<>0,IF(W17>1,MAX(MIN(AA17-AB17,W17-AH17-AJ17-AK17-AL17),0),0),0) -> 0 | AN17: =IF(J17<>0,IF(W17>1,MAX(MIN(AB17-AC17,W17-AH17-AJ17-AK17-AL17-AM17),0),0),0) -> 0 | AO17: =IF(W17>1,MAX(0,MIN(W17-AH17-AJ17-AK17-AL17-AM17,W17-AH17-AJ17-AK17-AL17-AM17-X17+1)),0) -> 0.012136068 | AP17: =AI17+AO17 -> 0.040202068 | AQ17: - | AR17: =AI17/($W17-1)*100 -> 1.9742033 | AS17: =AJ17/($W17-1)*100 -> 35.718348 | AT17: =AK17/($W17-1)*100 -> 45.283799 | AU17: =AL17/($W17-1)*100 -> 16.169981 | AV17: =AM17/($W17-1)*100 -> 0 | AW17: =AN17/($W17-1)*100 -> 0 | AX17: =AO17/($W17-1)*100 -> 0.85366867 | AY17: =AP17/($W17-1)*100 -> 2.827872 | AZ17: - | BA17: - | BB17: - | BC17: - | BD17: - | BE17: - | BF17: - | BG17: - | BH17: ='[5]2. Distributional by deciles o'!B141 -> 1.6755022e+10 | BI17: ='[5]2. Distributional by deciles o'!B159 -> 6.7177112e+09 | BJ17: ='[5]2. Distributional by deciles o'!B177 -> 1.9181017e+09 | BK17: ='[5]2. Distributional by deciles o'!B195 -> 5.6172337e+08 | BL17: =BH17/SUM($BH17:$BK17) -> 0.64560194 | BM17: =BI17/SUM($BH17:$BK17) -> 0.25884582 | BN17: =BJ17/SUM($BH17:$BK17) -> 0.073908002 | BO17: =BK17/SUM($BH17:$BK17) -> 0.021644238 | BP17: - | BQ17: - | BR17: - | BS17: =P17/P$22*100 -> 9.2873052 | CC17: - | CD17: - | CE17: - | CF17: - | CG17: - | CH17: - | CI17: - | CK17: - | CL17: - | CM17: - | CN17: - | CO17: - | CP17: - | CQ17: - | CS17: - | CT17: - | CU17: - | CV17: - | CW17: - | CX17: - | CY17: - | DA17: - | DB17: - | DC17: - | DD17: =(1-DE17)*100 -> 0 | DE17: ='[5]2. Distributional by deciles o'!J33 -> 1 | EA17: ='[6]2. Distributional by deciles o'!B105 -> 5.6726657e+09 | EB17: ='[6]2. Distributional by deciles o'!C105 -> 5.7998288e+09 | EC17: ='[6]2. Distributional by deciles o'!D105 -> 5.7295868e+09 | ED17: ='[6]2. Distributional by deciles o'!E105 -> 5.7735368e+09 | EE17: ='[6]2. Distributional by deciles o'!F105 -> 5.7411041e+09 | EF17: ='[6]2. Distributional by deciles o'!G105 -> 5.7297073e+09 | EI17: - | EJ17: - | EK17: - | EL17: - | EM17: =EA17/EA$22*100 -> 7.7407043 | EN17: ='[6]2. Distributional by deciles o'!B123 -> 3.1476472e+10 | EO17: ='[6]2. Distributional by deciles o'!C123 -> 3.1790926e+10 | EP17: =(EO17/EN17-1)*100 -> 0.99901314 | EQ17: - | ER17: - | ES17: - | ET17: - | EU17: =EN17/EN$22*100 -> 9.2640037 | EV17: =((EB17-$EA17)/ABS($EA17)) / ($EO17/$EN17-1) -> 2.2438963 | EW17: =IF(EC17<>0,((EC17-$EA17)/ABS($EA17)) / ($EO17/$EN17-1),0) -> 1.0044189 | EY17: =EV17-W17 -> -0.17774049 | EZ17: =(1-FA17)*100 -> 0 | FA17: ='[6]2. Distributional by deciles o'!I33 -> 1 | FB17: - | FC17: - | FD17: - | FE17: - | FF17: - | FG17: - | FH17: - | FI17: -
B18: 7 | C18: ='[5]2. Distributional by deciles o'!B106 -> 5.8158089e+09 | D18: ='[5]2. Distributional by deciles o'!C106 -> 5.9386368e+09 | E18: ='[5]2. Distributional by deciles o'!D106 -> 5.8767982e+09 | F18: ='[5]2. Distributional by deciles o'!E106 -> 5.9146956e+09 | G18: ='[5]2. Distributional by deciles o'!F106 -> 5.8887358e+09 | H18: ='[5]2. Distributional by deciles o'!G106 -> 5.8771996e+09 | I18: ='[5]2. Distributional by deciles o'!H106 -> 5.8771996e+09 | K18: - | L18: - | M18: - | N18: - | O18: =C18/C$22*100 -> 10.279917 | P18: ='[5]2. Distributional by deciles o'!B124 -> 2.9668273e+10 | Q18: ='[5]2. Distributional by deciles o'!C124 -> 2.9964956e+10 | R18: =(Q18/P18-1)*100 -> 1.0000015 | S18: - | T18: - | U18: - | V18: - | W18: =IF(D18<>0,((D18-$C18)/ABS($C18)) / ($Q18/$P18-1),0) -> 2.1119632 | X18: =IF(E18<>0,((E18-$C18)/ABS($C18)) / ($Q18/$P18-1),0) -> 1.0486803 | Y18: =IF(F18<>0,MAX(((F18-$C18)/ABS($C18)) / ($Q18/$P18-1),0),0) -> 1.7003066 | Z18: =IF(G18<>0,MAX(((G18-$C18)/ABS($C18)) / ($Q18/$P18-1),0),0) -> 1.2539401 | AA18: =IF(H18<>0,MAX(((H18-$C18)/ABS($C18)) / ($Q18/$P18-1),0),0) -> 1.0555817 | AB18: =IF(I18<>0,MAX(((I18-$C18)/ABS($C18)) / ($Q18/$P18-1),0),AA18) -> 1.0555817 | AC18: =IF(J18<>0,MAX(((J18-$C18)/ABS($C18)) / ($Q18/$P18-1),0),AB18) -> 1.0555817 | AD18: - | AE18: - | AF18: - | AG18: - | AH18: =MIN(W18,1) -> 1 | AI18: =IF(W18>1,MAX(W18-SUM(AH18,AJ18:AO18),0),0) -> 0.048680255 | AJ18: =IF(W18>1,MIN($W18-Y18,W18-AH18),0) -> 0.41165665 | AK18: =IF(W18>1,MAX(MIN(Y18-Z18,W18-AH18-AJ18),0),0) -> 0.44636651 | AL18: =IF(W18>1,MAX(MIN(Z18-AA18,W18-AH18-AJ18-AK18),0),0) -> 0.1983584 | AM18: =IF(I18<>0,IF(W18>1,MAX(MIN(AA18-AB18,W18-AH18-AJ18-AK18-AL18),0),0),0) -> 0 | AN18: =IF(J18<>0,IF(W18>1,MAX(MIN(AB18-AC18,W18-AH18-AJ18-AK18-AL18-AM18),0),0),0) -> 0 | AO18: =IF(W18>1,MAX(0,MIN(W18-AH18-AJ18-AK18-AL18-AM18,W18-AH18-AJ18-AK18-AL18-AM18-X18+1)),0) -> 0.0069014349 | AP18: =AI18+AO18 -> 0.05558169 | AQ18: - | AR18: =AI18/($W18-1)*100 -> 4.3778655 | AS18: =AJ18/($W18-1)*100 -> 37.020706 | AT18: =AK18/($W18-1)*100 -> 40.1422 | AU18: =AL18/($W18-1)*100 -> 17.838575 | AV18: =AM18/($W18-1)*100 -> 0 | AW18: =AN18/($W18-1)*100 -> 0 | AX18: =AO18/($W18-1)*100 -> 0.62065315 | AY18: =AP18/($W18-1)*100 -> 4.9985186 | AZ18: - | BA18: - | BB18: - | BC18: - | BD18: - | BE18: - | BF18: - | BG18: - | BH18: ='[5]2. Distributional by deciles o'!B142 -> 2.1669746e+10 | BI18: ='[5]2. Distributional by deciles o'!B160 -> 5.2503753e+09 | BJ18: ='[5]2. Distributional by deciles o'!B178 -> 2.2601267e+09 | BK18: ='[5]2. Distributional by deciles o'!B196 -> 4.8802867e+08 | BL18: =BH18/SUM($BH18:$BK18) -> 0.73040123 | BM18: =BI18/SUM($BH18:$BK18) -> 0.17696934 | BN18: =BJ18/SUM($BH18:$BK18) -> 0.076179914 | BO18: =BK18/SUM($BH18:$BK18) -> 0.016449512 | BP18: - | BQ18: - | BR18: - | BS18: =P18/P$22*100 -> 10.617002 | CC18: - | CD18: - | CE18: - | CF18: - | CG18: - | CH18: - | CI18: - | CK18: - | CL18: - | CM18: - | CN18: - | CO18: - | CP18: - | CQ18: - | CS18: - | CT18: - | CU18: - | CV18: - | CW18: - | CX18: - | CY18: - | DA18: - | DB18: - | DC18: - | DD18: =(1-DE18)*100 -> 0.1070778 | DE18: ='[5]2. Distributional by deciles o'!J34 -> 0.99892922 | EA18: ='[6]2. Distributional by deciles o'!B106 -> 7.6423869e+09 | EB18: ='[6]2. Distributional by deciles o'!C106 -> 7.800688e+09 | EC18: ='[6]2. Distributional by deciles o'!D106 -> 7.7265018e+09 | ED18: ='[6]2. Distributional by deciles o'!E106 -> 7.7706458e+09 | EE18: ='[6]2. Distributional by deciles o'!F106 -> 7.7401284e+09 | EF18: ='[6]2. Distributional by deciles o'!G106 -> 7.726656e+09 | EI18: - | EJ18: - | EK18: - | EL18: - | EM18: =EA18/EA$22*100 -> 10.428511 | EN18: ='[6]2. Distributional by deciles o'!B124 -> 3.6207602e+10 | EO18: ='[6]2. Distributional by deciles o'!C124 -> 3.6569368e+10 | EP18: =(EO18/EN18-1)*100 -> 0.99914551 | EQ18: - | ER18: - | ES18: - | ET18: - | EU18: =EN18/EN$22*100 -> 10.656447 | EV18: =((EB18-$EA18)/ABS($EA18)) / ($EO18/$EN18-1) -> 2.0731291 | EW18: =IF(EC18<>0,((EC18-$EA18)/ABS($EA18)) / ($EO18/$EN18-1),0) -> 1.1015785 | EY18: =EV18-W18 -> -0.038834196 | EZ18: =(1-FA18)*100 -> 0.10488755 | FA18: ='[6]2. Distributional by deciles o'!I34 -> 0.99895112 | FB18: - | FC18: - | FD18: - | FE18: - | FF18: - | FG18: - | FH18: - | FI18: -
B19: 8 | C19: ='[5]2. Distributional by deciles o'!B107 -> 7.6818436e+09 | D19: ='[5]2. Distributional by deciles o'!C107 -> 7.8302936e+09 | E19: ='[5]2. Distributional by deciles o'!D107 -> 7.761583e+09 | F19: ='[5]2. Distributional by deciles o'!E107 -> 7.8016598e+09 | G19: ='[5]2. Distributional by deciles o'!F107 -> 7.7758102e+09 | H19: ='[5]2. Distributional by deciles o'!G107 -> 7.7623477e+09 | I19: ='[5]2. Distributional by deciles o'!H107 -> 7.7623477e+09 | K19: - | L19: - | M19: - | N19: - | O19: =C19/C$22*100 -> 13.578285 | P19: ='[5]2. Distributional by deciles o'!B125 -> 3.4809442e+10 | Q19: ='[5]2. Distributional by deciles o'!C125 -> 3.5157537e+10 | R19: =(Q19/P19-1)*100 -> 1.000002 | S19: - | T19: - | U19: - | V19: - | W19: =IF(D19<>0,((D19-$C19)/ABS($C19)) / ($Q19/$P19-1),0) -> 1.9324757 | X19: =IF(E19<>0,((E19-$C19)/ABS($C19)) / ($Q19/$P19-1),0) -> 1.0380224 | Y19: =IF(F19<>0,MAX(((F19-$C19)/ABS($C19)) / ($Q19/$P19-1),0),0) -> 1.5597296 | Z19: =IF(G19<>0,MAX(((G19-$C19)/ABS($C19)) / ($Q19/$P19-1),0),0) -> 1.2232273 | AA19: =IF(H19<>0,MAX(((H19-$C19)/ABS($C19)) / ($Q19/$P19-1),0),0) -> 1.0479766 | AB19: =IF(I19<>0,MAX(((I19-$C19)/ABS($C19)) / ($Q19/$P19-1),0),AA19) -> 1.0479766 | AC19: =IF(J19<>0,MAX(((J19-$C19)/ABS($C19)) / ($Q19/$P19-1),0),AB19) -> 1.0479766 | AD19: - | AE19: - | AF19: - | AG19: - | AH19: =MIN(W19,1) -> 1 | AI19: =IF(W19>1,MAX(W19-SUM(AH19,AJ19:AO19),0),0) -> 0.038022399 | AJ19: =IF(W19>1,MIN($W19-Y19,W19-AH19),0) -> 0.37274615 | AK19: =IF(W19>1,MAX(MIN(Y19-Z19,W19-AH19-AJ19),0),0) -> 0.33650231 | AL19: =IF(W19>1,MAX(MIN(Z19-AA19,W19-AH19-AJ19-AK19),0),0) -> 0.1752507 | AM19: =IF(I19<>0,IF(W19>1,MAX(MIN(AA19-AB19,W19-AH19-AJ19-AK19-AL19),0),0),0) -> 0 | AN19: =IF(J19<>0,IF(W19>1,MAX(MIN(AB19-AC19,W19-AH19-AJ19-AK19-AL19-AM19),0),0),0) -> 0 | AO19: =IF(W19>1,MAX(0,MIN(W19-AH19-AJ19-AK19-AL19-AM19,W19-AH19-AJ19-AK19-AL19-AM19-X19+1)),0) -> 0.009954171 | AP19: =AI19+AO19 -> 0.04797657 | AQ19: - | AR19: =AI19/($W19-1)*100 -> 4.0775752 | AS19: =AJ19/($W19-1)*100 -> 39.973818 | AT19: =AK19/($W19-1)*100 -> 36.086978 | AU19: =AL19/($W19-1)*100 -> 18.79413 | AV19: =AM19/($W19-1)*100 -> 0 | AW19: =AN19/($W19-1)*100 -> 0 | AX19: =AO19/($W19-1)*100 -> 1.0674992 | AY19: =AP19/($W19-1)*100 -> 5.1450744 | AZ19: - | BA19: - | BB19: - | BC19: - | BD19: - | BE19: - | BF19: - | BG19: - | BH19: ='[5]2. Distributional by deciles o'!B143 -> 2.7520064e+10 | BI19: ='[5]2. Distributional by deciles o'!B161 -> 4.4620274e+09 | BJ19: ='[5]2. Distributional by deciles o'!B179 -> 2.2555738e+09 | BK19: ='[5]2. Distributional by deciles o'!B197 -> 5.7177978e+08 | BL19: =BH19/SUM($BH19:$BK19) -> 0.79059186 | BM19: =BI19/SUM($BH19:$BK19) -> 0.12818439 | BN19: =BJ19/SUM($BH19:$BK19) -> 0.064797752 | BO19: =BK19/SUM($BH19:$BK19) -> 0.016425995 | BP19: - | BQ19: - | BR19: - | BS19: =P19/P$22*100 -> 12.456805 | CC19: - | CD19: - | CE19: - | CF19: - | CG19: - | CH19: - | CI19: - | CK19: - | CL19: - | CM19: - | CN19: - | CO19: - | CP19: - | CQ19: - | CS19: - | CT19: - | CU19: - | CV19: - | CW19: - | CX19: - | CY19: - | DA19: - | DB19: - | DC19: - | DD19: =(1-DE19)*100 -> 0 | DE19: ='[5]2. Distributional by deciles o'!J35 -> 1 | EA19: ='[6]2. Distributional by deciles o'!B107 -> 9.9203176e+09 | EB19: ='[6]2. Distributional by deciles o'!C107 -> 1.0103976e+10 | EC19: ='[6]2. Distributional by deciles o'!D107 -> 1.0021261e+10 | ED19: ='[6]2. Distributional by deciles o'!E107 -> 1.0068525e+10 | EE19: ='[6]2. Distributional by deciles o'!F107 -> 1.0038263e+10 | EF19: ='[6]2. Distributional by deciles o'!G107 -> 1.0022533e+10 | EI19: - | EJ19: - | EK19: - | EL19: - | EM19: =EA19/EA$22*100 -> 13.536889 | EN19: ='[6]2. Distributional by deciles o'!B125 -> 4.2119809e+10 | EO19: ='[6]2. Distributional by deciles o'!C125 -> 4.254083e+10 | EP19: =(EO19/EN19-1)*100 -> 0.99957939 | EQ19: - | ER19: - | ES19: - | ET19: - | EU19: =EN19/EN$22*100 -> 12.396499 | EV19: =((EB19-$EA19)/ABS($EA19)) / ($EO19/$EN19-1) -> 1.8521125 | EW19: =IF(EC19<>0,((EC19-$EA19)/ABS($EA19)) / ($EO19/$EN19-1),0) -> 1.0179675 | EY19: =EV19-W19 -> -0.080363259 | EZ19: =(1-FA19)*100 -> 0 | FA19: ='[6]2. Distributional by deciles o'!I35 -> 1 | FB19: - | FC19: - | FD19: - | FE19: - | FF19: - | FG19: - | FH19: - | FI19: -
B20: 9 | C20: ='[5]2. Distributional by deciles o'!B108 -> 1.0867807e+10 | D20: ='[5]2. Distributional by deciles o'!C108 -> 1.1057491e+10 | E20: ='[5]2. Distributional by deciles o'!D108 -> 1.0980011e+10 | F20: ='[5]2. Distributional by deciles o'!E108 -> 1.1021777e+10 | G20: ='[5]2. Distributional by deciles o'!F108 -> 1.0996003e+10 | H20: ='[5]2. Distributional by deciles o'!G108 -> 1.0980487e+10 | I20: ='[5]2. Distributional by deciles o'!H108 -> 1.0980487e+10 | K20: - | L20: - | M20: - | N20: - | O20: =C20/C$22*100 -> 19.209736 | P20: ='[5]2. Distributional by deciles o'!B126 -> 4.3129455e+10 | Q20: ='[5]2. Distributional by deciles o'!C126 -> 4.3560748e+10 | R20: =(Q20/P20-1)*100 -> 0.99999752 | S20: - | T20: - | U20: - | V20: - | W20: =IF(D20<>0,((D20-$C20)/ABS($C20)) / ($Q20/$P20-1),0) -> 1.7453795 | X20: =IF(E20<>0,((E20-$C20)/ABS($C20)) / ($Q20/$P20-1),0) -> 1.0324475 | Y20: =IF(F20<>0,MAX(((F20-$C20)/ABS($C20)) / ($Q20/$P20-1),0),0) -> 1.4167591 | Z20: =IF(G20<>0,MAX(((G20-$C20)/ABS($C20)) / ($Q20/$P20-1),0),0) -> 1.1795961 | AA20: =IF(H20<>0,MAX(((H20-$C20)/ABS($C20)) / ($Q20/$P20-1),0),0) -> 1.0368256 | AB20: =IF(I20<>0,MAX(((I20-$C20)/ABS($C20)) / ($Q20/$P20-1),0),AA20) -> 1.0368256 | AC20: =IF(J20<>0,MAX(((J20-$C20)/ABS($C20)) / ($Q20/$P20-1),0),AB20) -> 1.0368256 | AD20: - | AE20: - | AF20: - | AG20: - | AH20: =MIN(W20,1) -> 1 | AI20: =IF(W20>1,MAX(W20-SUM(AH20,AJ20:AO20),0),0) -> 0.032447506 | AJ20: =IF(W20>1,MIN($W20-Y20,W20-AH20),0) -> 0.32862031 | AK20: =IF(W20>1,MAX(MIN(Y20-Z20,W20-AH20-AJ20),0),0) -> 0.23716303 | AL20: =IF(W20>1,MAX(MIN(Z20-AA20,W20-AH20-AJ20-AK20),0),0) -> 0.14277049 | AM20: =IF(I20<>0,IF(W20>1,MAX(MIN(AA20-AB20,W20-AH20-AJ20-AK20-AL20),0),0),0) -> 0 | AN20: =IF(J20<>0,IF(W20>1,MAX(MIN(AB20-AC20,W20-AH20-AJ20-AK20-AL20-AM20),0),0),0) -> 0 | AO20: =IF(W20>1,MAX(0,MIN(W20-AH20-AJ20-AK20-AL20-AM20,W20-AH20-AJ20-AK20-AL20-AM20-X20+1)),0) -> 0.0043781149 | AP20: =AI20+AO20 -> 0.036825621 | AQ20: - | AR20: =AI20/($W20-1)*100 -> 4.3531527 | AS20: =AJ20/($W20-1)*100 -> 44.087654 | AT20: =AK20/($W20-1)*100 -> 31.817757 | AU20: =AL20/($W20-1)*100 -> 19.154069 | AV20: =AM20/($W20-1)*100 -> 0 | AW20: =AN20/($W20-1)*100 -> 0 | AX20: =AO20/($W20-1)*100 -> 0.58736727 | AY20: =AP20/($W20-1)*100 -> 4.94052 | AZ20: - | BA20: - | BB20: - | BC20: - | BD20: - | BE20: - | BF20: - | BG20: - | BH20: ='[5]2. Distributional by deciles o'!B144 -> 3.4022259e+10 | BI20: ='[5]2. Distributional by deciles o'!B162 -> 4.4589493e+09 | BJ20: ='[5]2. Distributional by deciles o'!B180 -> 3.5282332e+09 | BK20: ='[5]2. Distributional by deciles o'!B198 -> 1.1200179e+09 | BL20: =BH20/SUM($BH20:$BK20) -> 0.78884038 | BM20: =BI20/SUM($BH20:$BK20) -> 0.10338523 | BN20: =BJ20/SUM($BH20:$BK20) -> 0.081805644 | BO20: =BK20/SUM($BH20:$BK20) -> 0.025968744 | BP20: - | BQ20: - | BR20: - | BS20: =P20/P$22*100 -> 15.434181 | CC20: - | CD20: - | CE20: - | CF20: - | CG20: - | CH20: - | CI20: - | CK20: - | CL20: - | CM20: - | CN20: - | CO20: - | CP20: - | CQ20: - | CS20: - | CT20: - | CU20: - | CV20: - | CW20: - | CX20: - | CY20: - | DA20: - | DB20: - | DC20: - | DD20: =(1-DE20)*100 -> 0 | DE20: ='[5]2. Distributional by deciles o'!J36 -> 1 | EA20: ='[6]2. Distributional by deciles o'!B108 -> 1.3830877e+10 | EB20: ='[6]2. Distributional by deciles o'!C108 -> 1.4063001e+10 | EC20: ='[6]2. Distributional by deciles o'!D108 -> 1.3971704e+10 | ED20: ='[6]2. Distributional by deciles o'!E108 -> 1.4019944e+10 | EE20: ='[6]2. Distributional by deciles o'!F108 -> 1.3989955e+10 | EF20: ='[6]2. Distributional by deciles o'!G108 -> 1.3971917e+10 | EI20: - | EJ20: - | EK20: - | EL20: - | EM20: =EA20/EA$22*100 -> 18.87309 | EN20: ='[6]2. Distributional by deciles o'!B126 -> 5.2114558e+10 | EO20: ='[6]2. Distributional by deciles o'!C126 -> 5.2635598e+10 | EP20: =(EO20/EN20-1)*100 -> 0.9997976 | EQ20: - | ER20: - | ES20: - | ET20: - | EU20: =EN20/EN$22*100 -> 15.338106 | EV20: =((EB20-$EA20)/ABS($EA20)) / ($EO20/$EN20-1) -> 1.6786404 | EW20: =IF(EC20<>0,((EC20-$EA20)/ABS($EA20)) / ($EO20/$EN20-1),0) -> 1.0184121 | EY20: =EV20-W20 -> -0.066739061 | EZ20: =(1-FA20)*100 -> 0 | FA20: ='[6]2. Distributional by deciles o'!I36 -> 1 | FB20: - | FC20: - | FD20: - | FE20: - | FF20: - | FG20: - | FH20: - | FI20: -
B21: 10 | C21: ='[5]2. Distributional by deciles o'!B109 -> 2.247111e+10 | D21: ='[5]2. Distributional by deciles o'!C109 -> 2.2785532e+10 | E21: ='[5]2. Distributional by deciles o'!D109 -> 2.2700334e+10 | F21: ='[5]2. Distributional by deciles o'!E109 -> 2.2742332e+10 | G21: ='[5]2. Distributional by deciles o'!F109 -> 2.2716933e+10 | H21: ='[5]2. Distributional by deciles o'!G109 -> 2.2701123e+10 | I21: ='[5]2. Distributional by deciles o'!H109 -> 2.2701123e+10 | K21: - | L21: - | M21: - | N21: - | O21: =C21/C$22*100 -> 39.71952 | P21: ='[5]2. Distributional by deciles o'!B127 -> 6.9182066e+10 | Q21: ='[5]2. Distributional by deciles o'!C127 -> 6.9873884e+10 | R21: =(Q21/P21-1)*100 -> 0.99999583 | S21: - | T21: - | U21: - | V21: - | W21: =IF(D21<>0,((D21-$C21)/ABS($C21)) / ($Q21/$P21-1),0) -> 1.3992367 | X21: =IF(E21<>0,((E21-$C21)/ABS($C21)) / ($Q21/$P21-1),0) -> 1.0200902 | Y21: =IF(F21<>0,MAX(((F21-$C21)/ABS($C21)) / ($Q21/$P21-1),0),0) -> 1.2069876 | Z21: =IF(G21<>0,MAX(((G21-$C21)/ABS($C21)) / ($Q21/$P21-1),0),0) -> 1.0939575 | AA21: =IF(H21<>0,MAX(((H21-$C21)/ABS($C21)) / ($Q21/$P21-1),0),0) -> 1.0236019 | AB21: =IF(I21<>0,MAX(((I21-$C21)/ABS($C21)) / ($Q21/$P21-1),0),AA21) -> 1.0236019 | AC21: =IF(J21<>0,MAX(((J21-$C21)/ABS($C21)) / ($Q21/$P21-1),0),AB21) -> 1.0236019 | AD21: - | AE21: - | AF21: - | AG21: - | AH21: =MIN(W21,1) -> 1 | AI21: =IF(W21>1,MAX(W21-SUM(AH21,AJ21:AO21),0),0) -> 0.020090165 | AJ21: =IF(W21>1,MIN($W21-Y21,W21-AH21),0) -> 0.19224902 | AK21: =IF(W21>1,MAX(MIN(Y21-Z21,W21-AH21-AJ21),0),0) -> 0.11303018 | AL21: =IF(W21>1,MAX(MIN(Z21-AA21,W21-AH21-AJ21-AK21),0),0) -> 0.070355574 | AM21: =IF(I21<>0,IF(W21>1,MAX(MIN(AA21-AB21,W21-AH21-AJ21-AK21-AL21),0),0),0) -> 0 | AN21: =IF(J21<>0,IF(W21>1,MAX(MIN(AB21-AC21,W21-AH21-AJ21-AK21-AL21-AM21),0),0),0) -> 0 | AO21: =IF(W21>1,MAX(0,MIN(W21-AH21-AJ21-AK21-AL21-AM21,W21-AH21-AJ21-AK21-AL21-AM21-X21+1)),0) -> 0.0035117195 | AP21: =AI21+AO21 -> 0.023601885 | AQ21: - | AR21: =AI21/($W21-1)*100 -> 5.0321443 | AS21: =AJ21/($W21-1)*100 -> 48.15415 | AT21: =AK21/($W21-1)*100 -> 28.311574 | AU21: =AL21/($W21-1)*100 -> 17.622523 | AV21: =AM21/($W21-1)*100 -> 0 | AW21: =AN21/($W21-1)*100 -> 0 | AX21: =AO21/($W21-1)*100 -> 0.87960847 | AY21: =AP21/($W21-1)*100 -> 5.9117528 | AZ21: - | BA21: - | BB21: - | BC21: - | BD21: - | BE21: - | BF21: - | BG21: - | BH21: ='[5]2. Distributional by deciles o'!B145 -> 5.1714468e+10 | BI21: ='[5]2. Distributional by deciles o'!B163 -> 9.2227908e+09 | BJ21: ='[5]2. Distributional by deciles o'!B181 -> 5.3513766e+09 | BK21: ='[5]2. Distributional by deciles o'!B199 -> 2.8934345e+09 | BL21: =BH21/SUM($BH21:$BK21) -> 0.74751259 | BM21: =BI21/SUM($BH21:$BK21) -> 0.13331187 | BN21: =BJ21/SUM($BH21:$BK21) -> 0.077352074 | BO21: =BK21/SUM($BH21:$BK21) -> 0.041823475 | BP21: - | BQ21: - | BR21: - | BS21: =P21/P$22*100 -> 24.757292 | CC21: - | CD21: - | CE21: - | CF21: - | CG21: - | CH21: - | CI21: - | CK21: - | CL21: - | CM21: - | CN21: - | CO21: - | CP21: - | CQ21: - | CS21: - | CT21: - | CU21: - | CV21: - | CW21: - | CX21: - | CY21: - | DA21: - | DB21: - | DC21: - | DD21: =(1-DE21)*100 -> 0 | DE21: ='[5]2. Distributional by deciles o'!J37 -> 1 | EA21: ='[6]2. Distributional by deciles o'!B109 -> 2.7995509e+10 | EB21: ='[6]2. Distributional by deciles o'!C109 -> 2.8377822e+10 | EC21: ='[6]2. Distributional by deciles o'!D109 -> 2.8278083e+10 | ED21: ='[6]2. Distributional by deciles o'!E109 -> 2.8326527e+10 | EE21: ='[6]2. Distributional by deciles o'!F109 -> 2.8296643e+10 | EF21: ='[6]2. Distributional by deciles o'!G109 -> 2.8278333e+10 | EI21: - | EJ21: - | EK21: - | EL21: - | EM21: =EA21/EA$22*100 -> 38.201609 | EN21: ='[6]2. Distributional by deciles o'!B127 -> 8.3878134e+10 | EO21: ='[6]2. Distributional by deciles o'!C127 -> 8.4716779e+10 | EP21: =(EO21/EN21-1)*100 -> 0.99983761 | EQ21: - | ER21: - | ES21: - | ET21: - | EU21: =EN21/EN$22*100 -> 24.686608 | EV21: =((EB21-$EA21)/ABS($EA21)) / ($EO21/$EN21-1) -> 1.3658445 | EW21: =IF(EC21<>0,((EC21-$EA21)/ABS($EA21)) / ($EO21/$EN21-1),0) -> 1.0095162 | EY21: =EV21-W21 -> -0.03339214 | EZ21: =(1-FA21)*100 -> 0 | FA21: ='[6]2. Distributional by deciles o'!I37 -> 1 | FB21: - | FC21: - | FD21: - | FE21: - | FF21: - | FG21: - | FH21: - | FI21: -
B22: Total | C22: ='[5]2. Distributional by deciles o'!B110 -> 5.6574475e+10 | D22: ='[5]2. Distributional by deciles o'!C110 -> 5.7686979e+10 | E22: ='[5]2. Distributional by deciles o'!D110 -> 5.7159168e+10 | F22: ='[5]2. Distributional by deciles o'!E110 -> 5.7483776e+10 | G22: ='[5]2. Distributional by deciles o'!F110 -> 5.7244409e+10 | H22: ='[5]2. Distributional by deciles o'!G110 -> 5.7163065e+10 | I22: ='[5]2. Distributional by deciles o'!H110 -> 5.7163065e+10 | K22: ='[7]1. Fiscal'!D11+'[7]1. Fiscal'!D12 -> 5.7338275e+10 | L22: ='[7]1. Fiscal'!E11+'[7]1. Fiscal'!E12 -> 5.6830047e+10 | M22: ='[7]1. Fiscal'!F11+'[7]1. Fiscal'!F12 -> 5.6653196e+10 | N22: ='[7]1. Fiscal'!G11+'[7]1. Fiscal'!G12 -> 5.6594928e+10 | O22: - | P22: ='[5]2. Distributional by deciles o'!B128 -> 2.7944116e+11 | Q22: ='[5]2. Distributional by deciles o'!C128 -> 2.8223556e+11 | R22: =(Q22/P22-1)*100 -> 0.99999389 | S22: ='[7]2. Distributional by deciles o'!D128 -> 2.8125018e+11 | T22: ='[7]2. Distributional by deciles o'!E128 -> 2.8015808e+11 | U22: ='[7]2. Distributional by deciles o'!F128 -> 2.7964062e+11 | V22: ='[7]2. Distributional by deciles o'!G128 -> 2.7951017e+11 | W22: =IF(D22<>0,((D22-$C22)/ABS($C22)) / ($Q22/$P22-1),0) -> 1.9664543 | X22: =IF(E22<>0,((E22-$C22)/ABS($C22)) / ($Q22/$P22-1),0) -> 1.0334991 | Y22: =IF(F22<>0,MAX(((F22-$C22)/ABS($C22)) / ($Q22/$P22-1),0),0) -> 1.6072743 | Z22: =IF(G22<>0,MAX(((G22-$C22)/ABS($C22)) / ($Q22/$P22-1),0),0) -> 1.1841713 | AA22: =IF(H22<>0,MAX(((H22-$C22)/ABS($C22)) / ($Q22/$P22-1),0),0) -> 1.0403884 | AB22: =IF(I22<>0,MAX(((I22-$C22)/ABS($C22)) / ($Q22/$P22-1),0),AA22) -> 1.0403884 | AC22: =IF(J22<>0,MAX(((J22-$C22)/ABS($C22)) / ($Q22/$P22-1),0),AB22) -> 1.0403884 | AD22: =(K22/$C22-1) / (S22/$P22-1) -> 2.0854921 | AE22: =(L22/$C22-1) / (T22/$P22-1) -> 1.7608154 | AF22: =(M22/$C22-1) / (U22/$P22-1) -> 1.9495121 | AG22: =(N22/$C22-1) / (V22/$P22-1) -> 1.4640341 | AH22: =MIN(W22,1) -> 1 | AI22: =IF(W22>1,MAX(W22-SUM(AH22,AJ22:AO22),0),0) -> 0.033499085 | AJ22: =IF(W22>1,MIN($W22-Y22,W22-AH22),0) -> 0.35917999 | AK22: =IF(W22>1,MAX(MIN(Y22-Z22,W22-AH22-AJ22),0),0) -> 0.42310299 | AL22: =IF(W22>1,MAX(MIN(Z22-AA22,W22-AH22-AJ22-AK22),0),0) -> 0.1437829 | AM22: =IF(I22<>0,IF(W22>1,MAX(MIN(AA22-AB22,W22-AH22-AJ22-AK22-AL22),0),0),0) -> 0 | AN22: =IF(J22<>0,IF(W22>1,MAX(MIN(AB22-AC22,W22-AH22-AJ22-AK22-AL22-AM22),0),0),0) -> 0 | AO22: =IF(W22>1,MAX(0,MIN(W22-AH22-AJ22-AK22-AL22-AM22,W22-AH22-AJ22-AK22-AL22-AM22-X22+1)),0) -> 0.0068893575 | AP22: =AI22+AO22 -> 0.040388443 | AQ22: - | AR22: =AI22/($W22-1)*100 -> 3.466184 | AS22: =AJ22/($W22-1)*100 -> 37.164715 | AT22: =AK22/($W22-1)*100 -> 43.778892 | AU22: =AL22/($W22-1)*100 -> 14.877361 | AV22: =AM22/($W22-1)*100 -> 0 | AW22: =AN22/($W22-1)*100 -> 0 | AX22: =AO22/($W22-1)*100 -> 0.71284874 | AY22: =AP22/($W22-1)*100 -> 4.1790327 | AZ22: 1.62 | BA22: 1.63 | BB22: 1.39 | BC22: 1.69 | BD22: =W22-AZ22 -> 0.34645432 | BE22: =AD22-BA22 -> 0.45549209 | BF22: =AF22-BB22 -> 0.55951213 | BG22: =AG22-BC22 -> -0.22596592 | BH22: ='[5]2. Distributional by deciles o'!B146 -> 1.8090122e+11 | BI22: ='[5]2. Distributional by deciles o'!B164 -> 7.1693369e+10 | BJ22: ='[5]2. Distributional by deciles o'!B182 -> 1.9945203e+10 | BK22: ='[5]2. Distributional by deciles o'!B200 -> 6.9013942e+09 | BL22: =BH22/SUM($BH22:$BK22) -> 0.64736778 | BM22: =BI22/SUM($BH22:$BK22) -> 0.25655978 | BN22: =BJ22/SUM($BH22:$BK22) -> 0.071375317 | BO22: =BK22/SUM($BH22:$BK22) -> 0.024697126 | BP22: =(AD22*BL22+AF22*BN22+AG22*BO22)/(BL22+BN22+BO22) -> 2.0517922 | BQ22: =W22-BP22 -> -0.085337901 | BR22: =BP22-AZ22 -> 0.43179222 | BS22: - | CK22: ='[5]3. Inequality and Poverty'!$B$7 -> 0.33621702 | CL22: ='[5]3. Inequality and Poverty'!$B$8 -> 0.2728555 | CM22: ='[5]3. Inequality and Poverty'!$C$7 -> 0.33621704 | CN22: ='[5]3. Inequality and Poverty'!$C$8 -> 0.27289573 | CO22: =(CK22-CL22)/CK22 -> 0.18845423 | CP22: =(CM22-CN22)/CM22 -> 0.18833462 | CQ22: =(CP22-CO22)*100 -> -0.011961443 | CR22: =CN22-CL22 -> 4.0233047e-05 | CS22: =(SUM(P20:P21))/(SUM(P12:P13)) -> 5.8466909 | CT22: =(SUM(P20:P21)-SUM(C20:C21))/(SUM(P12:P13)-SUM(C12:C13)) -> 4.0818057 | CU22: =(SUM(Q20:Q21))/(SUM(Q12:Q13)) -> 5.8466921 | CV22: =(SUM(Q20:Q21)-SUM(D20:D21))/(SUM(Q12:Q13)-SUM(D12:D13)) -> 4.0780217 | CW22: =(CS22-CT22)/CS22 -> 0.30186052 | CX22: =(CU22-CV22)/CU22 -> 0.30250786 | CY22: =(CX22-CW22)*100 -> 0.064734147 | CZ22: =CV22-CT22 -> -0.0037839827 | DA22: ='[5]3. Inequality and Poverty'!$B$34 -> 0.25452627 | DB22: ='[5]3. Inequality and Poverty'!$C$34 -> 0.25134648 | DC22: =DB22-DA22 -> -0.0031797868 | DD22: =(1-DE22)*100 -> 8.6881488 | DE22: ='[5]2. Distributional by deciles o'!J38 -> 0.91311851 | EA22: ='[6]2. Distributional by deciles o'!B110 -> 7.3283587e+10 | EB22: ='[6]2. Distributional by deciles o'!C110 -> 7.4674526e+10 | EC22: ='[6]2. Distributional by deciles o'!D110 -> 7.4024576e+10 | ED22: ='[6]2. Distributional by deciles o'!E110 -> 7.4420388e+10 | EE22: ='[6]2. Distributional by deciles o'!F110 -> 7.4122782e+10 | EF22: ='[6]2. Distributional by deciles o'!G110 -> 7.402679e+10 | EI22: ='[8]1. Fiscal'!D11+'[8]1. Fiscal'!D12 -> 7.4207512e+10 | EJ22: ='[8]1. Fiscal'!E11+'[8]1. Fiscal'!E12 -> 7.3624916e+10 | EK22: ='[8]1. Fiscal'!F11+'[8]1. Fiscal'!F12 -> 7.3373246e+10 | EL22: ='[8]1. Fiscal'!G11+'[8]1. Fiscal'!G12 -> 7.3304502e+10 | EM22: - | EN22: ='[6]2. Distributional by deciles o'!B128 -> 3.397718e+11 | EO22: ='[6]2. Distributional by deciles o'!C128 -> 3.4316672e+11 | EP22: =(EO22/EN22-1)*100 -> 0.99917583 | EQ22: ='[8]2. Distributional by deciles o'!D128 -> 3.4195108e+11 | ER22: ='[8]2. Distributional by deciles o'!E128 -> 3.4066241e+11 | ES22: ='[8]2. Distributional by deciles o'!F128 -> 3.4001029e+11 | ET22: ='[8]2. Distributional by deciles o'!G128 -> 3.3985835e+11 | EU22: - | EV22: =((EB22-$EA22)/ABS($EA22)) / ($EO22/$EN22-1) -> 1.8995894 | EW22: =IF(EC22<>0,((EC22-$EA22)/ABS($EA22)) / ($EO22/$EN22-1),0) -> 1.0119599 | EX22: =EW22-X22 -> -0.02153918 | EY22: =EV22-W22 -> -0.066864943 | EZ22: =(1-FA22)*100 -> 6.429406 | FA22: ='[6]2. Distributional by deciles o'!I38 -> 0.93570594 | FB22: =(EI22/$EA22-1) / (EQ22/$EN22-1) -> 1.9656473 | FC22: =(EJ22/$EA22-1) / (ER22/$EN22-1) -> 1.7769226 | FD22: =(EK22/$EA22-1) / (ES22/$EN22-1) -> 1.7430596 | FE22: =(EL22/$EA22-1) / (ET22/$EN22-1) -> 1.120481 | FF22: =FB22-AD22 -> -0.11984483 | FG22: =FC22-AE22 -> 0.016107202 | FH22: =FD22-AF22 -> -0.20645252 | FI22: =FE22-AG22 -> -0.34355304

Sheet 2BE
B2: Template corresponding to Part 2 of the project Fiscal Drag in Europe.
B3: Yellow cells have to be filled by you
B4: Remaing cells are automatically calculated using information from yellow cells (grey cells remain empty)
B5: Red cells are 2026 results that can be filled with fake/provisional results. When we fill them with final results (the plan is to use Dec BMPE data) turn them yellow.
B8: Country | C8: BE | D8: Belgium | E8: Updated: 11/02/2025
C10: Personal Income Tax Revenue | P10: Tax Base (il_fiscaldrag_all) | AM10: Sensitivity test
B11: Decile | C11: 2019_baseline | D11: 2020_baseline | E11: 2021_baseline | F11: 2022_baseline | G11: 2023_baseline | H11: 2023 if 2019legis unchanged (upper bound) | I11: 2023 if 2019legis indexed with tax base growth (lower bound a) | J11: 2023 if 2019legis indexed with lagged HCPI (lower bound b) | K11: 2023 if 2019legis indexed with concurrent HCPI (lower bound c) | P11: 2019_baseline | Q11: 2020_baseline | R11: 2021_baseline | S11: 2022_baseline | T11: 2023_baseline | U11: Growth rate 2023/2019 | AK11: 2023_baseline without indexation measures | AL11: pm: 2023 if 2019legis indexed with lagged CPI (lower bound x) | AM11: TBB elasticity | AN11: 2023_newbaseline | AO11: 2023_homogeneous | AP11: 2023_heterogeneous | AQ11: initial growth | AR11: adjusted growth | AS11: weight
B12: 1 | C12: ='[9]2. Distributional by deciles o'!B100 -> -1.9320262e+08 | D12: ='[9]2. Distributional by deciles o'!C100 -> -1.9217074e+08 | E12: ='[9]2. Distributional by deciles o'!D100 -> -1.9128353e+08 | F12: ='[9]2. Distributional by deciles o'!E100 -> -1.8256104e+08 | G12: ='[9]2. Distributional by deciles o'!F100 -> -2.0232015e+08 | H12: ='[9]2. Distributional by deciles o'!H100 -> -72406203 | I12: ='[9]2. Distributional by deciles o'!I100 -> -2.1368397e+08 | J12: ='[9]2. Distributional by deciles o'!J100 -> -1.8395727e+08 | K12: ='[9]2. Distributional by deciles o'!K100 -> -1.9025429e+08 | L12: =G12*(1+0.1+0.085) -> -2.3974937e+08 | M12: =$G12*(1+0.1+0) -> -2.2255216e+08 | N12: =$G12*(1+0.1+0) -> -2.2255216e+08 | O12: =$G12*(1+0.1+0) -> -2.2255216e+08 | P12: ='[9]2. Distributional by deciles o'!B118 -> 5.9810798e+09 | Q12: ='[9]2. Distributional by deciles o'!C118 -> 6.1909384e+09 | R12: ='[9]2. Distributional by deciles o'!D118 -> 6.3318039e+09 | S12: ='[9]2. Distributional by deciles o'!E118 -> 6.7811297e+09 | T12: ='[9]2. Distributional by deciles o'!F118 -> 7.3847963e+09 | U12: =T12/P12-1 -> 0.23469283 | AK12: ='[9]2. Distributional by deciles o'!L100 -> -88182820 | AL12: ='[9]2. Distributional by deciles o'!M100 -> -1.7843257e+08 | AM12: {=INDIRECT("'1"&$C$8&"'!W12")} -> 1.6516613 | AN12: =C12+C12*U12*AM12 -> -2.6809434e+08 | AO12: =C12+C12*U$22*AM12 -> -2.6209664e+08 | AP12: =C12+C12*AR12*AM12 -> -2.6809434e+08 | AQ12: =U12 -> 0.23469283 | AR12: =AQ12 -> 0.23469283 | AS12: =P12/P$22 -> 0.021403718
B13: 2 | C13: ='[9]2. Distributional by deciles o'!B101 -> 55151602 | D13: ='[9]2. Distributional by deciles o'!C101 -> 69562772 | E13: ='[9]2. Distributional by deciles o'!D101 -> 1.0415454e+08 | F13: ='[9]2. Distributional by deciles o'!E101 -> 2.0488726e+08 | G13: ='[9]2. Distributional by deciles o'!F101 -> 2.6687185e+08 | H13: ='[9]2. Distributional by deciles o'!H101 -> 8.1122772e+08 | I13: ='[9]2. Distributional by deciles o'!I101 -> 70601415 | J13: ='[9]2. Distributional by deciles o'!J101 -> 1.91082e+08 | K13: ='[9]2. Distributional by deciles o'!K101 -> 1.6237971e+08 | L13: =G13*(1+0.1+0.085) -> 3.1624314e+08 | M13: =$G13*(1+0.1+0) -> 2.9355903e+08 | N13: =$G13*(1+0.1+0) -> 2.9355903e+08 | O13: =$G13*(1+0.1+0) -> 2.9355903e+08 | P13: ='[9]2. Distributional by deciles o'!B119 -> 1.3228337e+10 | Q13: ='[9]2. Distributional by deciles o'!C119 -> 1.3616261e+10 | R13: ='[9]2. Distributional by deciles o'!D119 -> 1.3941608e+10 | S13: ='[9]2. Distributional by deciles o'!E119 -> 1.4821061e+10 | T13: ='[9]2. Distributional by deciles o'!F119 -> 1.6359976e+10 | U13: =T13/P13-1 -> 0.23673722 | AK13: ='[9]2. Distributional by deciles o'!L101 -> 8.9499366e+08 | AL13: ='[9]2. Distributional by deciles o'!M101 -> 2.1892959e+08 | AM13: {=INDIRECT("'1"&$C$8&"'!W13")} -> 34.733873 | AN13: =C13+C13*U13*AM13 -> 5.0865223e+08 | AO13: =C13+C13*U$22*AM13 -> 4.6873099e+08 | AP13: =C13+C13*AR13*AM13 -> 5.0865223e+08 | AQ13: =U13 -> 0.23673722 | AR13: =AQ13 -> 0.23673722 | AS13: =P13/P$22 -> 0.04733854
B14: 3 | C14: ='[9]2. Distributional by deciles o'!B102 -> 8.6033542e+08 | D14: ='[9]2. Distributional by deciles o'!C102 -> 9.5106916e+08 | E14: ='[9]2. Distributional by deciles o'!D102 -> 1.0351068e+09 | F14: ='[9]2. Distributional by deciles o'!E102 -> 1.2821037e+09 | G14: ='[9]2. Distributional by deciles o'!F102 -> 1.4665514e+09 | H14: ='[9]2. Distributional by deciles o'!H102 -> 2.1757091e+09 | I14: ='[9]2. Distributional by deciles o'!I102 -> 1.0838643e+09 | J14: ='[9]2. Distributional by deciles o'!J102 -> 1.3575856e+09 | K14: ='[9]2. Distributional by deciles o'!K102 -> 1.3006932e+09 | L14: =G14*(1+0.1+0.085) -> 1.7378634e+09 | M14: =$G14*(1+0.1+0) -> 1.6132065e+09 | N14: =$G14*(1+0.1+0) -> 1.6132065e+09 | O14: =$G14*(1+0.1+0) -> 1.6132065e+09 | P14: ='[9]2. Distributional by deciles o'!B120 -> 1.6300935e+10 | Q14: ='[9]2. Distributional by deciles o'!C120 -> 1.6764428e+10 | R14: ='[9]2. Distributional by deciles o'!D120 -> 1.7127268e+10 | S14: ='[9]2. Distributional by deciles o'!E120 -> 1.8129284e+10 | T14: ='[9]2. Distributional by deciles o'!F120 -> 2.000615e+10 | U14: =T14/P14-1 -> 0.22730081 | AK14: ='[9]2. Distributional by deciles o'!L102 -> 2.2516217e+09 | AL14: ='[9]2. Distributional by deciles o'!M102 -> 1.4090385e+09 | AM14: {=INDIRECT("'1"&$C$8&"'!W14")} -> 6.5566763 | AN14: =C14+C14*U14*AM14 -> 2.1425259e+09 | AO14: =C14+C14*U$22*AM14 -> 2.0782002e+09 | AP14: =C14+C14*AR14*AM14 -> 2.1425259e+09 | AQ14: =U14 -> 0.22730081 | AR14: =AQ14 -> 0.22730081 | AS14: =P14/P$22 -> 0.058334049
B15: 4 | C15: ='[9]2. Distributional by deciles o'!B103 -> 1.8956208e+09 | D15: ='[9]2. Distributional by deciles o'!C103 -> 2.0266011e+09 | E15: ='[9]2. Distributional by deciles o'!D103 -> 2.146738e+09 | F15: ='[9]2. Distributional by deciles o'!E103 -> 2.4693206e+09 | G15: ='[9]2. Distributional by deciles o'!F103 -> 2.7883368e+09 | H15: ='[9]2. Distributional by deciles o'!H103 -> 3.6176562e+09 | I15: ='[9]2. Distributional by deciles o'!I103 -> 2.3799531e+09 | J15: ='[9]2. Distributional by deciles o'!J103 -> 2.6886509e+09 | K15: ='[9]2. Distributional by deciles o'!K103 -> 2.6241344e+09 | L15: =G15*(1+0.1+0.085) -> 3.3041792e+09 | M15: =$G15*(1+0.1+0) -> 3.0671705e+09 | N15: =$G15*(1+0.1+0) -> 3.0671705e+09 | O15: =$G15*(1+0.1+0) -> 3.0671705e+09 | P15: ='[9]2. Distributional by deciles o'!B121 -> 1.9440481e+10 | Q15: ='[9]2. Distributional by deciles o'!C121 -> 2.0008369e+10 | R15: ='[9]2. Distributional by deciles o'!D121 -> 2.0430077e+10 | S15: ='[9]2. Distributional by deciles o'!E121 -> 2.165317e+10 | T15: ='[9]2. Distributional by deciles o'!F121 -> 2.3832293e+10 | U15: =T15/P15-1 -> 0.22591065 | AK15: ='[9]2. Distributional by deciles o'!L103 -> 3.6705809e+09 | AL15: ='[9]2. Distributional by deciles o'!M103 -> 2.7480944e+09 | AM15: {=INDIRECT("'1"&$C$8&"'!W15")} -> 3.8121034 | AN15: =C15+C15*U15*AM15 -> 3.5281195e+09 | AO15: =C15+C15*U$22*AM15 -> 3.4557612e+09 | AP15: =C15+C15*AR15*AM15 -> 3.5281195e+09 | AQ15: =U15 -> 0.22591065 | AR15: =AQ15 -> 0.22591065 | AS15: =P15/P$22 -> 0.06956914
B16: 5 | C16: ='[9]2. Distributional by deciles o'!B104 -> 2.8673942e+09 | D16: ='[9]2. Distributional by deciles o'!C104 -> 3.0702181e+09 | E16: ='[9]2. Distributional by deciles o'!D104 -> 3.177216e+09 | F16: ='[9]2. Distributional by deciles o'!E104 -> 3.6028098e+09 | G16: ='[9]2. Distributional by deciles o'!F104 -> 3.9560802e+09 | H16: ='[9]2. Distributional by deciles o'!H104 -> 4.7779032e+09 | I16: ='[9]2. Distributional by deciles o'!I104 -> 3.544826e+09 | J16: ='[9]2. Distributional by deciles o'!J104 -> 3.859085e+09 | K16: ='[9]2. Distributional by deciles o'!K104 -> 3.7941029e+09 | L16: =G16*(1+0.1+0.085) -> 4.6879551e+09 | M16: =$G16*(1+0.1+0) -> 4.3516882e+09 | N16: =$G16*(1+0.1+0) -> 4.3516882e+09 | O16: =$G16*(1+0.1+0) -> 4.3516882e+09 | P16: ='[9]2. Distributional by deciles o'!B122 -> 2.1748542e+10 | Q16: ='[9]2. Distributional by deciles o'!C122 -> 2.2484791e+10 | R16: ='[9]2. Distributional by deciles o'!D122 -> 2.288609e+10 | S16: ='[9]2. Distributional by deciles o'!E122 -> 2.4276449e+10 | T16: ='[9]2. Distributional by deciles o'!F122 -> 2.652787e+10 | U16: =T16/P16-1 -> 0.21975392 | AK16: ='[9]2. Distributional by deciles o'!L104 -> 4.8442522e+09 | AL16: ='[9]2. Distributional by deciles o'!M104 -> 3.9183666e+09 | AM16: {=INDIRECT("'1"&$C$8&"'!W16")} -> 2.8988533 | AN16: =C16+C16*U16*AM16 -> 4.6940229e+09 | AO16: =C16+C16*U$22*AM16 -> 4.6619674e+09 | AP16: =C16+C16*AR16*AM16 -> 4.6940229e+09 | AQ16: =U16 -> 0.21975392 | AR16: =AQ16 -> 0.21975392 | AS16: =P16/P$22 -> 0.0778287
B17: 6 | C17: ='[9]2. Distributional by deciles o'!B105 -> 4.2526059e+09 | D17: ='[9]2. Distributional by deciles o'!C105 -> 4.5433279e+09 | E17: ='[9]2. Distributional by deciles o'!D105 -> 4.6783053e+09 | F17: ='[9]2. Distributional by deciles o'!E105 -> 5.2166652e+09 | G17: ='[9]2. Distributional by deciles o'!F105 -> 5.6865463e+09 | H17: ='[9]2. Distributional by deciles o'!H105 -> 6.5765499e+09 | I17: ='[9]2. Distributional by deciles o'!I105 -> 5.2322794e+09 | J17: ='[9]2. Distributional by deciles o'!J105 -> 5.5784959e+09 | K17: ='[9]2. Distributional by deciles o'!K105 -> 5.5071933e+09 | L17: =G17*(1+0.1+0.085) -> 6.7385574e+09 | M17: =$G17*(1+0.1+0) -> 6.255201e+09 | N17: =$G17*(1+0.1+0) -> 6.255201e+09 | O17: =$G17*(1+0.1+0) -> 6.255201e+09 | P17: ='[9]2. Distributional by deciles o'!B123 -> 2.5952554e+10 | Q17: ='[9]2. Distributional by deciles o'!C123 -> 2.6886682e+10 | R17: ='[9]2. Distributional by deciles o'!D123 -> 2.7333766e+10 | S17: ='[9]2. Distributional by deciles o'!E123 -> 2.8988834e+10 | T17: ='[9]2. Distributional by deciles o'!F123 -> 3.157976e+10 | U17: =T17/P17-1 -> 0.21682669 | AK17: ='[9]2. Distributional by deciles o'!L105 -> 6.6390699e+09 | AL17: ='[9]2. Distributional by deciles o'!M105 -> 5.6432197e+09 | AM17: {=INDIRECT("'1"&$C$8&"'!W17")} -> 2.4216368 | AN17: =C17+C17*U17*AM17 -> 6.4855449e+09 | AO17: =C17+C17*U$22*AM17 -> 6.4759755e+09 | AP17: =C17+C17*AR17*AM17 -> 6.4855449e+09 | AQ17: =U17 -> 0.21682669 | AR17: =AQ17 -> 0.21682669 | AS17: =P17/P$22 -> 0.092873052
B18: 7 | C18: ='[9]2. Distributional by deciles o'!B106 -> 5.8158089e+09 | D18: ='[9]2. Distributional by deciles o'!C106 -> 6.1804838e+09 | E18: ='[9]2. Distributional by deciles o'!D106 -> 6.3520067e+09 | F18: ='[9]2. Distributional by deciles o'!E106 -> 6.998969e+09 | G18: ='[9]2. Distributional by deciles o'!F106 -> 7.5944519e+09 | H18: ='[9]2. Distributional by deciles o'!H106 -> 8.515292e+09 | I18: ='[9]2. Distributional by deciles o'!I106 -> 7.1135747e+09 | J18: ='[9]2. Distributional by deciles o'!J106 -> 7.4769735e+09 | K18: ='[9]2. Distributional by deciles o'!K106 -> 7.4022952e+09 | L18: =G18*(1+0.1+0.085) -> 8.9994255e+09 | M18: =$G18*(1+0.1+0) -> 8.3538971e+09 | N18: =$G18*(1+0.1+0) -> 8.3538971e+09 | O18: =$G18*(1+0.1+0) -> 8.3538971e+09 | P18: ='[9]2. Distributional by deciles o'!B124 -> 2.9668273e+10 | Q18: ='[9]2. Distributional by deciles o'!C124 -> 3.0745608e+10 | R18: ='[9]2. Distributional by deciles o'!D124 -> 3.1245072e+10 | S18: ='[9]2. Distributional by deciles o'!E124 -> 3.3124811e+10 | T18: ='[9]2. Distributional by deciles o'!F124 -> 3.599331e+10 | U18: =T18/P18-1 -> 0.21319197 | AK18: ='[9]2. Distributional by deciles o'!L106 -> 8.5813968e+09 | AL18: ='[9]2. Distributional by deciles o'!M106 -> 7.5451369e+09 | AM18: {=INDIRECT("'1"&$C$8&"'!W18")} -> 2.1119632 | AN18: =C18+C18*U18*AM18 -> 8.4343979e+09 | AO18: =C18+C18*U$22*AM18 -> 8.4676288e+09 | AP18: =C18+C18*AR18*AM18 -> 8.4343979e+09 | AQ18: =U18 -> 0.21319197 | AR18: =AQ18 -> 0.21319197 | AS18: =P18/P$22 -> 0.10617002
B19: 8 | C19: ='[9]2. Distributional by deciles o'!B107 -> 7.6818436e+09 | D19: ='[9]2. Distributional by deciles o'!C107 -> 8.1383531e+09 | E19: ='[9]2. Distributional by deciles o'!D107 -> 8.3366517e+09 | F19: ='[9]2. Distributional by deciles o'!E107 -> 9.1589261e+09 | G19: ='[9]2. Distributional by deciles o'!F107 -> 9.9246649e+09 | H19: ='[9]2. Distributional by deciles o'!H107 -> 1.0907678e+10 | I19: ='[9]2. Distributional by deciles o'!I107 -> 9.3553075e+09 | J19: ='[9]2. Distributional by deciles o'!J107 -> 9.7573526e+09 | K19: ='[9]2. Distributional by deciles o'!K107 -> 9.6737471e+09 | L19: =G19*(1+0.1+0.085) -> 1.1760728e+10 | M19: =$G19*(1+0.1+0) -> 1.0917131e+10 | N19: =$G19*(1+0.1+0) -> 1.0917131e+10 | O19: =$G19*(1+0.1+0) -> 1.0917131e+10 | P19: ='[9]2. Distributional by deciles o'!B125 -> 3.4809442e+10 | Q19: ='[9]2. Distributional by deciles o'!C125 -> 3.6089334e+10 | R19: ='[9]2. Distributional by deciles o'!D125 -> 3.6649558e+10 | S19: ='[9]2. Distributional by deciles o'!E125 -> 3.8807381e+10 | T19: ='[9]2. Distributional by deciles o'!F125 -> 4.2126652e+10 | U19: =T19/P19-1 -> 0.21020764 | AK19: ='[9]2. Distributional by deciles o'!L107 -> 1.1007881e+10 | AL19: ='[9]2. Distributional by deciles o'!M107 -> 9.8326237e+09 | AM19: {=INDIRECT("'1"&$C$8&"'!W19")} -> 1.9324757 | AN19: =C19+C19*U19*AM19 -> 1.0802371e+10 | AO19: =C19+C19*U$22*AM19 -> 1.0886836e+10 | AP19: =C19+C19*AR19*AM19 -> 1.0143518e+10 | AQ19: =U19 -> 0.21020764 | AR19: =U19-AP31*AS21/SUM(AS19:AS20) -> 0.16582539 | AS19: =P19/P$22 -> 0.12456805
B20: 9 | C20: ='[9]2. Distributional by deciles o'!B108 -> 1.0867807e+10 | D20: ='[9]2. Distributional by deciles o'!C108 -> 1.146881e+10 | E20: ='[9]2. Distributional by deciles o'!D108 -> 1.1752439e+10 | F20: ='[9]2. Distributional by deciles o'!E108 -> 1.2811003e+10 | G20: ='[9]2. Distributional by deciles o'!F108 -> 1.3868376e+10 | H20: ='[9]2. Distributional by deciles o'!H108 -> 1.4961451e+10 | I20: ='[9]2. Distributional by deciles o'!I108 -> 1.3225034e+10 | J20: ='[9]2. Distributional by deciles o'!J108 -> 1.3677783e+10 | K20: ='[9]2. Distributional by deciles o'!K108 -> 1.3584785e+10 | L20: =G20*(1+0.1+0.085) -> 1.6434025e+10 | M20: =$G20*(1+0.1+0) -> 1.5255213e+10 | N20: =$G20*(1+0.1+0) -> 1.5255213e+10 | O20: =$G20*(1+0.1+0) -> 1.5255213e+10 | P20: ='[9]2. Distributional by deciles o'!B126 -> 4.3129455e+10 | Q20: ='[9]2. Distributional by deciles o'!C126 -> 4.4712939e+10 | R20: ='[9]2. Distributional by deciles o'!D126 -> 4.5418533e+10 | S20: ='[9]2. Distributional by deciles o'!E126 -> 4.8164661e+10 | T20: ='[9]2. Distributional by deciles o'!F126 -> 5.2238301e+10 | U20: =T20/P20-1 -> 0.21119781 | AK20: ='[9]2. Distributional by deciles o'!L108 -> 1.5058784e+10 | AL20: ='[9]2. Distributional by deciles o'!M108 -> 1.3762305e+10 | AM20: {=INDIRECT("'1"&$C$8&"'!W20")} -> 1.7453795 | AN20: =C20+C20*U20*AM20 -> 1.4873902e+10 | AO20: =C20+C20*U$22*AM20 -> 1.4963047e+10 | AP20: =C20+C20*AR20*AM20 -> 1.4032039e+10 | AQ20: =U20 -> 0.21119781 | AR20: =U20-AP31*AS21/SUM(AS19:AS20) -> 0.16681557 | AS20: =P20/P$22 -> 0.15434181
B21: 10 | C21: ='[9]2. Distributional by deciles o'!B109 -> 2.247111e+10 | D21: ='[9]2. Distributional by deciles o'!C109 -> 2.3451922e+10 | E21: ='[9]2. Distributional by deciles o'!D109 -> 2.3973436e+10 | F21: ='[9]2. Distributional by deciles o'!E109 -> 2.5742903e+10 | G21: ='[9]2. Distributional by deciles o'!F109 -> 2.7934027e+10 | H21: ='[9]2. Distributional by deciles o'!H109 -> 2.9137002e+10 | I21: ='[9]2. Distributional by deciles o'!I109 -> 2.7220185e+10 | J21: ='[9]2. Distributional by deciles o'!J109 -> 2.7716288e+10 | K21: ='[9]2. Distributional by deciles o'!K109 -> 2.7614527e+10 | L21: =G21*(1+0.1+0.085) -> 3.3101822e+10 | M21: =$G21*(1+0.1+0) -> 3.072743e+10 | N21: =$G21*(1+0.1+0) -> 3.072743e+10 | O21: =$G21*(1+0.1+0) -> 3.072743e+10 | P21: ='[9]2. Distributional by deciles o'!B127 -> 6.9182066e+10 | Q21: ='[9]2. Distributional by deciles o'!C127 -> 7.1488043e+10 | R21: ='[9]2. Distributional by deciles o'!D127 -> 7.2742777e+10 | S21: ='[9]2. Distributional by deciles o'!E127 -> 7.7080862e+10 | T21: ='[9]2. Distributional by deciles o'!F127 -> 8.3722693e+10 | U21: =T21/P21-1 -> 0.21017913 | AK21: ='[9]2. Distributional by deciles o'!L109 -> 2.922775e+10 | AL21: ='[9]2. Distributional by deciles o'!M109 -> 2.7808681e+10 | AM21: {=INDIRECT("'1"&$C$8&"'!W21")} -> 1.3992367 | AN21: =C21+C21*U21*AM21 -> 2.9079646e+10 | AO21: =C21+C21*U$22*AM21 -> 2.9259444e+10 | AP21: =C21+C21*AR21*AM21 -> 3.0651766e+10 | AQ21: =U21 -> 0.21017913 | AR21: =U21+AP31 -> 0.26017913 | AS21: =P21/P$22 -> 0.24757292
B22: Total | C22: ='[9]2. Distributional by deciles o'!B110 -> 5.6574475e+10 | D22: ='[9]2. Distributional by deciles o'!C110 -> 5.9708177e+10 | E22: ='[9]2. Distributional by deciles o'!D110 -> 6.1364771e+10 | F22: ='[9]2. Distributional by deciles o'!E110 -> 6.7305027e+10 | G22: ='[9]2. Distributional by deciles o'!F110 -> 7.3283587e+10 | H22: ='[9]2. Distributional by deciles o'!H110 -> 8.1408062e+10 | I22: ='[9]2. Distributional by deciles o'!I110 -> 6.9011942e+10 | J22: ='[9]2. Distributional by deciles o'!J110 -> 7.2119339e+10 | K22: ='[9]2. Distributional by deciles o'!K110 -> 7.1473604e+10 | L22: =G22*(1+0.1+0.085) -> 8.684105e+10 | M22: =$G22*(1+0.1+0) -> 8.0611945e+10 | N22: =$G22*(1+0.1+0) -> 8.0611945e+10 | O22: =$G22*(1+0.1+0) -> 8.0611945e+10 | P22: ='[9]2. Distributional by deciles o'!B128 -> 2.7944116e+11 | Q22: ='[9]2. Distributional by deciles o'!C128 -> 2.8898739e+11 | R22: ='[9]2. Distributional by deciles o'!D128 -> 2.9410655e+11 | S22: ='[9]2. Distributional by deciles o'!E128 -> 3.1182764e+11 | T22: ='[9]2. Distributional by deciles o'!F128 -> 3.397718e+11 | U22: =T22/P22-1 -> 0.21589746 | AK22: ='[9]2. Distributional by deciles o'!L110 -> 8.2088147e+10 | AL22: ='[9]2. Distributional by deciles o'!M110 -> 7.2707963e+10 | AM22: {=INDIRECT("'1"&$C$8&"'!W22")} -> 1.9664543 | AN22: =SUM(AN12:AN21) -> 8.0281088e+10 | AO22: =SUM(AO12:AO21) -> 8.0455495e+10 | AP22: =SUM(AP12:AP21) -> 8.0352492e+10 | AQ22: =SUMPRODUCT(AQ12:AQ21,AS12:AS21) -> 0.21589746 | AR22: =SUMPRODUCT(AR12:AR21,AS12:AS21) -> 0.21589746
AR23: =U22 -> 0.21589746
G24: inc.growth | H24: =U22 -> 0.21589746 | K24: inc.growth | AN24: =AN22/G22-1 -> 0.095485245 | AR24: =IF(AR23-AR22<0.0000000001,"ok","wrong") -> ok
G25: laggedHCPI | H25: ='[10]Sheet 1'!$N$17 -> 0.1580233 | K25: laggedHCPI | AR25: =IF(AQ22-AR22<0.0000000001,"ok","wrong") -> ok
G26: concurr.HCPI | H26: ='[10]Sheet 1'!$O$17 -> 0.16980607 | K26: concurr.HCPI | AM26: relative to new baseline 2023 | AO26: =AO22/$AN22-1 -> 0.0021724559 | AP26: =AP22/$AN22-1 -> 0.00088942885
AM28: relative to potential fiscal drag | AO28: =(AO22-$AN22)/($W$37*1000000) -> 0.017492401 | AP28: =(AP22-$AN22)/($W$37*1000000) -> 0.0071615935
B29: Outcome: total tax revenue
AC30: Table for results (share GDP)
B31: Table for calculations | E31: For reescaling | F31: For reescaling | H31: All these are reescaled | N31: Table for results (million euros) | P31: Actual Fiscal Drag | T31: Potential Fiscal Drag | X31: Effective offsetting of Fiscal Drag | AC31: Actual Fiscal Drag | AF31: Potential Fiscal Drag | AO31: shock | AP31: 0.05
C32: Baseline (before reescaling) | D32: GDP (million euros) | E32: National Account PIT Revenue observed | F32: National Account PIT Revenue observed (euros) | G32: Reescaling factor | H32: Baseline | I32: Legislation unchanged since 2019/2023 | J32: Index with tax base growth | K32: Index with lagged HCPI | L32: Index with concurrent HCPI | M32: Baseline w/o "indexation measures" | O32: Size of reescaling | P32: Actual Fiscal Drag (wrt tax.inc.growth) | Q32: Actual Fiscal Drag (wrt lagged HCPI) | R32: Actual Fiscal Drag (wrt concurrent HCPI) | S32: Actual Fiscal Drag (wrt average index) | T32: Potential Fiscal Drag (wrt tax.inc.growth) | U32: Potential Fiscal Drag (wrt lagged HCPI) | V32: Potential Fiscal Drag (wrt concurrent HCPI) | W32: Potential Fiscal Drag (wrt average index) | X32: % Offsetting (wrt tax.inc.growth) | Y32: % Offsetting (wrt lagged HCPI) | Z32: % Offsetting (wrt concurrent HCPI) | AA32: % Offsetting (wrt average index) | AC32: Actual Fiscal Drag (wrt tax.inc.growth) | AD32: Actual Fiscal Drag (wrt lagged HCPI) | AE32: Actual Fiscal Drag (wrt concurrent HCPI) | AF32: Potential Fiscal Drag (wrt tax.inc.growth) | AG32: Potential Fiscal Drag (wrt lagged HCPI) | AH32: Potential Fiscal Drag (wrt concurrent HCPI)
B33: 2019 | C33: =C22 -> 5.6574475e+10 | D33: {=TRANSPOSE('[11]Sheet 1'!$I$14:$M$14)} -> 479444.9 | E33: =F33/D33*100/10^6 -> 11.233324 | F33: ='[12]Sheet 1'!$M$47*10^6 -> 53857600000 | G33: =F33/C33 -> 0.95197703 | H33: =C33*G33 -> 53857600000 | I33: - | J33: - | K33: - | L33: - | N33: 2019 | O33: =G33 -> 0.95197703
B34: 2020 | C34: =D22 -> 5.9708177e+10 | D34: 463750.9 | E34: =F34/D34*100/10^6 -> 11.644764 | F34: ='[12]Sheet 1'!$O$47*10^6 -> 54002700000 | G34: =F34/C34 -> 0.90444395 | H34: =C34*G34 -> 54002700000 | N34: 2020
B35: 2021 | C35: =E22 -> 6.1364771e+10 | D35: 506023.2 | E35: =F35/D35*100/10^6 -> 11.226047 | F35: ='[12]Sheet 1'!$Q$47*10^6 -> 56806400000 | G35: =F35/C35 -> 0.92571681 | H35: =C35*G35 -> 56806400000 | N35: 2021
B36: 2022 | C36: =F22 -> 6.7305027e+10 | D36: 563543.6 | E36: =F36/D36*100/10^6 -> 11.688998 | F36: ='[12]Sheet 1'!$S$47*10^6 -> 6.58726e+10 | G36: =F36/C36 -> 0.97871738 | H36: =C36*G36 -> 6.58726e+10 | N36: 2022
B37: 2023 | C37: =G22 -> 7.3283587e+10 | D37: 596320.6 | E37: =F37/D37*100/10^6 -> 11.625475 | F37: ='[12]Sheet 1'!$U$47*10^6 -> 69325100000 | G37: =F37/C37 -> 0.945984 | H37: =C37*G37 -> 69325100000 | I37: =H22*$G37 -> 7.7010724e+10 | J37: =I22*$G37 -> 6.5284193e+10 | K37: =J22*$G37 -> 6.8223741e+10 | L37: =K22*$G37 -> 6.7612885e+10 | M37: =AK22*$G37 -> 7.7654073e+10 | N37: 2023 | O37: =G37 -> 0.945984 | P37: =($H37-J37)/1000000 -> 4040.9072 | Q37: =($H37-K37)/1000000 -> 1101.3591 | R37: =($H37-L37)/1000000 -> 1712.2148 | S37: =AVERAGE(P37:R37) -> 2284.827 | T37: =($I37-J37)/1000000 -> 11726.531 | U37: =($I37-K37)/1000000 -> 8786.9829 | V37: =($I37-L37)/1000000 -> 9397.8386 | W37: =AVERAGE(T37:V37) -> 9970.4508 | X37: =(T37-P37)/T37 -> 0.65540472 | Y37: =(U37-Q37)/U37 -> 0.87466015 | Z37: =(V37-R37)/V37 -> 0.81780759 | AA37: =AVERAGE(X37:Z37) -> 0.78262415 | AC37: =P37/$D37 -> 0.0067764005 | AD37: =Q37/$D37 -> 0.0018469245 | AE37: =R37/$D37 -> 0.0028712992 | AF37: =T37/$D37 -> 0.019664809 | AG37: =U37/$D37 -> 0.014735333 | AH37: =V37/$D37 -> 0.015759708
B38: 2024 | N38: 2024
B39: 2025 | N39: 2025
B40: 2026 | N40: 2026
X41: Of which, through "indexation measures":
W42: 2023 | X42: =(($M37-$H37)/1000000)/T37 -> 0.71026747 | Y42: =(($M37-$H37)/1000000)/U37 -> 0.94787637 | Z42: =(($M37-$H37)/1000000)/V37 -> 0.88626479 | AA42: =AVERAGE(X42:Z42) -> 0.84813621
B44: Table for Figure (million euros) | D44: For reescaling | F44: All these are reescaled | U44: Table for Figure (share GDP) | W44: For reescaling | Y44: All these are reescaled
C45: Baseline simulation (before reescaling) | D45: Observed (National Accounts) | E45: Reescaling factor | F45: Baseline simulation (after reescaling) | G45: Unchanged legislation since 2019/2023 | H45: Indexing with tax base growth | I45: Indexing with lagged HCPI | J45: Indexing with concurrent HCPI | K45: Baseline w/o "indexation measures" | V45: Baseline simulation (before reescaling) | W45: Observed (National Accounts) | X45: Reescaling factor | Y45: Baseline simulation (after reescaling) | Z45: Unchanged legislation since 2019/2023 | AA45: Indexing with tax base growth | AB45: Indexing with lagged HCPI | AC45: Indexing with concurrent HCPI
B46: 2019 | C46: =C33/1000000 -> 56574.475 | D46: =F33/1000000 -> 53857.6 | F46: =H33/1000000 -> 53857.6 | U46: 2019 | V46: =C33/1000000/D33 -> 0.11799995 | W46: =F33/(D33*1000000) -> 0.11233324 | Y46: =H33/($D33*1000000) -> 0.11233324
B47: 2020 | C47: =C34/1000000 -> 59708.177 | D47: =F34/1000000 -> 54002.7 | U47: 2020 | V47: =C34/1000000/D34 -> 0.12875054 | W47: =F34/(D34*1000000) -> 0.11644764
B48: 2021 | C48: =C35/1000000 -> 61364.771 | D48: =F35/1000000 -> 56806.4 | U48: 2021 | V48: =C35/1000000/D35 -> 0.12126869 | W48: =F35/(D35*1000000) -> 0.11226047
B49: 2022 | C49: =C36/1000000 -> 67305.027 | D49: =F36/1000000 -> 65872.6 | U49: 2022 | V49: =C36/1000000/D36 -> 0.1194318 | W49: =F36/(D36*1000000) -> 0.11688998
B50: 2023 | C50: =C37/1000000 -> 73283.587 | D50: =F37/1000000 -> 69325.1 | F50: =H37/1000000 -> 69325.1 | G50: =I37/1000000 -> 77010.724 | H50: =J37/1000000 -> 65284.193 | I50: =K37/1000000 -> 68223.741 | J50: =L37/1000000 -> 67612.885 | K50: =M37/1000000 -> 77654.073 | L50: =AJ37/1000000 -> 0 | U50: 2023 | V50: =C37/1000000/D37 -> 0.12289293 | W50: =F37/(D37*1000000) -> 0.11625475 | Y50: =H37/($D37*1000000) -> 0.11625475 | Z50: =I37/($D37*1000000) -> 0.12914316 | AA50: =J37/($D37*1000000) -> 0.10947835 | AB50: =K37/($D37*1000000) -> 0.11440782 | AC50: =L37/($D37*1000000) -> 0.11338345
B51: 2024 | U51: 2024
B52: 2025 | U52: 2025
B53: 2026 | U53: 2026
B61: Outcome: average effective tax rate
B64: Table for Figure (%) | C64: Baseline simulation | D64: Legislation unchanged since 2019/2023 | E64: Index with tax base growth | F64: Index with lagged HCPI | G64: Index with concurrent HCPI
B65: 2019 | C65: =C22/P22*100 -> 20.245576
B66: 2020 | C66: =D22/Q22*100 -> 20.66117
B67: 2021 | C67: =E22/R22*100 -> 20.864809
B68: 2022 | C68: =F22/S22*100 -> 21.584048
B69: 2023 | C69: =G22/$T22*100 -> 21.568472 | D69: =H22/$T22*100 -> 23.959629 | E69: =I22/$T22*100 -> 20.311262 | F69: =J22/$T22*100 -> 21.225817 | G69: =K22/$T22*100 -> 21.035767 | H69: =AL22/$T22*100 -> 21.399058
B70: 2024
B71: 2025
B72: 2026
B77: Table for results % | C77: Baseline simulation | D77: Legislation unchanged since 2019/2023 | E77: Index with tax base growth | F77: Index with lagged HCPI | G77: Index with concurrent HCPI
B78: 2019 | C78: =C65 -> 20.245576
B79: 2020 | C79: =C66 -> 20.66117
B80: 2021 | C80: =C67 -> 20.864809
B81: 2022 | C81: =C68 -> 21.584048
B82: 2023 | C82: =C69 -> 21.568472 | D82: =D69 -> 23.959629 | E82: =E69 -> 20.311262 | F82: =F69 -> 21.225817 | G82: =G69 -> 21.035767
B83: 2024
B84: 2025
B85: 2026

Sheet 1CY
B2: Template corresponding to Part 1 of the project Fiscal Drag in Europe
B3: Yellow cells have to be filled by you (remember to rename the sheets as well)
B4: Remaing cells are automatically calculated using information from yellow cells (grey cells remain empty)
C6: 171581.1 | D6: 189038.8 | E6: 173291.77 | F6: 173291.77
B8: Country | C8: CY | D8: Cyprus | E8: Updated: 08/10/2024
C10: Personal Income Tax Revenue | P10: Tac Base (il_fiscaldrag_all) | W10: TTB | AD10: TTB by income source | AH10: Decomposition of TTB in pp | AQ10: Decomposition of fiscal drag in percentage | AZ10: OECD estimates | CC10: Ratio8020 all income | CK10: Gini tax base (from Table 3.1) | CS10: Ratio8020 tax base | DA10: Kakwani (from Table 3.2) | DD10: Share taxpayers | EA10: 2023 Personal Income Tax Revenue | EN10: 2023 Tax Base (il_fiscaldrag_all) | EV10: 2023 TTB | EZ10: 2023 Share taxpayers | FB10: 2023 TTB by income source
B11: Decile | C11: Original | D11: Incomes grow 1% | E11: Incomes & all parameters grow 1% | F11: Incomes & (only) tax brackets grow 1% | G11: Incomes & (only) tax brackets and tax benefit #1 grow 1% | H11: Incomes & tax brackets and tax benefit #1 & 2 grow 1% | I11: Incomes & tax brackets and tax benefit #1 & 2 & 3 grow 1% | K11: Labor income grows 1% | L11: Benefits and pensions grow 1% | M11: Self-employment income grows 1% | N11: Capital income grows 1% | O11: Share of total tax liability | P11: Original | Q11: Incomes grow 1% | R11: Relative change (should be 1%) | S11: Labor income grows 1% | T11: Benefits and pensions grow 1% | U11: Self-employment income grows 1% | V11: Capital income grows 1% | W11: Incomes grow 1% | X11: Incomes & all parameters grow 1% | Y11: Incomes & tax brackets grow 1% | Z11: Incomes & tax brackets and tax benefit #1 grow 1% | AA11: Incomes & tax brackets and tax benefit #1 & 2 grow 1% | AB11: Incomes & tax brackets and tax benefit #1 & 2 & 3 grow 1% | AC11: Incomes & tax brackets and tax benefit #1 & 2 & 3 & 4 grow 1% | AD11: Labor income grows 1% | AE11: Benefits and pensions grow 1% | AF11: Self-employment income grows 1% | AG11: Capital income grows 1% | AH11: Proportional effect | AI11: Residual | AJ11: By bracket progressivity | AK11: By tax benefit 1 | AL11: By tax benefit 2 | AM11: By tax benefit 3 | AN11: By tax benefit 4 | AO11: By other tax benefits | AP11: By other tax benefits and residual | AQ11: Proportional effect | AR11: Residual | AS11: By bracket progressivity | AT11: By tax benefit 1 | AU11: By tax benefit 2 | AV11: By tax benefit 3 | AX11: By other tax benefits | AY11: By other tax benefits and residual | AZ11: TTB all incomes | BA11: TTB earnings | BB11: TTB self-empl. | BC11: TTB capital | BD11: Diff. all incomes (pp) | BE11: Diff. earnings (pp) | BF11: Diff. self-empl. (pp) | BG11: Diff. capital (pp) | BH11: Labour income | BI11: Pension and benefits | BJ11: Self-employment income | BK11: Capital income | BL11: Share of labour income | BM11: Share of pension and benefits | BN11: Share of self-employment income | BO11: Share of capital income | BP11: TTB without pensions | BQ11: Diff TTB TTB_nopens | BR11: Diff TTB_nopens TTB_OECD | BS11: Share of total tax base | CC11: Ratio8020 all income preincrease pretax | CD11: Ratio8020 all income preincrease posttax | CE11: Ratio8020 all income postincrease pretax | CF11: Ratio8020 all income postincrease posttax | CG11: Ratio8020 allinc increase preincrease | CH11: Ratio8020 allinc increase postincrease | CI11: Diff Ratio8020 change allinc (pp) | CJ11: Diff Ratio8020 allinc postax (pp) | CK11: Gini tax base preincrease pretax | CL11: Gini tax base preincrease posttax | CM11: Gini tax base postincrease pretax | CN11: Gini tax base postincrease posttax | CO11: Gini taxinc reduction preincrease | CP11: Gini taxinc reduction postincrease | CQ11: Diff Gini reduction taxinc (pp) | CR11: Diff Gini tax base posttax | CS11: Ratio8020 tax base preincrease pretax | CT11: Ratio8020 tax base preincrease posttax | CU11: Ratio8020 tax base postincrease pretax | CV11: Ratio8020 tax base postincrease posttax | CW11: Ratio8020 taxinc decrease preincrease | CX11: Ratio8020 taxinc decrease postincrease | CY11: Diff Ratio8020 change taxinc (pp) | CZ11: Diff Ratio8020 taxinc postax (pp) | DA11: kawani taxinc preincrease | DB11: kawani taxinc postincrease | DC11: Diff kakwani taxinc | DD11: Share with zero tax liability (right axis) | DE11: Share with non-zero tax liability | EA11: 2023 Original | EB11: 2023 Incomes grow 1% | EC11: 2023 Incomes & all parameters grow 1% | ED11: 2023 Incomes & (only) tax brackets grow 1% | EE11: 2023 Incomes & (only) tax brackets and tax benefit #1 grow 1% | EF11: 2023 Incomes & tax brackets and tax benefit #1 & 2 grow 1% | EG11: 2023 Incomes & tax brackets and tax benefit #1 & 2 & 3 grow 1% | EI11: 2023 Labor income grows 1% | EJ11: 2023 Benefits and pensions grow 1% | EK11: 2023 Self-employment income grows 1% | EL11: 2023 Capital income grows 1% | EM11: Share of total tax liability | EN11: 2023 Original | EO11: 2023 Incomes grow 1% | EP11: 2023 Relative change (should be 1%) | EQ11: 2023 Labor income grows 1% | ER11: 2023 Benefits and pensions grow 1% | ES11: 2023 Self-employment income grows 1% | ET11: 2023 Capital income grows 1% | EU11: 2023 Share of total tax base | EV11: 2023 TTB Incomes grow 1% | EW11: 2023 Incomes & all parameters grow 1% | EX11: 2023 Diff residual (pp) | EY11: 2023 TTB change | EZ11: 2023 Share with zero tax liability (right axis) | FA11: 2023 Share with non-zero tax liability | FB11: 2023 TTB Labor income grows 1% | FC11: 2023 TTB Benefits and pensions grow 1% | FD11: 2023 TTB Self-employment income grows 1% | FE11: 2023 TTB Capital income grows 1% | FF11: 2023 TTB change Labor | FG11: 2023 TTB change Benefits and pensions | FH11: 2023 TTB change Self-employment income | FI11: 2023 TTB change Capital
B12: 1 | C12: ='[13]2. Distributional by deciles o'!B64 -> 0 | D12: ='[13]2. Distributional by deciles o'!C64 -> 0 | E12: ='[13]2. Distributional by deciles o'!D64 -> 0 | F12: ='[13]2. Distributional by deciles o'!E64 -> 0 | G12: ='[13]2. Distributional by deciles o'!F64 -> 0 | H12: =G12 -> 0 | K12: - | L12: - | M12: - | N12: - | O12: =C12/C$22*100 -> 0 | P12: ='[13]2. Distributional by deciles o'!B82 -> 1.588347e+08 | Q12: ='[13]2. Distributional by deciles o'!C82 -> 1.6042306e+08 | R12: =(Q12/P12-1)*100 -> 1.0000076 | S12: - | T12: - | U12: - | V12: - | W12: =IF(D12<>0,((D12-$C12)/ABS($C12)) / ($Q12/$P12-1),0) -> 0 | X12: =IF(E12<>0,((E12-$C12)/ABS($C12)) / ($Q12/$P12-1),0) -> 0 | Y12: =IF(F12<>0,MAX(((F12-$C12)/ABS($C12)) / ($Q12/$P12-1),0),0) -> 0 | Z12: =IF(G12<>0,MAX(((G12-$C12)/ABS($C12)) / ($Q12/$P12-1),0),0) -> 0 | AA12: =IF(H12<>0,MAX(((H12-$C12)/ABS($C12)) / ($Q12/$P12-1),0),0) -> 0 | AB12: =IF(I12<>0,MAX(((I12-$C12)/ABS($C12)) / ($Q12/$P12-1),0),AA12) -> 0 | AC12: =IF(J12<>0,MAX(((J12-$C12)/ABS($C12)) / ($Q12/$P12-1),0),AB12) -> 0 | AD12: - | AE12: - | AF12: - | AG12: - | AH12: =MIN(W12,1) -> 0 | AI12: =IF(W12>1,MAX(W12-SUM(AH12,AJ12:AO12),0),0) -> 0 | AJ12: =IF(W12>1,MIN($W12-Y12,W12-AH12),0) -> 0 | AK12: =IF(W12>1,MAX(MIN(Y12-Z12,W12-AH12-AJ12),0),0) -> 0 | AL12: =IF(W12>1,MAX(MIN(Z12-AA12,W12-AH12-AJ12-AK12),0),0) -> 0 | AM12: =IF(I12<>0,IF(W12>1,MAX(MIN(AA12-AB12,W12-AH12-AJ12-AK12-AL12),0),0),0) -> 0 | AN12: =IF(J12<>0,IF(W12>1,MAX(MIN(AB12-AC12,W12-AH12-AJ12-AK12-AL12-AM12),0),0),0) -> 0 | AO12: =IF(W12>1,MAX(0,MIN(W12-AH12-AJ12-AK12-AL12-AM12,W12-AH12-AJ12-AK12-AL12-AM12-X12+1)),0) -> 0 | AP12: =AI12+AO12 -> 0 | AQ12: - | AR12: =AI12/($W12-1)*100 -> 0 | AS12: =AJ12/($W12-1)*100 -> 0 | AT12: =AK12/($W12-1)*100 -> 0 | AU12: =AL12/($W12-1)*100 -> 0 | AV12: =AM12/($W12-1)*100 -> 0 | AW12: =AN12/($W12-1)*100 -> 0 | AX12: =AO12/($W12-1)*100 -> 0 | AY12: =AP12/($W12-1)*100 -> 0 | AZ12: - | BA12: - | BB12: - | BC12: - | BD12: - | BE12: - | BF12: - | BG12: - | BH12: ='[13]2. Distributional by deciles o'!B100 -> 92026407 | BI12: ='[13]2. Distributional by deciles o'!B118 -> 51722071 | BJ12: ='[13]2. Distributional by deciles o'!B136 -> 12856170 | BK12: ='[13]2. Distributional by deciles o'!B154 -> 2230166.8 | BL12: =BH12/SUM($BH12:$BK12) -> 0.57938436 | BM12: =BI12/SUM($BH12:$BK12) -> 0.32563435 | BN12: =BJ12/SUM($BH12:$BK12) -> 0.080940504 | BO12: =BK12/SUM($BH12:$BK12) -> 0.014040793 | BP12: - | BQ12: - | BR12: - | BS12: =P12/P$22*100 -> 1.3401225 | CC12: - | CD12: - | CE12: - | CF12: - | CG12: - | CH12: - | CI12: - | CK12: - | CL12: - | CM12: - | CN12: - | CO12: - | CP12: - | CQ12: - | CS12: - | CT12: - | CU12: - | CV12: - | CW12: - | CX12: - | CY12: - | DA12: - | DB12: - | DC12: - | DD12: =(1-DE12)*100 -> 100 | DE12: ='[13]2. Distributional by deciles o'!H28 -> 0 | EA12: ='[14]2. Distributional by deciles o'!B64 -> 0 | EB12: ='[14]2. Distributional by deciles o'!C64 -> 0 | EC12: ='[14]2. Distributional by deciles o'!D64 -> 0 | ED12: ='[14]2. Distributional by deciles o'!E64 -> 0 | EE12: ='[14]2. Distributional by deciles o'!F64 -> 0 | EF12: =EE12 -> 0 | EI12: - | EJ12: - | EK12: - | EL12: - | EM12: =EA12/EA$22*100 -> 0 | EN12: ='[14]2. Distributional by deciles o'!B82 -> 1.7920942e+08 | EO12: ='[14]2. Distributional by deciles o'!C82 -> 1.8100187e+08 | EP12: =(EO12/EN12-1)*100 -> 1.0001956 | EQ12: - | ER12: - | ES12: - | ET12: - | EU12: =EN12/EN$22*100 -> 1.3337213 | EV12: =((EB12-$EA12)/ABS($EA12)) / ($EO12/$EN12-1) -> #DIV/0! | EW12: =IF(EC12<>0,((EC12-$EA12)/ABS($EA12)) / ($EO12/$EN12-1),0) -> 0 | EY12: =EV12-W12 -> #DIV/0! | EZ12: =(1-FA12)*100 -> 100 | FA12: ='[14]2. Distributional by deciles o'!H28 -> 0 | FB12: - | FC12: - | FD12: - | FE12: - | FF12: - | FG12: - | FH12: - | FI12: -
B13: 2 | C13: ='[13]2. Distributional by deciles o'!B65 -> 171581.1 | D13: ='[13]2. Distributional by deciles o'!C65 -> 189038.8 | E13: ='[13]2. Distributional by deciles o'!D65 -> 173291.77 | F13: ='[13]2. Distributional by deciles o'!E65 -> 173291.77 | G13: ='[13]2. Distributional by deciles o'!F65 -> 173291.77 | H13: =G13 -> 173291.77 | K13: - | L13: - | M13: - | N13: - | O13: =C13/C$22*100 -> 0.020899647 | P13: ='[13]2. Distributional by deciles o'!B83 -> 4.4902594e+08 | Q13: ='[13]2. Distributional by deciles o'!C83 -> 4.5351651e+08 | R13: =(Q13/P13-1)*100 -> 1.0000706 | S13: - | T13: - | U13: - | V13: - | W13: =IF(D13<>0,((D13-$C13)/ABS($C13)) / ($Q13/$P13-1),0) -> 10.173885 | X13: =IF(E13<>0,((E13-$C13)/ABS($C13)) / ($Q13/$P13-1),0) -> 0.99693168 | Y13: =IF(F13<>0,MAX(((F13-$C13)/ABS($C13)) / ($Q13/$P13-1),0),0) -> 0.99693168 | Z13: =IF(G13<>0,MAX(((G13-$C13)/ABS($C13)) / ($Q13/$P13-1),0),0) -> 0.99693168 | AA13: =IF(H13<>0,MAX(((H13-$C13)/ABS($C13)) / ($Q13/$P13-1),0),0) -> 0.99693168 | AB13: =IF(I13<>0,MAX(((I13-$C13)/ABS($C13)) / ($Q13/$P13-1),0),AA13) -> 0.99693168 | AC13: =IF(J13<>0,MAX(((J13-$C13)/ABS($C13)) / ($Q13/$P13-1),0),AB13) -> 0.99693168 | AD13: - | AE13: - | AF13: - | AG13: - | AH13: =MIN(W13,1) -> 1 | AI13: =IF(W13>1,MAX(W13-SUM(AH13,AJ13:AO13),0),0) -> 0 | AJ13: =IF(W13>1,MIN($W13-Y13,W13-AH13),0) -> 9.1738851 | AK13: =IF(W13>1,MAX(MIN(Y13-Z13,W13-AH13-AJ13),0),0) -> 0 | AL13: =IF(W13>1,MAX(MIN(Z13-AA13,W13-AH13-AJ13-AK13),0),0) -> 0 | AM13: =IF(I13<>0,IF(W13>1,MAX(MIN(AA13-AB13,W13-AH13-AJ13-AK13-AL13),0),0),0) -> 0 | AN13: =IF(J13<>0,IF(W13>1,MAX(MIN(AB13-AC13,W13-AH13-AJ13-AK13-AL13-AM13),0),0),0) -> 0 | AO13: =IF(W13>1,MAX(0,MIN(W13-AH13-AJ13-AK13-AL13-AM13,W13-AH13-AJ13-AK13-AL13-AM13-X13+1)),0) -> 0 | AP13: =AI13+AO13 -> 0 | AQ13: - | AR13: =AI13/($W13-1)*100 -> 0 | AS13: =AJ13/($W13-1)*100 -> 100 | AT13: =AK13/($W13-1)*100 -> 0 | AU13: =AL13/($W13-1)*100 -> 0 | AV13: =AM13/($W13-1)*100 -> 0 | AW13: =AN13/($W13-1)*100 -> 0 | AX13: =AO13/($W13-1)*100 -> 0 | AY13: =AP13/($W13-1)*100 -> 0 | AZ13: - | BA13: - | BB13: - | BC13: - | BD13: - | BE13: - | BF13: - | BG13: - | BH13: ='[13]2. Distributional by deciles o'!B101 -> 2.1752044e+08 | BI13: ='[13]2. Distributional by deciles o'!B119 -> 1.8259613e+08 | BJ13: ='[13]2. Distributional by deciles o'!B137 -> 46237922 | BK13: ='[13]2. Distributional by deciles o'!B155 -> 2671511.6 | BL13: =BH13/SUM($BH13:$BK13) -> 0.48442727 | BM13: =BI13/SUM($BH13:$BK13) -> 0.40664934 | BN13: =BJ13/SUM($BH13:$BK13) -> 0.10297382 | BO13: =BK13/SUM($BH13:$BK13) -> 0.00594957 | BP13: - | BQ13: - | BR13: - | BS13: =P13/P$22*100 -> 3.7885283 | CC13: - | CD13: - | CE13: - | CF13: - | CG13: - | CH13: - | CI13: - | CK13: - | CL13: - | CM13: - | CN13: - | CO13: - | CP13: - | CQ13: - | CS13: - | CT13: - | CU13: - | CV13: - | CW13: - | CX13: - | CY13: - | DA13: - | DB13: - | DC13: - | DD13: =(1-DE13)*100 -> 98.877349 | DE13: ='[13]2. Distributional by deciles o'!H29 -> 0.011226514 | EA13: ='[14]2. Distributional by deciles o'!B65 -> 456150.25 | EB13: ='[14]2. Distributional by deciles o'!C65 -> 508094.37 | EC13: ='[14]2. Distributional by deciles o'!D65 -> 460719.9 | ED13: ='[14]2. Distributional by deciles o'!E65 -> 51944.116 | EE13: ='[14]2. Distributional by deciles o'!F65 -> 4569.6456 | EF13: =EE13 -> 4569.6456 | EI13: - | EJ13: - | EK13: - | EL13: - | EM13: =EA13/EA$22*100 -> 0.04295747 | EN13: ='[14]2. Distributional by deciles o'!B83 -> 5.0392889e+08 | EO13: ='[14]2. Distributional by deciles o'!C83 -> 5.0896852e+08 | EP13: =(EO13/EN13-1)*100 -> 1.0000674 | EQ13: - | ER13: - | ES13: - | ET13: - | EU13: =EN13/EN$22*100 -> 3.7503646 | EV13: =((EB13-$EA13)/ABS($EA13)) / ($EO13/$EN13-1) -> 11.386734 | EW13: =IF(EC13<>0,((EC13-$EA13)/ABS($EA13)) / ($EO13/$EN13-1),0) -> 1.0017176 | EY13: =EV13-W13 -> 1.2128485 | EZ13: =(1-FA13)*100 -> 100 | FA13: ='[14]2. Distributional by deciles o'!H29 -> 0 | FB13: - | FC13: - | FD13: - | FE13: - | FF13: - | FG13: - | FH13: - | FI13: -
B14: 3 | C14: ='[13]2. Distributional by deciles o'!B66 -> 1444605.3 | D14: ='[13]2. Distributional by deciles o'!C66 -> 1598354.8 | E14: ='[13]2. Distributional by deciles o'!D66 -> 1459086.6 | F14: ='[13]2. Distributional by deciles o'!E66 -> 1459086.6 | G14: ='[13]2. Distributional by deciles o'!F66 -> 1459086.6 | H14: =G14 -> 1459086.6 | K14: - | L14: - | M14: - | N14: - | O14: =C14/C$22*100 -> 0.17596192 | P14: ='[13]2. Distributional by deciles o'!B84 -> 5.8310511e+08 | Q14: ='[13]2. Distributional by deciles o'!C84 -> 5.8893653e+08 | R14: =(Q14/P14-1)*100 -> 1.0000633 | S14: - | T14: - | U14: - | V14: - | W14: =IF(D14<>0,((D14-$C14)/ABS($C14)) / ($Q14/$P14-1),0) -> 10.642337 | X14: =IF(E14<>0,((E14-$C14)/ABS($C14)) / ($Q14/$P14-1),0) -> 1.0023763 | Y14: =IF(F14<>0,MAX(((F14-$C14)/ABS($C14)) / ($Q14/$P14-1),0),0) -> 1.0023763 | Z14: =IF(G14<>0,MAX(((G14-$C14)/ABS($C14)) / ($Q14/$P14-1),0),0) -> 1.0023763 | AA14: =IF(H14<>0,MAX(((H14-$C14)/ABS($C14)) / ($Q14/$P14-1),0),0) -> 1.0023763 | AB14: =IF(I14<>0,MAX(((I14-$C14)/ABS($C14)) / ($Q14/$P14-1),0),AA14) -> 1.0023763 | AC14: =IF(J14<>0,MAX(((J14-$C14)/ABS($C14)) / ($Q14/$P14-1),0),AB14) -> 1.0023763 | AD14: - | AE14: - | AF14: - | AG14: - | AH14: =MIN(W14,1) -> 1 | AI14: =IF(W14>1,MAX(W14-SUM(AH14,AJ14:AO14),0),0) -> 0.0023763258 | AJ14: =IF(W14>1,MIN($W14-Y14,W14-AH14),0) -> 9.6399606 | AK14: =IF(W14>1,MAX(MIN(Y14-Z14,W14-AH14-AJ14),0),0) -> 0 | AL14: =IF(W14>1,MAX(MIN(Z14-AA14,W14-AH14-AJ14-AK14),0),0) -> 0 | AM14: =IF(I14<>0,IF(W14>1,MAX(MIN(AA14-AB14,W14-AH14-AJ14-AK14-AL14),0),0),0) -> 0 | AN14: =IF(J14<>0,IF(W14>1,MAX(MIN(AB14-AC14,W14-AH14-AJ14-AK14-AL14-AM14),0),0),0) -> 0 | AO14: =IF(W14>1,MAX(0,MIN(W14-AH14-AJ14-AK14-AL14-AM14,W14-AH14-AJ14-AK14-AL14-AM14-X14+1)),0) -> 2.220446e-16 | AP14: =AI14+AO14 -> 0.0023763258 | AQ14: - | AR14: =AI14/($W14-1)*100 -> 0.024644708 | AS14: =AJ14/($W14-1)*100 -> 99.975355 | AT14: =AK14/($W14-1)*100 -> 0 | AU14: =AL14/($W14-1)*100 -> 0 | AV14: =AM14/($W14-1)*100 -> 0 | AW14: =AN14/($W14-1)*100 -> 0 | AX14: =AO14/($W14-1)*100 -> 2.302809e-15 | AY14: =AP14/($W14-1)*100 -> 0.024644708 | AZ14: - | BA14: - | BB14: - | BC14: - | BD14: - | BE14: - | BF14: - | BG14: - | BH14: ='[13]2. Distributional by deciles o'!B102 -> 3.6499057e+08 | BI14: ='[13]2. Distributional by deciles o'!B120 -> 1.4428772e+08 | BJ14: ='[13]2. Distributional by deciles o'!B138 -> 69701247 | BK14: ='[13]2. Distributional by deciles o'!B156 -> 4125579.4 | BL14: =BH14/SUM($BH14:$BK14) -> 0.62594301 | BM14: =BI14/SUM($BH14:$BK14) -> 0.24744719 | BN14: =BJ14/SUM($BH14:$BK14) -> 0.11953462 | BO14: =BK14/SUM($BH14:$BK14) -> 0.0070751899 | BP14: - | BQ14: - | BR14: - | BS14: =P14/P$22*100 -> 4.9197831 | CC14: - | CD14: - | CE14: - | CF14: - | CG14: - | CH14: - | CI14: - | CK14: - | CL14: - | CM14: - | CN14: - | CO14: - | CP14: - | CQ14: - | CS14: - | CT14: - | CU14: - | CV14: - | CW14: - | CX14: - | CY14: - | DA14: - | DB14: - | DC14: - | DD14: =(1-DE14)*100 -> 88.585854 | DE14: ='[13]2. Distributional by deciles o'!H30 -> 0.11414146 | EA14: ='[14]2. Distributional by deciles o'!B66 -> 3721783 | EB14: ='[14]2. Distributional by deciles o'!C66 -> 3947898.2 | EC14: ='[14]2. Distributional by deciles o'!D66 -> 3759049.3 | ED14: ='[14]2. Distributional by deciles o'!E66 -> 226115.16 | EE14: ='[14]2. Distributional by deciles o'!F66 -> 37266.346 | EF14: =EE14 -> 37266.346 | EI14: - | EJ14: - | EK14: - | EL14: - | EM14: =EA14/EA$22*100 -> 0.350495 | EN14: ='[14]2. Distributional by deciles o'!B84 -> 6.6191161e+08 | EO14: ='[14]2. Distributional by deciles o'!C84 -> 6.6853056e+08 | EP14: =(EO14/EN14-1)*100 -> 0.99997553 | EQ14: - | ER14: - | ES14: - | ET14: - | EU14: =EN14/EN$22*100 -> 4.9261114 | EV14: =((EB14-$EA14)/ABS($EA14)) / ($EO14/$EN14-1) -> 6.0756012 | EW14: =IF(EC14<>0,((EC14-$EA14)/ABS($EA14)) / ($EO14/$EN14-1),0) -> 1.0013281 | EY14: =EV14-W14 -> -4.5667357 | EZ14: =(1-FA14)*100 -> -44964 | FA14: ='[14]2. Distributional by deciles o'!H30 -> 450.64 | FB14: - | FC14: - | FD14: - | FE14: - | FF14: - | FG14: - | FH14: - | FI14: -
B15: 4 | C15: ='[13]2. Distributional by deciles o'!B67 -> 4897896.6 | D15: ='[13]2. Distributional by deciles o'!C67 -> 5186680.6 | E15: ='[13]2. Distributional by deciles o'!D67 -> 4946874 | F15: ='[13]2. Distributional by deciles o'!E67 -> 4946874 | G15: ='[13]2. Distributional by deciles o'!F67 -> 4946874 | H15: =G15 -> 4946874 | K15: - | L15: - | M15: - | N15: - | O15: =C15/C$22*100 -> 0.59659432 | P15: ='[13]2. Distributional by deciles o'!B85 -> 7.5151917e+08 | Q15: ='[13]2. Distributional by deciles o'!C85 -> 7.590347e+08 | R15: =(Q15/P15-1)*100 -> 1.0000445 | S15: - | T15: - | U15: - | V15: - | W15: =IF(D15<>0,((D15-$C15)/ABS($C15)) / ($Q15/$P15-1),0) -> 5.8958205 | X15: =IF(E15<>0,((E15-$C15)/ABS($C15)) / ($Q15/$P15-1),0) -> 0.9999229 | Y15: =IF(F15<>0,MAX(((F15-$C15)/ABS($C15)) / ($Q15/$P15-1),0),0) -> 0.9999229 | Z15: =IF(G15<>0,MAX(((G15-$C15)/ABS($C15)) / ($Q15/$P15-1),0),0) -> 0.9999229 | AA15: =IF(H15<>0,MAX(((H15-$C15)/ABS($C15)) / ($Q15/$P15-1),0),0) -> 0.9999229 | AB15: =IF(I15<>0,MAX(((I15-$C15)/ABS($C15)) / ($Q15/$P15-1),0),AA15) -> 0.9999229 | AC15: =IF(J15<>0,MAX(((J15-$C15)/ABS($C15)) / ($Q15/$P15-1),0),AB15) -> 0.9999229 | AD15: - | AE15: - | AF15: - | AG15: - | AH15: =MIN(W15,1) -> 1 | AI15: =IF(W15>1,MAX(W15-SUM(AH15,AJ15:AO15),0),0) -> 0 | AJ15: =IF(W15>1,MIN($W15-Y15,W15-AH15),0) -> 4.8958205 | AK15: =IF(W15>1,MAX(MIN(Y15-Z15,W15-AH15-AJ15),0),0) -> 0 | AL15: =IF(W15>1,MAX(MIN(Z15-AA15,W15-AH15-AJ15-AK15),0),0) -> 0 | AM15: =IF(I15<>0,IF(W15>1,MAX(MIN(AA15-AB15,W15-AH15-AJ15-AK15-AL15),0),0),0) -> 0 | AN15: =IF(J15<>0,IF(W15>1,MAX(MIN(AB15-AC15,W15-AH15-AJ15-AK15-AL15-AM15),0),0),0) -> 0 | AO15: =IF(W15>1,MAX(0,MIN(W15-AH15-AJ15-AK15-AL15-AM15,W15-AH15-AJ15-AK15-AL15-AM15-X15+1)),0) -> 0 | AP15: =AI15+AO15 -> 0 | AQ15: - | AR15: =AI15/($W15-1)*100 -> 0 | AS15: =AJ15/($W15-1)*100 -> 100 | AT15: =AK15/($W15-1)*100 -> 0 | AU15: =AL15/($W15-1)*100 -> 0 | AV15: =AM15/($W15-1)*100 -> 0 | AW15: =AN15/($W15-1)*100 -> 0 | AX15: =AO15/($W15-1)*100 -> 0 | AY15: =AP15/($W15-1)*100 -> 0 | AZ15: - | BA15: - | BB15: - | BC15: - | BD15: - | BE15: - | BF15: - | BG15: - | BH15: ='[13]2. Distributional by deciles o'!B103 -> 5.2405913e+08 | BI15: ='[13]2. Distributional by deciles o'!B121 -> 1.2727617e+08 | BJ15: ='[13]2. Distributional by deciles o'!B139 -> 87035978 | BK15: ='[13]2. Distributional by deciles o'!B157 -> 13147838 | BL15: =BH15/SUM($BH15:$BK15) -> 0.69733306 | BM15: =BI15/SUM($BH15:$BK15) -> 0.16935853 | BN15: =BJ15/SUM($BH15:$BK15) -> 0.11581339 | BO15: =BK15/SUM($BH15:$BK15) -> 0.017495014 | BP15: - | BQ15: - | BR15: - | BS15: =P15/P$22*100 -> 6.3407287 | CC15: - | CD15: - | CE15: - | CF15: - | CG15: - | CH15: - | CI15: - | CK15: - | CL15: - | CM15: - | CN15: - | CO15: - | CP15: - | CQ15: - | CS15: - | CT15: - | CU15: - | CV15: - | CW15: - | CX15: - | CY15: - | DA15: - | DB15: - | DC15: - | DD15: =(1-DE15)*100 -> 81.084072 | DE15: ='[13]2. Distributional by deciles o'!H31 -> 0.18915928 | EA15: ='[14]2. Distributional by deciles o'!B67 -> 9260869.4 | EB15: ='[14]2. Distributional by deciles o'!C67 -> 9720096.8 | EC15: ='[14]2. Distributional by deciles o'!D67 -> 9353558.5 | ED15: ='[14]2. Distributional by deciles o'!E67 -> 459227.4 | EE15: ='[14]2. Distributional by deciles o'!F67 -> 92689.104 | EF15: =EE15 -> 92689.104 | EI15: - | EJ15: - | EK15: - | EL15: - | EM15: =EA15/EA$22*100 -> 0.87213263 | EN15: ='[14]2. Distributional by deciles o'!B85 -> 8.4683767e+08 | EO15: ='[14]2. Distributional by deciles o'!C85 -> 8.5530614e+08 | EP15: =(EO15/EN15-1)*100 -> 1.000011 | EQ15: - | ER15: - | ES15: - | ET15: - | EU15: =EN15/EN$22*100 -> 6.3023773 | EV15: =((EB15-$EA15)/ABS($EA15)) / ($EO15/$EN15-1) -> 4.9587391 | EW15: =IF(EC15<>0,((EC15-$EA15)/ABS($EA15)) / ($EO15/$EN15-1),0) -> 1.0008573 | EY15: =EV15-W15 -> -0.93708139 | EZ15: =(1-FA15)*100 -> -28893 | FA15: ='[14]2. Distributional by deciles o'!H31 -> 289.93 | FB15: - | FC15: - | FD15: - | FE15: - | FF15: - | FG15: - | FH15: - | FI15: -
B16: 5 | C16: ='[13]2. Distributional by deciles o'!B68 -> 7657774.3 | D16: ='[13]2. Distributional by deciles o'!C68 -> 8065245.3 | E16: ='[13]2. Distributional by deciles o'!D68 -> 7734398.8 | F16: ='[13]2. Distributional by deciles o'!E68 -> 7734514.6 | G16: ='[13]2. Distributional by deciles o'!F68 -> 7734398.8 | H16: =G16 -> 7734398.8 | K16: - | L16: - | M16: - | N16: - | O16: =C16/C$22*100 -> 0.93276462 | P16: ='[13]2. Distributional by deciles o'!B86 -> 9.0103515e+08 | Q16: ='[13]2. Distributional by deciles o'!C86 -> 9.1004583e+08 | R16: =(Q16/P16-1)*100 -> 1.000036 | S16: - | T16: - | U16: - | V16: - | W16: =IF(D16<>0,((D16-$C16)/ABS($C16)) / ($Q16/$P16-1),0) -> 5.3208203 | X16: =IF(E16<>0,((E16-$C16)/ABS($C16)) / ($Q16/$P16-1),0) -> 1.0005749 | Y16: =IF(F16<>0,MAX(((F16-$C16)/ABS($C16)) / ($Q16/$P16-1),0),0) -> 1.002087 | Z16: =IF(G16<>0,MAX(((G16-$C16)/ABS($C16)) / ($Q16/$P16-1),0),0) -> 1.0005749 | AA16: =IF(H16<>0,MAX(((H16-$C16)/ABS($C16)) / ($Q16/$P16-1),0),0) -> 1.0005749 | AB16: =IF(I16<>0,MAX(((I16-$C16)/ABS($C16)) / ($Q16/$P16-1),0),AA16) -> 1.0005749 | AC16: =IF(J16<>0,MAX(((J16-$C16)/ABS($C16)) / ($Q16/$P16-1),0),AB16) -> 1.0005749 | AD16: - | AE16: - | AF16: - | AG16: - | AH16: =MIN(W16,1) -> 1 | AI16: =IF(W16>1,MAX(W16-SUM(AH16,AJ16:AO16),0),0) -> 0.00057491703 | AJ16: =IF(W16>1,MIN($W16-Y16,W16-AH16),0) -> 4.3187332 | AK16: =IF(W16>1,MAX(MIN(Y16-Z16,W16-AH16-AJ16),0),0) -> 0.0015121029 | AL16: =IF(W16>1,MAX(MIN(Z16-AA16,W16-AH16-AJ16-AK16),0),0) -> 0 | AM16: =IF(I16<>0,IF(W16>1,MAX(MIN(AA16-AB16,W16-AH16-AJ16-AK16-AL16),0),0),0) -> 0 | AN16: =IF(J16<>0,IF(W16>1,MAX(MIN(AB16-AC16,W16-AH16-AJ16-AK16-AL16-AM16),0),0),0) -> 0 | AO16: =IF(W16>1,MAX(0,MIN(W16-AH16-AJ16-AK16-AL16-AM16,W16-AH16-AJ16-AK16-AL16-AM16-X16+1)),0) -> 0 | AP16: =AI16+AO16 -> 0.00057491703 | AQ16: - | AR16: =AI16/($W16-1)*100 -> 0.013305738 | AS16: =AJ16/($W16-1)*100 -> 99.951699 | AT16: =AK16/($W16-1)*100 -> 0.034995738 | AU16: =AL16/($W16-1)*100 -> 0 | AV16: =AM16/($W16-1)*100 -> 0 | AW16: =AN16/($W16-1)*100 -> 0 | AX16: =AO16/($W16-1)*100 -> 0 | AY16: =AP16/($W16-1)*100 -> 0.013305738 | AZ16: - | BA16: - | BB16: - | BC16: - | BD16: - | BE16: - | BF16: - | BG16: - | BH16: ='[13]2. Distributional by deciles o'!B104 -> 6.6631284e+08 | BI16: ='[13]2. Distributional by deciles o'!B122 -> 1.0434476e+08 | BJ16: ='[13]2. Distributional by deciles o'!B140 -> 1.1320199e+08 | BK16: ='[13]2. Distributional by deciles o'!B158 -> 17175651 | BL16: =BH16/SUM($BH16:$BK16) -> 0.73949698 | BM16: =BI16/SUM($BH16:$BK16) -> 0.11580542 | BN16: =BJ16/SUM($BH16:$BK16) -> 0.12563547 | BO16: =BK16/SUM($BH16:$BK16) -> 0.01906213 | BP16: - | BQ16: - | BR16: - | BS16: =P16/P$22*100 -> 7.6022272 | CC16: - | CD16: - | CE16: - | CF16: - | CG16: - | CH16: - | CI16: - | CK16: - | CL16: - | CM16: - | CN16: - | CO16: - | CP16: - | CQ16: - | CS16: - | CT16: - | CU16: - | CV16: - | CW16: - | CX16: - | CY16: - | DA16: - | DB16: - | DC16: - | DD16: =(1-DE16)*100 -> 75.201801 | DE16: ='[13]2. Distributional by deciles o'!H32 -> 0.24798199 | EA16: ='[14]2. Distributional by deciles o'!B68 -> 13628937 | EB16: ='[14]2. Distributional by deciles o'!C68 -> 14296984 | EC16: ='[14]2. Distributional by deciles o'!D68 -> 13765329 | ED16: ='[14]2. Distributional by deciles o'!E68 -> 668046.93 | EE16: ='[14]2. Distributional by deciles o'!F68 -> 136391.95 | EF16: =EE16 -> 136391.95 | EI16: - | EJ16: - | EK16: - | EL16: - | EM16: =EA16/EA$22*100 -> 1.2834908 | EN16: ='[14]2. Distributional by deciles o'!B86 -> 1.026793e+09 | EO16: ='[14]2. Distributional by deciles o'!C86 -> 1.0370611e+09 | EP16: =(EO16/EN16-1)*100 -> 1.0000161 | EQ16: - | ER16: - | ES16: - | ET16: - | EU16: =EN16/EN$22*100 -> 7.6416498 | EV16: =((EB16-$EA16)/ABS($EA16)) / ($EO16/$EN16-1) -> 4.9016012 | EW16: =IF(EC16<>0,((EC16-$EA16)/ABS($EA16)) / ($EO16/$EN16-1),0) -> 1.0007365 | EY16: =EV16-W16 -> -0.41921909 | EZ16: =(1-FA16)*100 -> -43186 | FA16: ='[14]2. Distributional by deciles o'!H32 -> 432.86 | FB16: - | FC16: - | FD16: - | FE16: - | FF16: - | FG16: - | FH16: - | FI16: -
B17: 6 | C17: ='[13]2. Distributional by deciles o'!B69 -> 18900666 | D17: ='[13]2. Distributional by deciles o'!C69 -> 19756719 | E17: ='[13]2. Distributional by deciles o'!D69 -> 19089937 | F17: ='[13]2. Distributional by deciles o'!E69 -> 19090269 | G17: ='[13]2. Distributional by deciles o'!F69 -> 19089937 | H17: =G17 -> 19089937 | K17: - | L17: - | M17: - | N17: - | O17: =C17/C$22*100 -> 2.3022188 | P17: ='[13]2. Distributional by deciles o'!B87 -> 1.0401274e+09 | Q17: ='[13]2. Distributional by deciles o'!C87 -> 1.050529e+09 | R17: =(Q17/P17-1)*100 -> 1.0000316 | S17: - | T17: - | U17: - | V17: - | W17: =IF(D17<>0,((D17-$C17)/ABS($C17)) / ($Q17/$P17-1),0) -> 4.5290819 | X17: =IF(E17<>0,((E17-$C17)/ABS($C17)) / ($Q17/$P17-1),0) -> 1.001367 | Y17: =IF(F17<>0,MAX(((F17-$C17)/ABS($C17)) / ($Q17/$P17-1),0),0) -> 1.0031264 | Z17: =IF(G17<>0,MAX(((G17-$C17)/ABS($C17)) / ($Q17/$P17-1),0),0) -> 1.001367 | AA17: =IF(H17<>0,MAX(((H17-$C17)/ABS($C17)) / ($Q17/$P17-1),0),0) -> 1.001367 | AB17: =IF(I17<>0,MAX(((I17-$C17)/ABS($C17)) / ($Q17/$P17-1),0),AA17) -> 1.001367 | AC17: =IF(J17<>0,MAX(((J17-$C17)/ABS($C17)) / ($Q17/$P17-1),0),AB17) -> 1.001367 | AD17: - | AE17: - | AF17: - | AG17: - | AH17: =MIN(W17,1) -> 1 | AI17: =IF(W17>1,MAX(W17-SUM(AH17,AJ17:AO17),0),0) -> 0.0013670014 | AJ17: =IF(W17>1,MIN($W17-Y17,W17-AH17),0) -> 3.5259556 | AK17: =IF(W17>1,MAX(MIN(Y17-Z17,W17-AH17-AJ17),0),0) -> 0.0017593555 | AL17: =IF(W17>1,MAX(MIN(Z17-AA17,W17-AH17-AJ17-AK17),0),0) -> 0 | AM17: =IF(I17<>0,IF(W17>1,MAX(MIN(AA17-AB17,W17-AH17-AJ17-AK17-AL17),0),0),0) -> 0 | AN17: =IF(J17<>0,IF(W17>1,MAX(MIN(AB17-AC17,W17-AH17-AJ17-AK17-AL17-AM17),0),0),0) -> 0 | AO17: =IF(W17>1,MAX(0,MIN(W17-AH17-AJ17-AK17-AL17-AM17,W17-AH17-AJ17-AK17-AL17-AM17-X17+1)),0) -> 0 | AP17: =AI17+AO17 -> 0.0013670014 | AQ17: - | AR17: =AI17/($W17-1)*100 -> 0.038735327 | AS17: =AJ17/($W17-1)*100 -> 99.911412 | AT17: =AK17/($W17-1)*100 -> 0.049853064 | AU17: =AL17/($W17-1)*100 -> 0 | AV17: =AM17/($W17-1)*100 -> 0 | AW17: =AN17/($W17-1)*100 -> 0 | AX17: =AO17/($W17-1)*100 -> 0 | AY17: =AP17/($W17-1)*100 -> 0.038735327 | AZ17: - | BA17: - | BB17: - | BC17: - | BD17: - | BE17: - | BF17: - | BG17: - | BH17: ='[13]2. Distributional by deciles o'!B105 -> 8.0937198e+08 | BI17: ='[13]2. Distributional by deciles o'!B123 -> 97405130 | BJ17: ='[13]2. Distributional by deciles o'!B141 -> 1.1460206e+08 | BK17: ='[13]2. Distributional by deciles o'!B159 -> 18748135 | BL17: =BH17/SUM($BH17:$BK17) -> 0.77814703 | BM17: =BI17/SUM($BH17:$BK17) -> 0.093647315 | BN17: =BJ17/SUM($BH17:$BK17) -> 0.1101808 | BO17: =BK17/SUM($BH17:$BK17) -> 0.018024847 | BP17: - | BQ17: - | BR17: - | BS17: =P17/P$22*100 -> 8.775778 | CC17: - | CD17: - | CE17: - | CF17: - | CG17: - | CH17: - | CI17: - | CK17: - | CL17: - | CM17: - | CN17: - | CO17: - | CP17: - | CQ17: - | CS17: - | CT17: - | CU17: - | CV17: - | CW17: - | CX17: - | CY17: - | DA17: - | DB17: - | DC17: - | DD17: =(1-DE17)*100 -> 49.124206 | DE17: ='[13]2. Distributional by deciles o'!H33 -> 0.50875794 | EA17: ='[14]2. Distributional by deciles o'!B69 -> 30548561 | EB17: ='[14]2. Distributional by deciles o'!C69 -> 31765346 | EC17: ='[14]2. Distributional by deciles o'!D69 -> 30854791 | ED17: ='[14]2. Distributional by deciles o'!E69 -> 1216785.2 | EE17: ='[14]2. Distributional by deciles o'!F69 -> 306230.27 | EF17: =EE17 -> 306230.27 | EI17: - | EJ17: - | EK17: - | EL17: - | EM17: =EA17/EA$22*100 -> 2.8768786 | EN17: ='[14]2. Distributional by deciles o'!B87 -> 1.1770277e+09 | EO17: ='[14]2. Distributional by deciles o'!C87 -> 1.1887979e+09 | EP17: =(EO17/EN17-1)*100 -> 0.99999337 | EQ17: - | ER17: - | ES17: - | ET17: - | EU17: =EN17/EN$22*100 -> 8.7597336 | EV17: =((EB17-$EA17)/ABS($EA17)) / ($EO17/$EN17-1) -> 3.9831444 | EW17: =IF(EC17<>0,((EC17-$EA17)/ABS($EA17)) / ($EO17/$EN17-1),0) -> 1.0024443 | EY17: =EV17-W17 -> -0.54593754 | EZ17: =(1-FA17)*100 -> -47477 | FA17: ='[14]2. Distributional by deciles o'!H33 -> 475.77 | FB17: - | FC17: - | FD17: - | FE17: - | FF17: - | FG17: - | FH17: - | FI17: -
B18: 7 | C18: ='[13]2. Distributional by deciles o'!B70 -> 36663739 | D18: ='[13]2. Distributional by deciles o'!C70 -> 38067248 | E18: ='[13]2. Distributional by deciles o'!D70 -> 37030770 | F18: ='[13]2. Distributional by deciles o'!E70 -> 37031665 | G18: ='[13]2. Distributional by deciles o'!F70 -> 37030770 | H18: =G18 -> 37030770 | K18: - | L18: - | M18: - | N18: - | O18: =C18/C$22*100 -> 4.4658719 | P18: ='[13]2. Distributional by deciles o'!B88 -> 1.2206351e+09 | Q18: ='[13]2. Distributional by deciles o'!C88 -> 1.2328417e+09 | R18: =(Q18/P18-1)*100 -> 1.0000242 | S18: - | T18: - | U18: - | V18: - | W18: =IF(D18<>0,((D18-$C18)/ABS($C18)) / ($Q18/$P18-1),0) -> 3.8279643 | X18: =IF(E18<>0,((E18-$C18)/ABS($C18)) / ($Q18/$P18-1),0) -> 1.0010481 | Y18: =IF(F18<>0,MAX(((F18-$C18)/ABS($C18)) / ($Q18/$P18-1),0),0) -> 1.0034901 | Z18: =IF(G18<>0,MAX(((G18-$C18)/ABS($C18)) / ($Q18/$P18-1),0),0) -> 1.0010481 | AA18: =IF(H18<>0,MAX(((H18-$C18)/ABS($C18)) / ($Q18/$P18-1),0),0) -> 1.0010481 | AB18: =IF(I18<>0,MAX(((I18-$C18)/ABS($C18)) / ($Q18/$P18-1),0),AA18) -> 1.0010481 | AC18: =IF(J18<>0,MAX(((J18-$C18)/ABS($C18)) / ($Q18/$P18-1),0),AB18) -> 1.0010481 | AD18: - | AE18: - | AF18: - | AG18: - | AH18: =MIN(W18,1) -> 1 | AI18: =IF(W18>1,MAX(W18-SUM(AH18,AJ18:AO18),0),0) -> 0.0010481417 | AJ18: =IF(W18>1,MIN($W18-Y18,W18-AH18),0) -> 2.8244742 | AK18: =IF(W18>1,MAX(MIN(Y18-Z18,W18-AH18-AJ18),0),0) -> 0.0024419308 | AL18: =IF(W18>1,MAX(MIN(Z18-AA18,W18-AH18-AJ18-AK18),0),0) -> 0 | AM18: =IF(I18<>0,IF(W18>1,MAX(MIN(AA18-AB18,W18-AH18-AJ18-AK18-AL18),0),0),0) -> 0 | AN18: =IF(J18<>0,IF(W18>1,MAX(MIN(AB18-AC18,W18-AH18-AJ18-AK18-AL18-AM18),0),0),0) -> 0 | AO18: =IF(W18>1,MAX(0,MIN(W18-AH18-AJ18-AK18-AL18-AM18,W18-AH18-AJ18-AK18-AL18-AM18-X18+1)),0) -> 2.220446e-16 | AP18: =AI18+AO18 -> 0.0010481417 | AQ18: - | AR18: =AI18/($W18-1)*100 -> 0.03706347 | AS18: =AJ18/($W18-1)*100 -> 99.876587 | AT18: =AK18/($W18-1)*100 -> 0.08634942 | AU18: =AL18/($W18-1)*100 -> 0 | AV18: =AM18/($W18-1)*100 -> 0 | AW18: =AN18/($W18-1)*100 -> 0 | AX18: =AO18/($W18-1)*100 -> 7.8517471e-15 | AY18: =AP18/($W18-1)*100 -> 0.03706347 | AZ18: - | BA18: - | BB18: - | BC18: - | BD18: - | BE18: - | BF18: - | BG18: - | BH18: ='[13]2. Distributional by deciles o'!B106 -> 9.7386977e+08 | BI18: ='[13]2. Distributional by deciles o'!B124 -> 1.123809e+08 | BJ18: ='[13]2. Distributional by deciles o'!B142 -> 1.1823111e+08 | BK18: ='[13]2. Distributional by deciles o'!B160 -> 16153318 | BL18: =BH18/SUM($BH18:$BK18) -> 0.79783858 | BM18: =BI18/SUM($BH18:$BK18) -> 0.092067561 | BN18: =BJ18/SUM($BH18:$BK18) -> 0.096860321 | BO18: =BK18/SUM($BH18:$BK18) -> 0.013233536 | BP18: - | BQ18: - | BR18: - | BS18: =P18/P$22*100 -> 10.298761 | CC18: - | CD18: - | CE18: - | CF18: - | CG18: - | CH18: - | CI18: - | CK18: - | CL18: - | CM18: - | CN18: - | CO18: - | CP18: - | CQ18: - | CS18: - | CT18: - | CU18: - | CV18: - | CW18: - | CX18: - | CY18: - | DA18: - | DB18: - | DC18: - | DD18: =(1-DE18)*100 -> 27.246169 | DE18: ='[13]2. Distributional by deciles o'!H34 -> 0.72753831 | EA18: ='[14]2. Distributional by deciles o'!B70 -> 56865055 | EB18: ='[14]2. Distributional by deciles o'!C70 -> 58860648 | EC18: ='[14]2. Distributional by deciles o'!D70 -> 57435331 | ED18: ='[14]2. Distributional by deciles o'!E70 -> 1995593.4 | EE18: ='[14]2. Distributional by deciles o'!F70 -> 570275.95 | EF18: =EE18 -> 570275.95 | EI18: - | EJ18: - | EK18: - | EL18: - | EM18: =EA18/EA$22*100 -> 5.3552067 | EN18: ='[14]2. Distributional by deciles o'!B88 -> 1.3908588e+09 | EO18: ='[14]2. Distributional by deciles o'!C88 -> 1.4047673e+09 | EP18: =(EO18/EN18-1)*100 -> 0.99999388 | EQ18: - | ER18: - | ES18: - | ET18: - | EU18: =EN18/EN$22*100 -> 10.351118 | EV18: =((EB18-$EA18)/ABS($EA18)) / ($EO18/$EN18-1) -> 3.5093707 | EW18: =IF(EC18<>0,((EC18-$EA18)/ABS($EA18)) / ($EO18/$EN18-1),0) -> 1.0028645 | EY18: =EV18-W18 -> -0.31859358 | EZ18: =(1-FA18)*100 -> -11943 | FA18: ='[14]2. Distributional by deciles o'!H34 -> 120.43 | FB18: - | FC18: - | FD18: - | FE18: - | FF18: - | FG18: - | FH18: - | FI18: -
B19: 8 | C19: ='[13]2. Distributional by deciles o'!B71 -> 72276275 | D19: ='[13]2. Distributional by deciles o'!C71 -> 74638771 | E19: ='[13]2. Distributional by deciles o'!D71 -> 73000432 | F19: ='[13]2. Distributional by deciles o'!E71 -> 73000936 | G19: ='[13]2. Distributional by deciles o'!F71 -> 73000432 | H19: =G19 -> 73000432 | K19: - | L19: - | M19: - | N19: - | O19: =C19/C$22*100 -> 8.8037006 | P19: ='[13]2. Distributional by deciles o'!B89 -> 1.4740019e+09 | Q19: ='[13]2. Distributional by deciles o'!C89 -> 1.4887421e+09 | R19: =(Q19/P19-1)*100 -> 1.0000138 | S19: - | T19: - | U19: - | V19: - | W19: =IF(D19<>0,((D19-$C19)/ABS($C19)) / ($Q19/$P19-1),0) -> 3.2686568 | X19: =IF(E19<>0,((E19-$C19)/ABS($C19)) / ($Q19/$P19-1),0) -> 1.0019162 | Y19: =IF(F19<>0,MAX(((F19-$C19)/ABS($C19)) / ($Q19/$P19-1),0),0) -> 1.0026126 | Z19: =IF(G19<>0,MAX(((G19-$C19)/ABS($C19)) / ($Q19/$P19-1),0),0) -> 1.0019162 | AA19: =IF(H19<>0,MAX(((H19-$C19)/ABS($C19)) / ($Q19/$P19-1),0),0) -> 1.0019162 | AB19: =IF(I19<>0,MAX(((I19-$C19)/ABS($C19)) / ($Q19/$P19-1),0),AA19) -> 1.0019162 | AC19: =IF(J19<>0,MAX(((J19-$C19)/ABS($C19)) / ($Q19/$P19-1),0),AB19) -> 1.0019162 | AD19: - | AE19: - | AF19: - | AG19: - | AH19: =MIN(W19,1) -> 1 | AI19: =IF(W19>1,MAX(W19-SUM(AH19,AJ19:AO19),0),0) -> 0.0019162086 | AJ19: =IF(W19>1,MIN($W19-Y19,W19-AH19),0) -> 2.2660442 | AK19: =IF(W19>1,MAX(MIN(Y19-Z19,W19-AH19-AJ19),0),0) -> 0.00069640484 | AL19: =IF(W19>1,MAX(MIN(Z19-AA19,W19-AH19-AJ19-AK19),0),0) -> 0 | AM19: =IF(I19<>0,IF(W19>1,MAX(MIN(AA19-AB19,W19-AH19-AJ19-AK19-AL19),0),0),0) -> 0 | AN19: =IF(J19<>0,IF(W19>1,MAX(MIN(AB19-AC19,W19-AH19-AJ19-AK19-AL19-AM19),0),0),0) -> 0 | AO19: =IF(W19>1,MAX(0,MIN(W19-AH19-AJ19-AK19-AL19-AM19,W19-AH19-AJ19-AK19-AL19-AM19-X19+1)),0) -> 2.220446e-16 | AP19: =AI19+AO19 -> 0.0019162086 | AQ19: - | AR19: =AI19/($W19-1)*100 -> 0.084464457 | AS19: =AJ19/($W19-1)*100 -> 99.884839 | AT19: =AK19/($W19-1)*100 -> 0.030696792 | AU19: =AL19/($W19-1)*100 -> 0 | AV19: =AM19/($W19-1)*100 -> 0 | AW19: =AN19/($W19-1)*100 -> 0 | AX19: =AO19/($W19-1)*100 -> 9.7874922e-15 | AY19: =AP19/($W19-1)*100 -> 0.084464457 | AZ19: - | BA19: - | BB19: - | BC19: - | BD19: - | BE19: - | BF19: - | BG19: - | BH19: ='[13]2. Distributional by deciles o'!B107 -> 1.1561124e+09 | BI19: ='[13]2. Distributional by deciles o'!B125 -> 1.6291474e+08 | BJ19: ='[13]2. Distributional by deciles o'!B143 -> 1.27582e+08 | BK19: ='[13]2. Distributional by deciles o'!B161 -> 27392861 | BL19: =BH19/SUM($BH19:$BK19) -> 0.7843357 | BM19: =BI19/SUM($BH19:$BK19) -> 0.11052545 | BN19: =BJ19/SUM($BH19:$BK19) -> 0.086554835 | BO19: =BK19/SUM($BH19:$BK19) -> 0.018584006 | BP19: - | BQ19: - | BR19: - | BS19: =P19/P$22*100 -> 12.436471 | CC19: - | CD19: - | CE19: - | CF19: - | CG19: - | CH19: - | CI19: - | CK19: - | CL19: - | CM19: - | CN19: - | CO19: - | CP19: - | CQ19: - | CS19: - | CT19: - | CU19: - | CV19: - | CW19: - | CX19: - | CY19: - | DA19: - | DB19: - | DC19: - | DD19: =(1-DE19)*100 -> 7.5470006 | DE19: ='[13]2. Distributional by deciles o'!H35 -> 0.92452999 | EA19: ='[14]2. Distributional by deciles o'!B71 -> 1.0469203e+08 | EB19: ='[14]2. Distributional by deciles o'!C71 -> 1.0778389e+08 | EC19: ='[14]2. Distributional by deciles o'!D71 -> 1.0574072e+08 | ED19: ='[14]2. Distributional by deciles o'!E71 -> 3091858.7 | EE19: ='[14]2. Distributional by deciles o'!F71 -> 1048692.9 | EF19: =EE19 -> 1048692.9 | EI19: - | EJ19: - | EK19: - | EL19: - | EM19: =EA19/EA$22*100 -> 9.8592616 | EN19: ='[14]2. Distributional by deciles o'!B89 -> 1.678767e+09 | EO19: ='[14]2. Distributional by deciles o'!C89 -> 1.6955547e+09 | EP19: =(EO19/EN19-1)*100 -> 0.99999766 | EQ19: - | ER19: - | ES19: - | ET19: - | EU19: =EN19/EN$22*100 -> 12.493803 | EV19: =((EB19-$EA19)/ABS($EA19)) / ($EO19/$EN19-1) -> 2.9532964 | EW19: =IF(EC19<>0,((EC19-$EA19)/ABS($EA19)) / ($EO19/$EN19-1),0) -> 1.0016956 | EY19: =EV19-W19 -> -0.31536034 | EZ19: =(1-FA19)*100 -> -3408 | FA19: ='[14]2. Distributional by deciles o'!H35 -> 35.08 | FB19: - | FC19: - | FD19: - | FE19: - | FF19: - | FG19: - | FH19: - | FI19: -
B20: 9 | C20: ='[13]2. Distributional by deciles o'!B72 -> 1.4815838e+08 | D20: ='[13]2. Distributional by deciles o'!C72 -> 1.5213839e+08 | E20: ='[13]2. Distributional by deciles o'!D72 -> 1.4964087e+08 | F20: ='[13]2. Distributional by deciles o'!E72 -> 1.4964384e+08 | G20: ='[13]2. Distributional by deciles o'!F72 -> 1.4964087e+08 | H20: =G20 -> 1.4964087e+08 | K20: - | L20: - | M20: - | N20: - | O20: =C20/C$22*100 -> 18.046614 | P20: ='[13]2. Distributional by deciles o'!B90 -> 1.9361845e+09 | Q20: ='[13]2. Distributional by deciles o'!C90 -> 1.9555465e+09 | R20: =(Q20/P20-1)*100 -> 1.0000086 | S20: - | T20: - | U20: - | V20: - | W20: =IF(D20<>0,((D20-$C20)/ABS($C20)) / ($Q20/$P20-1),0) -> 2.6862996 | X20: =IF(E20<>0,((E20-$C20)/ABS($C20)) / ($Q20/$P20-1),0) -> 1.0006036 | Y20: =IF(F20<>0,MAX(((F20-$C20)/ABS($C20)) / ($Q20/$P20-1),0),0) -> 1.0026085 | Z20: =IF(G20<>0,MAX(((G20-$C20)/ABS($C20)) / ($Q20/$P20-1),0),0) -> 1.0006036 | AA20: =IF(H20<>0,MAX(((H20-$C20)/ABS($C20)) / ($Q20/$P20-1),0),0) -> 1.0006036 | AB20: =IF(I20<>0,MAX(((I20-$C20)/ABS($C20)) / ($Q20/$P20-1),0),AA20) -> 1.0006036 | AC20: =IF(J20<>0,MAX(((J20-$C20)/ABS($C20)) / ($Q20/$P20-1),0),AB20) -> 1.0006036 | AD20: - | AE20: - | AF20: - | AG20: - | AH20: =MIN(W20,1) -> 1 | AI20: =IF(W20>1,MAX(W20-SUM(AH20,AJ20:AO20),0),0) -> 0.00060361056 | AJ20: =IF(W20>1,MIN($W20-Y20,W20-AH20),0) -> 1.6836911 | AK20: =IF(W20>1,MAX(MIN(Y20-Z20,W20-AH20-AJ20),0),0) -> 0.0020048754 | AL20: =IF(W20>1,MAX(MIN(Z20-AA20,W20-AH20-AJ20-AK20),0),0) -> 0 | AM20: =IF(I20<>0,IF(W20>1,MAX(MIN(AA20-AB20,W20-AH20-AJ20-AK20-AL20),0),0),0) -> 0 | AN20: =IF(J20<>0,IF(W20>1,MAX(MIN(AB20-AC20,W20-AH20-AJ20-AK20-AL20-AM20),0),0),0) -> 0 | AO20: =IF(W20>1,MAX(0,MIN(W20-AH20-AJ20-AK20-AL20-AM20,W20-AH20-AJ20-AK20-AL20-AM20-X20+1)),0) -> 0 | AP20: =AI20+AO20 -> 0.00060361056 | AQ20: - | AR20: =AI20/($W20-1)*100 -> 0.035794977 | AS20: =AJ20/($W20-1)*100 -> 99.845313 | AT20: =AK20/($W20-1)*100 -> 0.11889201 | AU20: =AL20/($W20-1)*100 -> 0 | AV20: =AM20/($W20-1)*100 -> 0 | AW20: =AN20/($W20-1)*100 -> 0 | AX20: =AO20/($W20-1)*100 -> 0 | AY20: =AP20/($W20-1)*100 -> 0.035794977 | AZ20: - | BA20: - | BB20: - | BC20: - | BD20: - | BE20: - | BF20: - | BG20: - | BH20: ='[13]2. Distributional by deciles o'!B108 -> 1.4823966e+09 | BI20: ='[13]2. Distributional by deciles o'!B126 -> 2.8792767e+08 | BJ20: ='[13]2. Distributional by deciles o'!B144 -> 1.312202e+08 | BK20: ='[13]2. Distributional by deciles o'!B162 -> 34640103 | BL20: =BH20/SUM($BH20:$BK20) -> 0.76562773 | BM20: =BI20/SUM($BH20:$BK20) -> 0.14870879 | BN20: =BJ20/SUM($BH20:$BK20) -> 0.067772568 | BO20: =BK20/SUM($BH20:$BK20) -> 0.01789091 | BP20: - | BQ20: - | BR20: - | BS20: =P20/P$22*100 -> 16.336005 | CC20: - | CD20: - | CE20: - | CF20: - | CG20: - | CH20: - | CI20: - | CK20: - | CL20: - | CM20: - | CN20: - | CO20: - | CP20: - | CQ20: - | CS20: - | CT20: - | CU20: - | CV20: - | CW20: - | CX20: - | CY20: - | DA20: - | DB20: - | DC20: - | DD20: =(1-DE20)*100 -> 0 | DE20: ='[13]2. Distributional by deciles o'!H36 -> 1 | EA20: ='[14]2. Distributional by deciles o'!B72 -> 1.973999e+08 | EB20: ='[14]2. Distributional by deciles o'!C72 -> 2.0228263e+08 | EC20: ='[14]2. Distributional by deciles o'!D72 -> 1.9937612e+08 | ED20: ='[14]2. Distributional by deciles o'!E72 -> 4882733.8 | EE20: ='[14]2. Distributional by deciles o'!F72 -> 1976217 | EF20: =EE20 -> 1976217 | EI20: - | EJ20: - | EK20: - | EL20: - | EM20: =EA20/EA$22*100 -> 18.589928 | EN20: ='[14]2. Distributional by deciles o'!B90 -> 2.2017926e+09 | EO20: ='[14]2. Distributional by deciles o'!C90 -> 2.2238106e+09 | EP20: =(EO20/EN20-1)*100 -> 1.0000014 | EQ20: - | ER20: - | ES20: - | ET20: - | EU20: =EN20/EN$22*100 -> 16.38629 | EV20: =((EB20-$EA20)/ABS($EA20)) / ($EO20/$EN20-1) -> 2.4735205 | EW20: =IF(EC20<>0,((EC20-$EA20)/ABS($EA20)) / ($EO20/$EN20-1),0) -> 1.0011222 | EY20: =EV20-W20 -> -0.21277915 | EZ20: =(1-FA20)*100 -> 100 | FA20: ='[14]2. Distributional by deciles o'!H36 -> 0 | FB20: - | FC20: - | FD20: - | FE20: - | FF20: - | FG20: - | FH20: - | FI20: -
B21: 10 | C21: ='[13]2. Distributional by deciles o'!B73 -> 5.3080515e+08 | D21: ='[13]2. Distributional by deciles o'!C73 -> 5.4020257e+08 | E21: ='[13]2. Distributional by deciles o'!D73 -> 5.3612656e+08 | F21: ='[13]2. Distributional by deciles o'!E73 -> 5.3614339e+08 | G21: ='[13]2. Distributional by deciles o'!F73 -> 5.3612656e+08 | H21: =G21 -> 5.3612656e+08 | K21: - | L21: - | M21: - | N21: - | O21: =C21/C$22*100 -> 64.655375 | P21: ='[13]2. Distributional by deciles o'!B91 -> 3.3377835e+09 | Q21: ='[13]2. Distributional by deciles o'!C91 -> 3.3711614e+09 | R21: =(Q21/P21-1)*100 -> 1.0000044 | S21: - | T21: - | U21: - | V21: - | W21: =IF(D21<>0,((D21-$C21)/ABS($C21)) / ($Q21/$P21-1),0) -> 1.7703998 | X21: =IF(E21<>0,((E21-$C21)/ABS($C21)) / ($Q21/$P21-1),0) -> 1.0025126 | Y21: =IF(F21<>0,MAX(((F21-$C21)/ABS($C21)) / ($Q21/$P21-1),0),0) -> 1.0056822 | Z21: =IF(G21<>0,MAX(((G21-$C21)/ABS($C21)) / ($Q21/$P21-1),0),0) -> 1.0025126 | AA21: =IF(H21<>0,MAX(((H21-$C21)/ABS($C21)) / ($Q21/$P21-1),0),0) -> 1.0025126 | AB21: =IF(I21<>0,MAX(((I21-$C21)/ABS($C21)) / ($Q21/$P21-1),0),AA21) -> 1.0025126 | AC21: =IF(J21<>0,MAX(((J21-$C21)/ABS($C21)) / ($Q21/$P21-1),0),AB21) -> 1.0025126 | AD21: - | AE21: - | AF21: - | AG21: - | AH21: =MIN(W21,1) -> 1 | AI21: =IF(W21>1,MAX(W21-SUM(AH21,AJ21:AO21),0),0) -> 0.0025125908 | AJ21: =IF(W21>1,MIN($W21-Y21,W21-AH21),0) -> 0.76471762 | AK21: =IF(W21>1,MAX(MIN(Y21-Z21,W21-AH21-AJ21),0),0) -> 0.0031696193 | AL21: =IF(W21>1,MAX(MIN(Z21-AA21,W21-AH21-AJ21-AK21),0),0) -> 0 | AM21: =IF(I21<>0,IF(W21>1,MAX(MIN(AA21-AB21,W21-AH21-AJ21-AK21-AL21),0),0),0) -> 0 | AN21: =IF(J21<>0,IF(W21>1,MAX(MIN(AB21-AC21,W21-AH21-AJ21-AK21-AL21-AM21),0),0),0) -> 0 | AO21: =IF(W21>1,MAX(0,MIN(W21-AH21-AJ21-AK21-AL21-AM21,W21-AH21-AJ21-AK21-AL21-AM21-X21+1)),0) -> 0 | AP21: =AI21+AO21 -> 0.0025125908 | AQ21: - | AR21: =AI21/($W21-1)*100 -> 0.32614114 | AS21: =AJ21/($W21-1)*100 -> 99.262434 | AT21: =AK21/($W21-1)*100 -> 0.41142524 | AU21: =AL21/($W21-1)*100 -> 0 | AV21: =AM21/($W21-1)*100 -> 0 | AW21: =AN21/($W21-1)*100 -> 0 | AX21: =AO21/($W21-1)*100 -> 0 | AY21: =AP21/($W21-1)*100 -> 0.32614114 | AZ21: - | BA21: - | BB21: - | BC21: - | BD21: - | BE21: - | BF21: - | BG21: - | BH21: ='[13]2. Distributional by deciles o'!B109 -> 2.4686225e+09 | BI21: ='[13]2. Distributional by deciles o'!B127 -> 5.8141346e+08 | BJ21: ='[13]2. Distributional by deciles o'!B145 -> 1.9181433e+08 | BK21: ='[13]2. Distributional by deciles o'!B163 -> 95933096 | BL21: =BH21/SUM($BH21:$BK21) -> 0.73959938 | BM21: =BI21/SUM($BH21:$BK21) -> 0.17419149 | BN21: =BJ21/SUM($BH21:$BK21) -> 0.057467579 | BO21: =BK21/SUM($BH21:$BK21) -> 0.028741558 | BP21: - | BQ21: - | BR21: - | BS21: =P21/P$22*100 -> 28.161596 | CC21: - | CD21: - | CE21: - | CF21: - | CG21: - | CH21: - | CI21: - | CK21: - | CL21: - | CM21: - | CN21: - | CO21: - | CP21: - | CQ21: - | CS21: - | CT21: - | CU21: - | CV21: - | CW21: - | CX21: - | CY21: - | DA21: - | DB21: - | DC21: - | DD21: =(1-DE21)*100 -> 0 | DE21: ='[13]2. Distributional by deciles o'!H37 -> 1 | EA21: ='[14]2. Distributional by deciles o'!B73 -> 6.4529151e+08 | EB21: ='[14]2. Distributional by deciles o'!C73 -> 6.5617129e+08 | EC21: ='[14]2. Distributional by deciles o'!D73 -> 6.5177322e+08 | ED21: ='[14]2. Distributional by deciles o'!E73 -> 10879778 | EE21: ='[14]2. Distributional by deciles o'!F73 -> 6481712.7 | EF21: =EE21 -> 6481712.7 | EI21: - | EJ21: - | EK21: - | EL21: - | EM21: =EA21/EA$22*100 -> 60.769649 | EN21: ='[14]2. Distributional by deciles o'!B91 -> 3.7696706e+09 | EO21: ='[14]2. Distributional by deciles o'!C91 -> 3.8073677e+09 | EP21: =(EO21/EN21-1)*100 -> 1.00001 | EQ21: - | ER21: - | ES21: - | ET21: - | EU21: =EN21/EN$22*100 -> 28.05483 | EV21: =((EB21-$EA21)/ABS($EA21)) / ($EO21/$EN21-1) -> 1.6860085 | EW21: =IF(EC21<>0,((EC21-$EA21)/ABS($EA21)) / ($EO21/$EN21-1),0) -> 1.0044527 | EY21: =EV21-W21 -> -0.084391359 | EZ21: =(1-FA21)*100 -> 100 | FA21: ='[14]2. Distributional by deciles o'!H37 -> 0 | FB21: - | FC21: - | FD21: - | FE21: - | FF21: - | FG21: - | FH21: - | FI21: -
B22: Total | C22: ='[13]2. Distributional by deciles o'!B74 -> 8.2097607e+08 | D22: ='[13]2. Distributional by deciles o'!C74 -> 8.3984301e+08 | E22: ='[13]2. Distributional by deciles o'!D74 -> 8.2920222e+08 | F22: ='[13]2. Distributional by deciles o'!E74 -> 8.2922386e+08 | G22: ='[13]2. Distributional by deciles o'!F74 -> 8.2920222e+08 | H22: =G22 -> 8.2920222e+08 | K22: ='[15]1. Fiscal'!D11 -> 8.3513885e+08 | L22: ='[15]1. Fiscal'!E11 -> 8.2402002e+08 | M22: ='[15]1. Fiscal'!F11 -> 8.220312e+08 | N22: ='[15]1. Fiscal'!G11 -> 8.21299e+08 | O22: - | P22: ='[13]2. Distributional by deciles o'!B92 -> 1.1852252e+10 | Q22: ='[13]2. Distributional by deciles o'!C92 -> 1.1970777e+10 | R22: =(Q22/P22-1)*100 -> 1.0000211 | S22: ='[15]1. Fiscal'!D134 -> 1.1939806e+10 | T22: ='[15]1. Fiscal'!E134 -> 1.1870776e+10 | U22: ='[15]1. Fiscal'!F134 -> 1.1862378e+10 | V22: ='[15]1. Fiscal'!G134 -> 1.1854575e+10 | W22: =IF(D22<>0,((D22-$C22)/ABS($C22)) / ($Q22/$P22-1),0) -> 2.2980633 | X22: =IF(E22<>0,((E22-$C22)/ABS($C22)) / ($Q22/$P22-1),0) -> 1.0019759 | Y22: =IF(F22<>0,MAX(((F22-$C22)/ABS($C22)) / ($Q22/$P22-1),0),0) -> 1.004612 | Z22: =IF(G22<>0,MAX(((G22-$C22)/ABS($C22)) / ($Q22/$P22-1),0),0) -> 1.0019759 | AA22: =IF(H22<>0,MAX(((H22-$C22)/ABS($C22)) / ($Q22/$P22-1),0),0) -> 1.0019759 | AB22: =IF(I22<>0,MAX(((I22-$C22)/ABS($C22)) / ($Q22/$P22-1),0),AA22) -> 1.0019759 | AC22: =IF(J22<>0,MAX(((J22-$C22)/ABS($C22)) / ($Q22/$P22-1),0),AB22) -> 1.0019759 | AD22: =(K22/$C22-1) / (S22/$P22-1) -> 2.3353021 | AE22: =(L22/$C22-1) / (T22/$P22-1) -> 2.3723707 | AF22: =(M22/$C22-1) / (U22/$P22-1) -> 1.5044129 | AG22: =(N22/$C22-1) / (V22/$P22-1) -> 2.0075493 | AH22: =MIN(W22,1) -> 1 | AI22: =IF(W22>1,MAX(W22-SUM(AH22,AJ22:AO22),0),0) -> 0.0019759073 | AJ22: =IF(W22>1,MIN($W22-Y22,W22-AH22),0) -> 1.2934514 | AK22: =IF(W22>1,MAX(MIN(Y22-Z22,W22-AH22-AJ22),0),0) -> 0.0026360747 | AL22: =IF(W22>1,MAX(MIN(Z22-AA22,W22-AH22-AJ22-AK22),0),0) -> 0 | AM22: =IF(I22<>0,IF(W22>1,MAX(MIN(AA22-AB22,W22-AH22-AJ22-AK22-AL22),0),0),0) -> 0 | AN22: =IF(J22<>0,IF(W22>1,MAX(MIN(AB22-AC22,W22-AH22-AJ22-AK22-AL22-AM22),0),0),0) -> 0 | AO22: =IF(W22>1,MAX(0,MIN(W22-AH22-AJ22-AK22-AL22-AM22,W22-AH22-AJ22-AK22-AL22-AM22-X22+1)),0) -> 0 | AP22: =AI22+AO22 -> 0.0019759073 | AQ22: - | AR22: =AI22/($W22-1)*100 -> 0.15221964 | AS22: =AJ22/($W22-1)*100 -> 99.644703 | AT22: =AK22/($W22-1)*100 -> 0.20307751 | AU22: =AL22/($W22-1)*100 -> 0 | AV22: =AM22/($W22-1)*100 -> 0 | AW22: =AN22/($W22-1)*100 -> 0 | AX22: =AO22/($W22-1)*100 -> 0 | AY22: =AP22/($W22-1)*100 -> 0.15221964 | AZ22: =W22 -> 2.2980633 | BA22: =AD22 -> 2.3353021 | BB22: =AF22 -> 1.5044129 | BC22: =AG22 -> 2.0075493 | BD22: =W22-AZ22 -> 0 | BE22: =AD22-BA22 -> 0 | BF22: =AF22-BB22 -> 0 | BG22: =AG22-BC22 -> 0 | BH22: ='[13]2. Distributional by deciles o'!B110 -> 8.7552826e+09 | BI22: ='[13]2. Distributional by deciles o'!B128 -> 1.8522687e+09 | BJ22: ='[13]2. Distributional by deciles o'!B146 -> 1.012483e+09 | BK22: ='[13]2. Distributional by deciles o'!B164 -> 2.3221826e+08 | BL22: =BH22/SUM($BH22:$BK22) -> 0.73870199 | BM22: =BI22/SUM($BH22:$BK22) -> 0.15627989 | BN22: =BJ22/SUM($BH22:$BK22) -> 0.085425365 | BO22: =BK22/SUM($BH22:$BK22) -> 0.019592753 | BP22: =(AD22*BL22+AF22*BN22+AG22*BO22)/(BL22+BN22+BO22) -> 2.2435648 | BQ22: =W22-BP22 -> 0.05449852 | BR22: =BP22-AZ22 -> -0.05449852 | BS22: - | CK22: ='[13]3. Inequality and Poverty'!$B$7 -> 0.38361613 | CL22: ='[13]3. Inequality and Poverty'!$B$8 -> 0.35429544 | CM22: ='[13]3. Inequality and Poverty'!$C$7 -> 0.38361605 | CN22: ='[13]3. Inequality and Poverty'!$C$8 -> 0.35406859 | CO22: =(CK22-CL22)/CK22 -> 0.076432384 | CP22: =(CM22-CN22)/CM22 -> 0.077023512 | CQ22: =(CP22-CO22)*100 -> 0.059112818 | CR22: =CN22-CL22 -> -0.00022684793 | CS22: =(SUM(P20:P21))/(SUM(P12:P13)) -> 8.6762782 | CT22: =(SUM(P20:P21)-SUM(C20:C21))/(SUM(P12:P13)-SUM(C12:C13)) -> 7.5614402 | CU22: =(SUM(Q20:Q21))/(SUM(Q12:Q13)) -> 8.676274 | CV22: =(SUM(Q20:Q21)-SUM(D20:D21))/(SUM(Q12:Q13)-SUM(D12:D13)) -> 7.5508969 | CW22: =(CS22-CT22)/CS22 -> 0.12849265 | CX22: =(CU22-CV22)/CU22 -> 0.12970742 | CY22: =(CX22-CW22)*100 -> 0.12147677 | CZ22: =CV22-CT22 -> -0.010543271 | DA22: ='[13]3. Inequality and Poverty'!$B$34 -> 0.39873029 | DB22: ='[13]3. Inequality and Poverty'!$C$34 -> 0.39638893 | DC22: =DB22-DA22 -> -0.0023413656 | DD22: =(1-DE22)*100 -> 54.508321 | DE22: ='[13]2. Distributional by deciles o'!H38 -> 0.45491679 | EA22: ='[14]2. Distributional by deciles o'!B74 -> 1.0618648e+09 | EB22: ='[14]2. Distributional by deciles o'!C74 -> 1.0853369e+09 | EC22: ='[14]2. Distributional by deciles o'!D74 -> 1.0725188e+09 | ED22: ='[14]2. Distributional by deciles o'!E74 -> 23472083 | EE22: ='[14]2. Distributional by deciles o'!F74 -> 10654046 | EF22: =EE22 -> 10654046 | EI22: ='[16]1. Fiscal'!D11 -> 1.0796944e+09 | EJ22: ='[16]1. Fiscal'!E11 -> 1.0653957e+09 | EK22: ='[16]1. Fiscal'!F11 -> 1.063222e+09 | EL22: ='[16]1. Fiscal'!G11 -> 1.0622578e+09 | EM22: - | EN22: ='[14]2. Distributional by deciles o'!B92 -> 1.3436797e+10 | EO22: ='[14]2. Distributional by deciles o'!C92 -> 1.3571166e+10 | EP22: =(EO22/EN22-1)*100 -> 1.0000074 | EQ22: ='[16]1. Fiscal'!D138 -> 1.3536618e+10 | ER22: ='[16]1. Fiscal'!E138 -> 1.3457163e+10 | ES22: ='[16]1. Fiscal'!F138 -> 1.3448341e+10 | ET22: ='[16]1. Fiscal'!G138 -> 1.3439436e+10 | EU22: - | EV22: =((EB22-$EA22)/ABS($EA22)) / ($EO22/$EN22-1) -> 2.2104424 | EW22: =IF(EC22<>0,((EC22-$EA22)/ABS($EA22)) / ($EO22/$EN22-1),0) -> 1.0033262 | EX22: =EW22-X22 -> 0.0013502514 | EY22: =EV22-W22 -> -0.087620947 | EZ22: =(1-FA22)*100 -> -180371 | FA22: ='[14]2. Distributional by deciles o'!H38 -> 1804.71 | FB22: =(EI22/$EA22-1) / (EQ22/$EN22-1) -> 2.2602179 | FC22: =(EJ22/$EA22-1) / (ER22/$EN22-1) -> 2.1938826 | FD22: =(EK22/$EA22-1) / (ES22/$EN22-1) -> 1.4877641 | FE22: =(EL22/$EA22-1) / (ET22/$EN22-1) -> 1.8842268 | FF22: =FB22-AD22 -> -0.075084206 | FG22: =FC22-AE22 -> -0.17848802 | FH22: =FD22-AF22 -> -0.016648738 | FI22: =FE22-AG22 -> -0.12332253

Sheet 2CY
B2: Template corresponding to Part 2 of the project Fiscal Drag in Europe.
B3: Yellow cells have to be filled by you
B4: Remaing cells are automatically calculated using information from yellow cells (grey cells remain empty)
B5: Red cells are 2026 results that can be filled with fake/provisional results. When we fill them with final results (the plan is to use Dec BMPE data) turn them yellow.
B8: Country | C8: CY | D8: Cyrprus | E8: Updated: 13/02/2025
E9: K50
C10: Personal Income Tax Revenue | E10: K50 | P10: Tax Base (il_fiscaldrag_all) | AM10: Sensitivity test
B11: Decile | C11: 2019_baseline | D11: 2020_baseline | E11: 2021_baseline | F11: 2022_baseline | G11: 2023_baseline | H11: 2023 if 2019legis unchanged (upper bound) | I11: 2023 if 2019legis indexed with tax base growth (lower bound a) | J11: 2023 if 2019legis indexed with lagged HCPI (lower bound b) | K11: 2023 if 2019legis indexed with concurrent HCPI (lower bound c) | P11: 2019_baseline | Q11: 2020_baseline | R11: 2021_baseline | S11: 2022_baseline | T11: 2023_baseline | U11: Growth rate 2023/2019 | AK11: 2023_baseline without indexation measures | AM11: TBB elasticity | AN11: 2023_newbaseline | AO11: 2023_homogeneous | AP11: 2023_heterogeneous | AQ11: initial growth | AR11: adjusted growth | AS11: weight
B12: 1 | C12: ='[17]2. Distributional by deciles o'!B64 -> 0 | D12: ='[17]2. Distributional by deciles o'!C64 -> 0 | E12: ='[17]2. Distributional by deciles o'!D64 -> 0 | F12: ='[17]2. Distributional by deciles o'!E64 -> 0 | G12: ='[17]2. Distributional by deciles o'!F64 -> 0 | H12: ='[17]2. Distributional by deciles o'!H64 -> 0 | I12: ='[17]2. Distributional by deciles o'!I64 -> 0 | J12: ='[17]2. Distributional by deciles o'!J64 -> 0 | K12: ='[17]2. Distributional by deciles o'!K64 -> 0 | L12: =G12*(1+0.1+0.085) -> 0 | M12: =$G12*(1+0.1+0) -> 0 | N12: =$G12*(1+0.1+0) -> 0 | O12: =$G12*(1+0.1+0) -> 0 | P12: ='[17]2. Distributional by deciles o'!B82 -> 1.588347e+08 | Q12: ='[17]2. Distributional by deciles o'!C82 -> 1.5855851e+08 | R12: ='[17]2. Distributional by deciles o'!D82 -> 1.6494837e+08 | S12: ='[17]2. Distributional by deciles o'!E82 -> 1.6987383e+08 | T12: ='[17]2. Distributional by deciles o'!F82 -> 1.788359e+08 | U12: =T12/P12-1 -> 0.12592464 | V12: =T12*1.1 -> 1.9671949e+08 | AK12: ='[17]2. Distributional by deciles o'!$L64 -> 0 | AM12: {=INDIRECT("'1"&$C$8&"'!W12")} -> 0 | AN12: =C12+C12*U12*AM12 -> 0 | AO12: =C12+C12*U$22*AM12 -> 0 | AP12: =C12+C12*AR12*AM12 -> 0 | AQ12: =U12 -> 0.12592464 | AR12: =AQ12 -> 0.12592464 | AS12: =P12/P$22 -> 0.013401225
B13: 2 | C13: ='[17]2. Distributional by deciles o'!B65 -> 171581.1 | D13: ='[17]2. Distributional by deciles o'!C65 -> 150648.19 | E13: ='[17]2. Distributional by deciles o'!D65 -> 214135.14 | F13: ='[17]2. Distributional by deciles o'!E65 -> 296652.96 | G13: ='[17]2. Distributional by deciles o'!F65 -> 535115.01 | H13: ='[17]2. Distributional by deciles o'!H65 -> 595333.97 | I13: ='[17]2. Distributional by deciles o'!I65 -> 200614.56 | J13: ='[17]2. Distributional by deciles o'!J65 -> 274665.51 | K13: ='[17]2. Distributional by deciles o'!K65 -> 205397.6 | L13: =G13*(1+0.1+0.085) -> 634111.29 | M13: =$G13*(1+0.1+0) -> 588626.51 | N13: =$G13*(1+0.1+0) -> 588626.51 | O13: =$G13*(1+0.1+0) -> 588626.51 | P13: ='[17]2. Distributional by deciles o'!B83 -> 4.4902594e+08 | Q13: ='[17]2. Distributional by deciles o'!C83 -> 4.4858087e+08 | R13: ='[17]2. Distributional by deciles o'!D83 -> 4.6709328e+08 | S13: ='[17]2. Distributional by deciles o'!E83 -> 4.7998373e+08 | T13: ='[17]2. Distributional by deciles o'!F83 -> 5.044553e+08 | U13: =T13/P13-1 -> 0.12344357 | V13: =T13*1.1 -> 5.5490083e+08 | AK13: ='[17]2. Distributional by deciles o'!$L65 -> 535115.01 | AM13: {=INDIRECT("'1"&$C$8&"'!W13")} -> 10.173885 | AN13: =C13+C13*U13*AM13 -> 387069.93 | AO13: =C13+C13*U$22*AM13 -> 404959.12 | AP13: =C13+C13*AR13*AM13 -> 387069.93 | AQ13: =U13 -> 0.12344357 | AR13: =AQ13 -> 0.12344357 | AS13: =P13/P$22 -> 0.037885283
B14: 3 | C14: ='[17]2. Distributional by deciles o'!B66 -> 1444605.3 | D14: ='[17]2. Distributional by deciles o'!C66 -> 1261747.7 | E14: ='[17]2. Distributional by deciles o'!D66 -> 1768850 | F14: ='[17]2. Distributional by deciles o'!E66 -> 2434274.9 | G14: ='[17]2. Distributional by deciles o'!F66 -> 3716031.7 | H14: ='[17]2. Distributional by deciles o'!H66 -> 4069295.3 | I14: ='[17]2. Distributional by deciles o'!I66 -> 1802023.5 | J14: ='[17]2. Distributional by deciles o'!J66 -> 2429316.6 | K14: ='[17]2. Distributional by deciles o'!K66 -> 1844984.5 | L14: =G14*(1+0.1+0.085) -> 4403497.6 | M14: =$G14*(1+0.1+0) -> 4087634.9 | N14: =$G14*(1+0.1+0) -> 4087634.9 | O14: =$G14*(1+0.1+0) -> 4087634.9 | P14: ='[17]2. Distributional by deciles o'!B84 -> 5.8310511e+08 | Q14: ='[17]2. Distributional by deciles o'!C84 -> 5.8165985e+08 | R14: ='[17]2. Distributional by deciles o'!D84 -> 6.0494435e+08 | S14: ='[17]2. Distributional by deciles o'!E84 -> 6.2417391e+08 | T14: ='[17]2. Distributional by deciles o'!F84 -> 6.588994e+08 | U14: =T14/P14-1 -> 0.12998393 | V14: =T14*1.1 -> 7.2478934e+08 | AK14: ='[17]2. Distributional by deciles o'!$L66 -> 3716031.7 | AM14: {=INDIRECT("'1"&$C$8&"'!W14")} -> 10.642337 | AN14: =C14+C14*U14*AM14 -> 3442975.1 | AO14: =C14+C14*U$22*AM14 -> 3499974.6 | AP14: =C14+C14*AR14*AM14 -> 3442975.1 | AQ14: =U14 -> 0.12998393 | AR14: =AQ14 -> 0.12998393 | AS14: =P14/P$22 -> 0.049197831
B15: 4 | C15: ='[17]2. Distributional by deciles o'!B67 -> 4897896.6 | D15: ='[17]2. Distributional by deciles o'!C67 -> 4493705.4 | E15: ='[17]2. Distributional by deciles o'!D67 -> 5587530 | F15: ='[17]2. Distributional by deciles o'!E67 -> 6757023.3 | G15: ='[17]2. Distributional by deciles o'!F67 -> 9175250.7 | H15: ='[17]2. Distributional by deciles o'!H67 -> 9735197.1 | I15: ='[17]2. Distributional by deciles o'!I67 -> 5679611.4 | J15: ='[17]2. Distributional by deciles o'!J67 -> 6761074.7 | K15: ='[17]2. Distributional by deciles o'!K67 -> 5754647 | L15: =G15*(1+0.1+0.085) -> 10872672 | M15: =$G15*(1+0.1+0) -> 10092776 | N15: =$G15*(1+0.1+0) -> 10092776 | O15: =$G15*(1+0.1+0) -> 10092776 | P15: ='[17]2. Distributional by deciles o'!B85 -> 7.5151917e+08 | Q15: ='[17]2. Distributional by deciles o'!C85 -> 7.4909834e+08 | R15: ='[17]2. Distributional by deciles o'!D85 -> 7.7859548e+08 | S15: ='[17]2. Distributional by deciles o'!E85 -> 8.0532794e+08 | T15: ='[17]2. Distributional by deciles o'!F85 -> 8.5175972e+08 | U15: =T15/P15-1 -> 0.13338389 | V15: =T15*1.1 -> 9.3693569e+08 | AK15: ='[17]2. Distributional by deciles o'!$L67 -> 9175250.7 | AM15: {=INDIRECT("'1"&$C$8&"'!W15")} -> 5.8958205 | AN15: =C15+C15*U15*AM15 -> 8749639 | AO15: =C15+C15*U$22*AM15 -> 8758520.8 | AP15: =C15+C15*AR15*AM15 -> 8749639 | AQ15: =U15 -> 0.13338389 | AR15: =AQ15 -> 0.13338389 | AS15: =P15/P$22 -> 0.063407287
